Workbook
Name \A: #REF!
Name \M: #REF!
Name ___ATS98: #REF!
Name ___BGT02: [1]Budget!$A$1:$IV$65536
Name ___CHF98: #REF!
Name ___CHX2002: [2]Zellennamen!#REF!
Name ___CHX2003: [2]Zellennamen!#REF!
Name ___CHX2004: [2]Zellennamen!#REF!
Name ___CHX2005: [2]Zellennamen!#REF!
Name ___DTB2003: #REF!
Name ___DTB2004: #REF!
Name ___LY01: '[3]Last Year'!$A$1:$IV$65536
Name ___Mkt1: '[4]Rolling F''Cast P&L'!$GQ$26:$GQ$42
Name ___VAR1: #REF!
Name ___VAR2: #REF!
Name ___var22: '[5](Setup)'!$C$17
Name ___VAR3: #REF!
Name ___VAR4: #REF!
Name ___VAR5: #REF!
Name ___VAR6: #REF!
Name ___VAR7: #REF!
Name __ATS98: #REF!
Name __BGT02: [1]Budget!$A$1:$IV$65536
Name __CHF98: #REF!
Name __CHX2002: [2]Zellennamen!#REF!
Name __CHX2003: [2]Zellennamen!#REF!
Name __CHX2004: [2]Zellennamen!#REF!
Name __CHX2005: [2]Zellennamen!#REF!
Name __DAT1: #REF!
Name __DAT10: #REF!
Name __DAT11: #REF!
Name __DAT12: #REF!
Name __DAT13: #REF!
Name __DAT14: #REF!
Name __DAT15: #REF!
Name __DAT16: #REF!
Name __DAT17: #REF!
Name __DAT18: #REF!
Name __DAT19: #REF!
Name __DAT2: #REF!
Name __DAT20: #REF!
Name __DAT21: #REF!
Name __DAT22: #REF!
Name __DAT23: #REF!
Name __DAT24: #REF!
Name __DAT25: #REF!
Name __DAT26: #REF!
Name __DAT27: #REF!
Name __DAT28: #REF!
Name __DAT29: #REF!
Name __DAT3: #REF!
Name __DAT30: #REF!
Name __DAT31: #REF!
Name __DAT32: #REF!
Name __DAT33: #REF!
Name __DAT34: #REF!
Name __DAT35: #REF!
Name __DAT36: #REF!
Name __DAT37: #REF!
Name __DAT38: #REF!

Sheet Summary Capex
C2: TỔNG GIÁ TRỊ ĐẦU TƯ CAPEX 2019 đến 2026 (VND)
C3: Ghi chú: 2019 không phát sinh | K3: ĐVT: VNĐ
D4: ='Capex TT 2020'!G2 -> 24000 | E4: ='Capex TT 2021'!G2 -> 24300 | F4: ='Capex TT 2022'!G2 -> 24500 | G4: ='Capex TT 2023'!G2 -> 24700 | H4: ='Capex TT 2024'!G2 -> 25000 | I4: ='Capex TT 2025'!G2 -> 25500 | J4: ='Capex TT 2026'!G2 -> 26500 | S4: ĐVT: USD
B5: STT | C5: Nội dung | D5: Giá trị đầu tư VND | L5: Giá trị đầu tư USD
D6: 2020 | E6: 2021 | F6: 2022 | G6: 2023 | H6: 2024 | I6: 2025 | J6: 2026 | K6: Cộng 2020 -> 2026 | L6: 2020 | M6: 2021 | N6: 2022 | O6: 2023 | P6: 2024 | Q6: 2025 | R6: 2026 | S6: Cộng 2020 -> 2026
B7: 1 | C7: Nhà cửa, vật kiến trúc | D7: =D22 -> 2816980160 | E7: =E22 -> 98740200260 | F7: =F22 -> 45313950003 | G7: =G22 -> 58568025289 | H7: =H22 -> 2816980160 | I7: =I22 -> 1842503798 | J7: =J22 -> 1087426293 | K7: =SUM(D7:J7) -> 211186065963 | L7: =D7/D$4 -> 117374.17 | M7: =E7/E$4 -> 4063382.7 | N7: =F7/F$4 -> 1849549 | O7: =G7/G$4 -> 2371175.1 | P7: =H7/H$4 -> 112679.21 | Q7: =I7/I$4 -> 72255.051 | R7: =J7/J$4 -> 41034.954 | S7: =SUM(L7:R7) -> 8627450.2
B8: 2 | C8: Máy móc thiết bị | D8: =D30 -> 4317651482 | E8: =E30 -> 217005167222 | F8: =F30 -> 176781774442 | G8: =G30-G28 -> 2.9387833e+11 | H8: =H30 -> 69251846447 | I8: =I30 -> 52052051838 | J8: =J30 -> 26020850224 | K8: =SUM(D8:J8) -> 8.3930768e+11 | L8: =D8/D$4 -> 179902.15 | M8: =E8/E$4 -> 8930253.8 | N8: =F8/F$4 -> 7215582.6 | O8: =G8/G$4 -> 11897908 | P8: =H8/H$4 -> 2770073.9 | Q8: =I8/I$4 -> 2041256.9 | R8: =J8/J$4 -> 981918.88 | S8: =SUM(L8:R8) -> 34016896
B9: 3 | C9: Khuôn đầu tư sản phẩm mới | D9: =VLOOKUP($C9,'Capex TT 2020'!$E$5:$G$86,2,0) -> 0 | E9: =VLOOKUP($C9,'Capex TT 2021'!$E$5:$G$86,2,0) -> 0 | F9: =VLOOKUP($C9,'Capex TT 2022'!$E$5:$G$86,2,0) -> 60000000 | G9: =VLOOKUP($C9,'Capex TT 2023'!$E$5:$G$114,2,0) -> 79900000 | H9: =VLOOKUP(C9,'Capex TT 2024'!$E$5:$F$79,2,0) -> 1164204641 | I9: =VLOOKUP(C9,'Capex TT 2025'!$E$5:$F$203,2,0) -> 0 | J9: =VLOOKUP(C9,'Capex TT 2026'!$E$5:$F$210,2,0) -> 0 | K9: =SUM(D9:J9) -> 1304104641 | L9: =D9/D$4 -> 0 | M9: =E9/E$4 -> 0 | N9: =F9/F$4 -> 2448.9796 | O9: =G9/G$4 -> 3234.8178 | P9: =H9/H$4 -> 46568.186 | Q9: =I9/I$4 -> 0 | R9: =J9/J$4 -> 0 | S9: =SUM(L9:R9) -> 52251.983
B10: 4 | C10: Khuôn đầu tư thay thế | D10: =VLOOKUP($C10,'Capex TT 2020'!$E$5:$G$86,2,0) -> 0 | E10: =VLOOKUP($C10,'Capex TT 2021'!$E$5:$G$86,2,0) -> 0 | F10: =VLOOKUP($C10,'Capex TT 2022'!$E$5:$G$86,2,0) -> 0 | G10: =VLOOKUP($C10,'Capex TT 2023'!$E$5:$G$114,2,0) -> 0 | H10: =VLOOKUP(C10,'Capex TT 2024'!$E$5:$F$79,2,0) -> 0 | I10: =VLOOKUP(C10,'Capex TT 2025'!$E$5:$F$203,2,0) -> 0 | J10: =VLOOKUP(C10,'Capex TT 2026'!$E$5:$F$210,2,0) -> 0 | K10: =SUM(D10:J10) -> 0 | L10: =D10/D$4 -> 0 | M10: =E10/E$4 -> 0 | N10: =F10/F$4 -> 0 | O10: =G10/G$4 -> 0 | P10: =H10/H$4 -> 0 | Q10: =I10/I$4 -> 0 | R10: =J10/J$4 -> 0 | S10: =SUM(L10:R10) -> 0
B11: 5 | C11: Phương tiện vận tải | D11: =VLOOKUP($C11,'Capex TT 2020'!$E$5:$G$86,2,0) -> 380000000 | E11: =VLOOKUP($C11,'Capex TT 2021'!$E$5:$G$86,2,0) -> 2573766789 | F11: =VLOOKUP($C11,'Capex TT 2022'!$E$5:$G$86,2,0) -> 7797835728 | G11: =VLOOKUP($C11,'Capex TT 2023'!$E$5:$G$114,2,0) -> 5418910000 | H11: =VLOOKUP(C11,'Capex TT 2024'!$E$5:$F$79,2,0) -> 306314815 | I11: =VLOOKUP(C11,'Capex TT 2025'!$E$5:$F$203,2,0) -> 589564815 | J11: =VLOOKUP(C11,'Capex TT 2026'!$E$5:$F$210,2,0) -> 4514261846 | K11: =SUM(D11:J11) -> 21580653993 | L11: =D11/D$4 -> 15833.333 | M11: =E11/E$4 -> 105916.33 | N11: =F11/F$4 -> 318279.01 | O11: =G11/G$4 -> 219389.07 | P11: =H11/H$4 -> 12252.593 | Q11: =I11/I$4 -> 23120.189 | R11: =J11/J$4 -> 170349.5 | S11: =SUM(L11:R11) -> 865140.03
B12: 6 | C12: Thiết bị quản lý | D12: =VLOOKUP($C12,'Capex TT 2020'!$E$5:$G$86,2,0) -> 0 | E12: =VLOOKUP($C12,'Capex TT 2021'!$E$5:$G$86,2,0) -> 105866000 | F12: =VLOOKUP($C12,'Capex TT 2022'!$E$5:$G$86,2,0) -> 1208647832 | G12: =VLOOKUP($C12,'Capex TT 2023'!$E$5:$G$114,2,0) -> 369065000 | H12: =VLOOKUP(C12,'Capex TT 2024'!$E$5:$F$79,2,0) -> 0 | I12: =VLOOKUP(C12,'Capex TT 2025'!$E$5:$F$203,2,0) -> 68076000 | J12: =VLOOKUP(C12,'Capex TT 2026'!$E$5:$F$210,2,0) -> 232367703 | K12: =SUM(D12:J12) -> 1984022535 | L12: =D12/D$4 -> 0 | M12: =E12/E$4 -> 4356.6255 | N12: =F12/F$4 -> 49332.565 | O12: =G12/G$4 -> 14941.903 | P12: =H12/H$4 -> 0 | Q12: =I12/I$4 -> 2669.6471 | R12: =J12/J$4 -> 8768.5926 | S12: =SUM(L12:R12) -> 80069.333
B13: 7 | C13: Phần mềm vi tính | D13: =VLOOKUP($C13,'Capex TT 2020'!$E$5:$G$86,2,0) -> 0 | E13: =VLOOKUP($C13,'Capex TT 2021'!$E$5:$G$86,2,0) -> 0 | F13: =VLOOKUP($C13,'Capex TT 2022'!$E$5:$G$86,2,0) -> 784148252 | G13: =G28 -> 3483552000 | H13: =VLOOKUP(C13,'Capex TT 2024'!$E$5:$F$79,2,0) -> 960422938 | I13: =VLOOKUP(C13,'Capex TT 2025'!$E$5:$F$203,2,0) -> 2485202733 | J13: =VLOOKUP(C13,'Capex TT 2026'!$E$5:$F$210,2,0) -> 0 | K13: =SUM(D13:J13) -> 7713325923 | L13: =D13/D$4 -> 0 | M13: =E13/E$4 -> 0 | N13: =F13/F$4 -> 32006.051 | O13: =G13/G$4 -> 141034.49 | P13: =H13/H$4 -> 38416.918 | Q13: =I13/I$4 -> 97458.931 | R13: =J13/J$4 -> 0 | S13: =SUM(L13:R13) -> 308916.39
B14: 8 | C14: Khác | D14: =VLOOKUP($C14,'Capex TT 2020'!$E$5:$G$86,2,0) -> 0 | E14: =VLOOKUP($C14,'Capex TT 2021'!$E$5:$G$86,2,0) -> 1813062045 | F14: =VLOOKUP($C14,'Capex TT 2022'!$E$5:$G$86,2,0) -> 0 | G14: =VLOOKUP($C14,'Capex TT 2023'!$E$5:$G$114,2,0) -> 0 | H14: =VLOOKUP(C14,'Capex TT 2024'!$E$5:$F$79,2,0) -> 0 | I14: =VLOOKUP(C14,'Capex TT 2025'!$E$5:$F$203,2,0) -> 0 | J14: =VLOOKUP(C14,'Capex TT 2026'!$E$5:$F$210,2,0) -> 1230644844 | K14: =SUM(D14:J14) -> 3043706889 | L14: =D14/D$4 -> 0 | M14: =E14/E$4 -> 74611.607 | N14: =F14/F$4 -> 0 | O14: =G14/G$4 -> 0 | P14: =H14/H$4 -> 0 | Q14: =I14/I$4 -> 0 | R14: =J14/J$4 -> 46439.428 | S14: =SUM(L14:R14) -> 121051.03
C15: TỔNG CỘNG | D15: =SUM(D7:D14) -> 7514631642 | E15: =SUM(E7:E14) -> 320238062316 | F15: =SUM(F7:F14) -> 231946356257 | G15: =SUM(G7:G14) -> 3.6179779e+11 | H15: =SUM(H7:H14) -> 74499769001 | I15: =SUM(I7:I14) -> 57037399184 | J15: =SUM(J7:J14) -> 33085550910 | K15: =SUM(K7:K14) -> 1.0861196e+12 | ... S15: =SUM(S7:S14) -> 44071775
C16: LŨY KẾ | D16: =D15 -> 7514631642 | E16: =E15+D16 -> 327752693958 | F16: =F15+E16 -> 559699050215 | G16: =G15+F16 -> 9.2149684e+11 | H16: =H15+G16 -> 9.9599661e+11 | I16: =I15+H16 -> 1.053034e+12 | J16: =J15+I16 -> 1.0861196e+12 | K16: =K15+J16 -> 2.1722391e+12 | L16: =L15 -> 313109.65 | M16: =M15+L16 -> 13491631 | N16: =N15+M16 -> 22958829 | O16: =O15+N16 -> 37606513 | P16: =P15+O16 -> 40586503 | Q16: =Q15+P16 -> 42823264 | R16: =R15+Q16 -> 44071775 | S16: =S15+R16 -> 88143551
C20: Nhà cửa vật kiến trúc (VNĐ)
D21: 2020 | E21: 2021 | F21: 2022 | G21: 2023 | H21: 2024 | I21: 2025 | J21: 2026 | K21: Cộng
D22: ='Nhà cửa vật kiến trúc (VNĐ)'!F5 -> 2816980160 | E22: ='Nhà cửa vật kiến trúc (VNĐ)'!F2 -> 98740200260 | F22: ='Nhà cửa vật kiến trúc (VNĐ)'!F3 -> 45313950003 | G22: ='Nhà cửa vật kiến trúc (VNĐ)'!F4 -> 58568025289 | H22: ='Nhà cửa vật kiến trúc (VNĐ)'!F5 -> 2816980160 | I22: ='Nhà cửa vật kiến trúc (VNĐ)'!F6 -> 1842503798 | J22: ='Nhà cửa vật kiến trúc (VNĐ)'!F7 -> 1087426293 | K22: =SUM(D22:I22) -> 210098639670
C24: Máy móc thiết bị | D24: (VNĐ)
D25: 2020 | E25: 2021 | F25: 2022 | G25: 2023 | H25: 2024 | I25: 2025 | J25: 2026 | K25: Cộng
C26: DTR | D26: =VLOOKUP($C24,'Capex TT 2020'!$E$5:$G$86,2,0) -> 4317651482 | E26: =VLOOKUP($C24,'Capex TT 2021'!$E$5:$G$86,2,0) -> 214888211254 | F26: =VLOOKUP($C24,'Capex TT 2022'!$E$5:$G$86,2,0) -> 36050065845 | G26: =VLOOKUP($C24,'Capex TT 2023'!$E$5:$G$86,2,0) -> 47513794431 | H26: =VLOOKUP(C24,'Capex TT 2024'!E5:F79,2,0) -> 69251846447 | I26: =VLOOKUP(C24,'Capex TT 2025'!E5:F92,2,0) -> 52052051838 | J26: =VLOOKUP(C24,'Capex TT 2026'!E5:F96,2,0) -> 26020850224 | K26: =SUM(D26:I26) -> 424073621297
C27: TNHH | D27: 0 | E27: ='TNHH sở hữu'!T1 -> 2116955968 | F27: ='TNHH sở hữu'!T2 -> 140731708597 | G27: =SUM(G28:G29) -> 2.4984809e+11 | H27: 0 | I27: 0 | J27: 0 | K27: =SUM(D27:I27) -> 3.9269676e+11
C28: Phần mềm vi tính | G28: ='TNHH sở hữu'!T4 -> 3483552000
C29: MMTB | G29: ='TNHH sở hữu'!T5 -> 2.4636454e+11
C30: Cộng | D30: =SUM(D26:D27) -> 4317651482 | E30: =SUM(E26:E27) -> 217005167222 | F30: =SUM(F26:F27) -> 176781774442 | G30: =SUM(G26:G27) -> 2.9736189e+11 | H30: =SUM(H26:H27) -> 69251846447 | I30: =SUM(I26:I27) -> 52052051838 | J30: =SUM(J26:J27) -> 26020850224 | K30: =SUM(K26:K27) -> 8.1677038e+11

Sheet Slide
A1: Nhóm tài sản (SAP) | B1: Tên Nhóm tài sản (SAP)
C2: STT | D2: Nội dung | E2: Giá trị đầu tư VND | F2: Giá trị đầu tư USD
C3: 1 | D3: Máy móc thiết bị | E3: ='Capex TT 2025'!F15 -> 52052051838 | F3: ='Capex TT 2025'!G15 -> 2041256.9
C4: 2 | D4: Nhà cửa, vật kiến trúc | E4: ='Capex TT 2025'!F5 -> 1842503798 | F4: ='Capex TT 2025'!G5 -> 72255.051
C5: 3 | D5: Thiết bị quản lí | E5: ='Capex TT 2025'!F90 -> 68076000 | F5: ='Capex TT 2025'!G90 -> 2669.6471
C6: 4 | D6: Khác | E6: ='Capex TT 2025'!F97 -> 0 | F6: ='Capex TT 2025'!G97 -> 0
C7: 5 | D7: Phần mềm vi tính | E7: ='Capex TT 2025'!F93 -> 2485202733 | F7: ='Capex TT 2025'!G93 -> 97458.931
C8: 6 | D8: Khuôn đầu tư sản phẩm mới | E8: ='Capex TT 2025'!F77 -> 0 | F8: ='Capex TT 2025'!G77 -> 0
C9: 7 | D9: Khuôn đầu tư thay thế | E9: ='Capex TT 2025'!F80 -> 0 | F9: ='Capex TT 2025'!G80 -> 0
C10: 8 | D10: Phương tiện vận tải | E10: ='Capex TT 2025'!F81 -> 589564815 | F10: ='Capex TT 2025'!G81 -> 23120.189
D11: CỘNG | E11: =SUM(E3:E10) -> 57037399184 | F11: =SUM(F3:F10) -> 2236760.8
C14: STT | D14: Bộ Phận | E14: Giá trị đầu tư VND | F14: Giá trị đầu tư USD
C15: 1 | D15: Cung ứng | E15: 546708775 | F15: =E15/25500 -> 21439.56
C16: 2 | D16: HCNS | E16: 192107000 | F16: =E16/25500 -> 7533.6078
C17: 3 | D17: Kế Toán | E17: 248763230 | F17: =E17/25500 -> 9755.4208
C18: 4 | D18: Kinh doanh | E18: 1938493958 | F18: =E18/25500 -> 76019.371
C19: 5 | D19: Kỹ thuật | E19: 2641290458 | F19: =E19/25500 -> 103580.02
C20: 6 | D20: QC | E20: 291950000 | F20: =E20/25500 -> 11449.02
C21: 7 | D21: R&D | E21: 1025280138 | F21: =E21/25500 -> 40207.064
C22: 8 | D22: Sản xuất | E22: 41990040054 | F22: =E22/25500 -> 1646668.2
D23: CỘNG | E23: =SUM(E15:E22) -> 48874633613 | F23: =SUM(F15:F22) -> 1916652.3 | G23: =E11-E23 -> 8162765571 | H23: =F11-F23 -> 320108.45

Sheet Capex TT 2026
E1: ĐẦU TƯ CAPEX THỰC TẾ 2026 | G1: Cập nhật | H1: 11.04.2026
F2: Tỷ giá: | G2: 26500 | H2: Lấy theo tỉ giá kế hoạch 2026
F3: =SUM(F5,F15,F77,F80,F81,F90,F97,F101) -> 33085550910 | G3: =SUM(G5,G15,G77,G80,G81,G90,G97,G101) -> 1248511.4
A4: Nhóm tài sản (SAP) | B4: Tên Nhóm tài sản (SAP) | C4: STT | D4: Mã TS | E4: Nội dung | F4: số tiền VND | G4: số tiền USD
C5: 1 | E5: Nhà cửa, vật kiến trúc | F5: =SUM(F6:F14) -> 1087426293 | G5: =F5/$G$2 -> 41034.954
A6: Z21110P | B6: Nhà cửa, vật kiến trúc - SX 627 | C6: =SUBTOTAL(3,$E$6:E6) -> 1 | D6: 101000030 | E6: TC lắp thông gió Xưởng F2 (Kỹ thuật) | F6: 722538166 | G6: =F6/$G$2 -> 27265.591
A7: Z21110P | B7: Nhà cửa, vật kiến trúc - SX 627 | C7: =SUBTOTAL(3,$E$6:E7) -> 2 | D7: 101000032 | E7: Mái che hồ nước sản xuất F3 | F7: 364888127 | G7: =F7/$G$2 -> 13769.363
C8: =SUBTOTAL(3,$E$6:E8) -> 2 | G8: =F8/$G$2 -> 0
C9: =SUBTOTAL(3,$E$6:E9) -> 2 | G9: =F9/$G$2 -> 0
C10: =SUBTOTAL(3,$E$6:E10) -> 2 | G10: =F10/$G$2 -> 0
C11: =SUBTOTAL(3,$E$6:E11) -> 2 | G11: =F11/$G$2 -> 0
C12: =SUBTOTAL(3,$E$6:E12) -> 2 | G12: =F12/$G$2 -> 0
C13: =SUBTOTAL(3,$E$6:E13) -> 2 | G13: =F13/$G$2 -> 0
C15: 2 | E15: Máy móc thiết bị | F15: =SUM(F16:F76) -> 26020850224 | G15: =F15/$G$2 -> 981918.88
A16: Z211201P | B16: Máy móc, thiết bị phụ - SX 627 | C16: =SUBTOTAL(3,$E$16:E16) -> 1 | D16: 104600162 | E16: Sàng rung hạt cho chuyền STAR-01 F03 | F16: 247617183 | G16: =F16/$G$2 -> 9344.0446
A17: Z211201P | B17: Máy móc, thiết bị phụ - SX 627 | C17: =SUBTOTAL(3,$E$16:E17) -> 2 | D17: 104600163 | E17: Sàng rung hạt chuyền STAR-03 F03 Sàng 1 | F17: 246437220 | G17: =F17/$G$2 -> 9299.5177
A18: Z211201P | B18: Máy móc, thiết bị phụ - SX 627 | C18: =SUBTOTAL(3,$E$16:E18) -> 3 | D18: 104600164 | E18: Sàng rung hạt chuyền STAR-03 F03 Sàng 2 | F18: 242357220 | G18: =F18/$G$2 -> 9145.5555
A19: Z211201P | B19: Máy móc, thiết bị phụ - SX 627 | C19: =SUBTOTAL(3,$E$16:E19) -> 4 | D19: 104600165 | E19: Sàng rung hạt cho máy MIX-03 F02 | F19: 225996893 | G19: =F19/$G$2 -> 8528.1846
A20: Z211201P | B20: Máy móc, thiết bị phụ - SX 627 | C20: =SUBTOTAL(3,$E$16:E20) -> 5 | D20: 104600166 | E20: Sàng rung hạt cho máy MEYE-01 F02 | F20: 225996893 | G20: =F20/$G$2 -> 8528.1846
A21: Z211201P | B21: Máy móc, thiết bị phụ - SX 627 | C21: =SUBTOTAL(3,$E$16:E21) -> 6 | D21: 104600178 | E21: Lắp đặt sàn lấy mẫu F03 | F21: 516564328 | G21: =F21/$G$2 -> 19492.994
A22: Z21120P | B22: Máy móc, thiết bị - SX 627 | C22: =SUBTOTAL(3,$E$16:E22) -> 7 | D22: 104000199 | E22: Nâng cấp hệ chân không SSP Star-01(F3) | F22: 1665768146 | G22: =F22/$G$2 -> 62859.175
A23: Z21180P | B23: TSCĐ khác - SX 627 | C23: =SUBTOTAL(3,$E$16:E23) -> 8 | D23: 115000040 | E23: Máy ép phun riêng Thử nghiệm HD-PP F2 | F23: 38275500 | G23: =F23/$G$2 -> 1444.3585
A24: Z21120P | B24: Máy móc, thiết bị - SX 627 | C24: =SUBTOTAL(3,$E$16:E24) -> 9 | D24: 104000200 | E24: Chuyền rửa Boretech 3 tấn/giờ F5 | F24: 22443634993 | G24: =F24/$G$2 -> 846929.62
A25: Z211201P | B25: Máy móc, thiết bị phụ - SX 627 | C25: =SUBTOTAL(3,$E$16:E25) -> 10 | D25: 104600180 | E25: Băng tải chuyển chai lựa KL Băm3 (F3) | F25: 96247486 | G25: =F25/$G$2 -> 3631.9806
A26: Z211201P | B26: Máy móc, thiết bị phụ - SX 627 | C26: =SUBTOTAL(3,$E$16:E26) -> 11 | D26: 104600184 | E26: Trục vít tải liệu 01 CHWO-B01 (F3) | F26: 71954362 | G26: =F26/$G$2 -> 2715.2589
C27: =SUBTOTAL(3,$E$16:E27) -> 11 | G27: =F27/$G$2 -> 0
C28: =SUBTOTAL(3,$E$16:E28) -> 11 | G28: =F28/$G$2 -> 0
C29: =SUBTOTAL(3,$E$16:E29) -> 11 | G29: =F29/$G$2 -> 0
C30: =SUBTOTAL(3,$E$16:E30) -> 11 | G30: =F30/$G$2 -> 0
C31: =SUBTOTAL(3,$E$16:E31) -> 11 | G31: =F31/$G$2 -> 0
C32: =SUBTOTAL(3,$E$16:E32) -> 11 | G32: =F32/$G$2 -> 0
C33: =SUBTOTAL(3,$E$16:E33) -> 11 | G33: =F33/$G$2 -> 0
C34: =SUBTOTAL(3,$E$16:E34) -> 11 | G34: =F34/$G$2 -> 0
C35: =SUBTOTAL(3,$E$16:E35) -> 11 | G35: =F35/$G$2 -> 0
C36: =SUBTOTAL(3,$E$16:E36) -> 11 | G36: =F36/$G$2 -> 0
C37: =SUBTOTAL(3,$E$16:E37) -> 11 | G37: =F37/$G$2 -> 0
C38: =SUBTOTAL(3,$E$16:E38) -> 11 | G38: =F38/$G$2 -> 0
... C75: =SUBTOTAL(3,$E$16:E75) -> 11 | G75: =F75/$G$2 -> 0
C77: 3 | E77: Khuôn đầu tư sản phẩm mới | F77: =SUM(F78:F79) -> 0 | G77: =F77/$G$2 -> 0
C78: =SUBTOTAL(3,$E$78:E78) -> 0 | G78: =F78/$G$2 -> 0
C79: =SUBTOTAL(3,$E$78:E79) -> 0 | G79: =F79/$G$2 -> 0
C80: 4 | E80: Khuôn đầu tư thay thế | F80: 0 | G80: =F80/$G$2 -> 0
C81: 5 | E81: Phương tiện vận tải | F81: =SUM(F82:F89) -> 4514261846 | G81: =F81/$G$2 -> 170349.5
A82: Z21130P | B82: Phương tiện vận tải , truyền dẫn - SX 627 | C82: =SUBTOTAL(3,$E$82:E82) -> 1 | D82: 107000062 | E82: Xe tải Isuzu Fvr34Ve5 Euro 5- số 01-70A68119 | F82: 1489706410 | G82: =F82/$G$2 -> 56215.336
A83: Z21130P | B83: Phương tiện vận tải , truyền dẫn - SX 627 | C83: =SUBTOTAL(3,$E$82:E83) -> 2 | D83: 107000063 | E83: Xe tải Isuzu Fvr34Ve5 Euro 5- số 02-70A68100 | F83: 1489706410 | G83: =F83/$G$2 -> 56215.336
A84: Z21130P | B84: Phương tiện vận tải , truyền dẫn - SX 627 | C84: =SUBTOTAL(3,$E$82:E84) -> 3 | D84: 107000064 | E84: Xe tải Isuzu Fvr34Ve5 Euro 5- số 3- 70A68138 | F84: 1534849026 | G84: =F84/$G$2 -> 57918.831
C85: =SUBTOTAL(3,$E$82:E85) -> 3 | G85: =F85/$G$2 -> 0
C86: =SUBTOTAL(3,$E$82:E86) -> 3 | G86: =F86/$G$2 -> 0
C87: =SUBTOTAL(3,$E$82:E87) -> 3 | G87: =F87/$G$2 -> 0
C88: =SUBTOTAL(3,$E$82:E88) -> 3 | G88: =F88/$G$2 -> 0
C89: =SUBTOTAL(3,$E$82:E89) -> 3 | G89: =F89/$G$2 -> 0
C90: 6 | E90: Thiết bị quản lý | F90: =SUM(F91:F96) -> 232367703 | G90: =SUM(G91:G96) -> 8768.5926
A91: Z21140A | B91: Thiết bị, dụng cụ quản lý - QL 642 | C91: =SUBTOTAL(3,$E$91:E91) -> 1 | D91: 112000030 | E91: TB MÀN HÌNH TƯƠNG TÁC THÔNG MINH P.HỌP 3 (1) | F91: 62400000 | G91: =F91/$G$2 -> 2354.717
A92: Z21140A | B92: Thiết bị, dụng cụ quản lý - QL 642 | C92: =SUBTOTAL(3,$E$91:E92) -> 2 | D92: 112000031 | E92: TB MÀN HÌNH TƯƠNG TÁC THÔNG MINH P.HỌP 3 (2) | F92: 62400000 | G92: =F92/$G$2 -> 2354.717
A93: Z21140A | B93: Thiết bị, dụng cụ quản lý - QL 642 | C93: =SUBTOTAL(3,$E$91:E93) -> 3 | D93: 112000032 | E93: Tivi xem camera trạm (P. A. Thạch) | F93: 39689000 | G93: =F93/$G$2 -> 1497.6981
A94: Z21140A | B94: Thiết bị, dụng cụ quản lý - QL 642 | C94: =SUBTOTAL(3,$E$91:E94) -> 4 | D94: 112000029 | E94: Laptop HP Omnibook (A.Quân) | F94: 33878703 | G94: =F94/$G$2 -> 1278.4416
A95: Z21140A | B95: Thiết bị, dụng cụ quản lý - QL 642 | C95: =SUBTOTAL(3,$E$91:E95) -> 5 | D95: 112000033 | E95: Laptop HP OmniBook 7 Core Ultra 7 (A.Thạch) | F95: 34000000 | G95: =F95/$G$2 -> 1283.0189
C96: =SUBTOTAL(3,$E$91:E96) -> 5 | G96: =F96/$G$2 -> 0
C97: 7 | E97: Phần mềm vi tính | F97: =SUM(F98:F100) -> 0 | G97: =F97/$G$2 -> 0
C98: =SUBTOTAL(3,$E98:E$100) -> 0 | G98: =F98/$G$2 -> 0
C99: =SUBTOTAL(3,$E99:E$100) -> 0 | G99: =F99/$G$2 -> 0
C100: =SUBTOTAL(3,$E100:E$100) -> 0 | G100: =F100/$G$2 -> 0
C101: 8 | E101: Khác | F101: =SUM(F102:F105) -> 1230644844 | G101: =SUM(G102:G105) -> 46439.428
A102: Z21180P | B102: TSCĐ khác - SX 627 | C102: =SUBTOTAL(3,$E102:E$102) -> 1 | D102: 115000034 | E102: Máy quét rác ngồi lái DF32(pet+kho) | F102: 150000000 | G102: =F102/$G$2 -> 5660.3774
A103: Z21180P | B103: TSCĐ khác - SX 627 | C103: =SUBTOTAL(3,$E$102:E103) -> 2 | D103: 115000038 | E103: HT AI cảnh báo cân xe (Cổng BV số 3 F6) | F103: 473517301 | G103: =F103/$G$2 -> 17868.577
A104: Z21180P | B104: TSCĐ khác - SX 627 | C104: =SUBTOTAL(3,$E$102:E104) -> 3 | D104: 115000039 | E104: Lắp đặt dàn gạt bùn bể lắng sinh học 400m3 F3 | F104: 409877543 | G104: =F104/$G$2 -> 15467.077
A105: Z21180A | B105: TSCĐ khác - QL 642 | C105: =SUBTOTAL(3,$E$102:E105) -> 4 | D105: 117000012 | E105: Máy chia cơm tự động (nhà ăn) | F105: 197250000 | G105: =F105/$G$2 -> 7443.3962

Sheet Capex TT 2025
E1: ĐẦU TƯ CAPEX THỰC TẾ 2025 | G1: Cập nhật | H1: 12.01.2026
F2: Tỷ giá: | G2: 25500 | H2: Lấy theo tỉ giá kế hoạch 2025
F3: =SUM(F5,F15,F77,F80,F81,F90,F93,F97) -> 57037399184 | G3: =SUM(G5,G15,G77,G80,G81,G90,G93,G97) -> 2236760.8
A4: Nhóm tài sản (SAP) | B4: Tên Nhóm tài sản (SAP) | C4: STT | D4: Mã TS | E4: Nội dung | F4: số tiền VND | G4: số tiền USD
C5: 1 | E5: Nhà cửa, vật kiến trúc | F5: =SUM(F6:F14) -> 1842503798 | G5: =F5/$G$2 -> 72255.051
A6: Z21110A | B6: Nhà cửa, vật kiến trúc - QL 642 | C6: =SUBTOTAL(3,$E$6:E6) -> 1 | D6: 103000016 | E6: Hạ tầng mạng cho 5 chốt chặn | F6: 140570000 | G6: =F6/$G$2 -> 5512.549
A7: Z21110A | B7: Nhà cửa, vật kiến trúc - QL 642 | C7: =SUBTOTAL(3,$E$6:E7) -> 2 | D7: 103000017 | E7: Nhà chờ cổng 1 | F7: 72217040 | G7: =F7/$G$2 -> 2832.0408
A8: Z211201P | B8: Máy móc, thiết bị phụ - SX 627 | C8: =SUBTOTAL(3,$E$6:E8) -> 3 | D8: 104600117 | E8: Nhà chống côn trùng Meyer F2 | F8: 127088350 | G8: =F8/$G$2 -> 4983.8569
A9: Z21180P | B9: TSCĐ khác - SX 627 | C9: =SUBTOTAL(3,$E$6:E9) -> 4 | D9: 115000029 | E9: Lắp đặt Vách bạt cuốn di động F2 và F3 | F9: 90591075 | G9: =F9/$G$2 -> 3552.5912
A10: Z21110A | B10: Nhà cửa, vật kiến trúc - QL 642 | C10: =SUBTOTAL(3,$E$6:E10) -> 5 | D10: 103000018 | E10: Chốt chặn F5 | F10: 108193230 | G10: =F10/$G$2 -> 4242.8718
A11: Z21110P | B11: Nhà cửa, vật kiến trúc - SX 627 | C11: =SUBTOTAL(3,$E$6:E11) -> 6 | D11: 101000026 | E11: Lắp mái che di động trục giữa F1 và F2 | F11: 723140800 | G11: =F11/$G$2 -> 28358.463
A12: Z21180P | B12: TSCĐ khác - SX 627 | C12: =SUBTOTAL(3,$E$6:E12) -> 7 | D12: 115000032 | E12: Thi công mới nhà vệ sinh Văn phòng F02 | F12: 248009202 | G12: =F12/$G$2 -> 9725.8511
A13: Z21180P | B13: TSCĐ khác - SX 627 | C13: =SUBTOTAL(3,$E$6:E13) -> 8 | D13: 115000035 | E13: Trạm sạc xe nâng-F5 | F13: 332694101 | G13: =F13/$G$2 -> 13046.827
C15: 2 | E15: Máy móc thiết bị | F15: =SUM(F16:F76) -> 52052051838 | G15: =F15/$G$2 -> 2041256.9
A16: Z21120P | B16: Máy móc, thiết bị - SX 627 | C16: =SUBTOTAL(3,$E$16:E16) -> 1 | D16: 104000158 | E16: Máy lọc bụi Cartridge CDC -PL-6 (QLCL) | F16: 36200000 | G16: =F16/$G$2 -> 1419.6078
A17: Z211201P | B17: Máy móc, thiết bị phụ - SX 627 | C17: =SUBTOTAL(3,$E$16:E17) -> 2 | D17: 104600123 | E17: Tủ hút H.chất Bestlab PhượngHải BL.H-2.0 | F17: 185000000 | G17: =F17/$G$2 -> 7254.902
A18: Z21120P | B18: Máy móc, thiết bị - SX 627 | C18: =SUBTOTAL(3,$E$16:E18) -> 3 | D18: 104000173 | E18: lắp chuyền rửa lạnh mới F03 | F18: 2745703965 | G18: =F18/$G$2 -> 107674.67
A19: Z21120P | B19: Máy móc, thiết bị - SX 627 | C19: =SUBTOTAL(3,$E$16:E19) -> 4 | D19: 104000176 | E19: TC máy tách liệu chuyền rửa lạnh F3 BRT | F19: 1300467332 | G19: =F19/$G$2 -> 50998.719
A20: Z21120P | B20: Máy móc, thiết bị - SX 627 | C20: =SUBTOTAL(3,$E$16:E20) -> 5 | D20: 104000179 | E20: Hệ khung sàn cho chuyền rửa lạnh mới F03 | F20: 486411454 | G20: =F20/$G$2 -> 19074.959
A21: Z21120P | B21: Máy móc, thiết bị - SX 627 | C21: =SUBTOTAL(3,$E$16:E21) -> 6 | D21: 104000183 | E21: TỦ ĐIỆN HỆ RỬA NÓNG CHWO-R02 | F21: 432632369 | G21: =F21/$G$2 -> 16965.975
A22: Z21120P | B22: Máy móc, thiết bị - SX 627 | C22: =SUBTOTAL(3,$E$16:E22) -> 7 | D22: 104000184 | E22: Máy tạo hạt nhựa Gran (HD02)(TLP) F2 | F22: 6670000000 | G22: =F22/$G$2 -> 261568.63
A23: Z211201P | B23: Máy móc, thiết bị phụ - SX 627 | C23: =SUBTOTAL(3,$E$16:E23) -> 8 | D23: 104600106 | E23: Sàng rung 2000x800 công suất 2000kg/h (F2) | F23: 118000000 | G23: =F23/$G$2 -> 4627.451
A24: Z211201P | B24: Máy móc, thiết bị phụ - SX 627 | C24: =SUBTOTAL(3,$E$16:E24) -> 9 | D24: 104600107 | E24: Sàng rung 2000x800 công suất 2000kg/h (F4) | F24: 118000000 | G24: =F24/$G$2 -> 4627.451
A25: Z211201P | B25: Máy móc, thiết bị phụ - SX 627 | C25: =SUBTOTAL(3,$E$16:E25) -> 10 | D25: 104600110 | E25: Máy móc tăng cường CHWO-R01 | F25: 1590298692 | G25: =F25/$G$2 -> 62364.655
A26: Z211201P | B26: Máy móc, thiết bị phụ - SX 627 | C26: =SUBTOTAL(3,$E$16:E26) -> 11 | D26: 104600111 | E26: HTxả bao Jumbo1 tấn tự động-Rửa nóng R01 | F26: 504861258 | G26: =F26/$G$2 -> 19798.481
A27: Z211201P | B27: Máy móc, thiết bị phụ - SX 627 | C27: =SUBTOTAL(3,$E$16:E27) -> 12 | D27: 104600112 | E27: HTxả bao Jumbo1 tấn tự động-Rửa lạnh R01 | F27: 500738186 | G27: =F27/$G$2 -> 19636.792
... A75: Z211201P | B75: Máy móc, thiết bị phụ - SX 627 | C75: =SUBTOTAL(3,$E$16:E75) -> 60 | D75: 104600161 | E75: Máy sấy bụi 1 tấn-F05 | F75: 453547830 | G75: =F75/$G$2 -> 17786.189
C77: 3 | E77: Khuôn đầu tư sản phẩm mới | F77: =SUM(F78:F79) -> 0 | G77: =F77/$G$2 -> 0
C78: =SUBTOTAL(3,$E$78:E78) -> 0 | G78: =F78/$G$2 -> 0
C79: =SUBTOTAL(3,$E$78:E79) -> 0 | G79: =F79/$G$2 -> 0
C80: 4 | E80: Khuôn đầu tư thay thế | F80: 0 | G80: =F80/$G$2 -> 0
C81: 5 | E81: Phương tiện vận tải | F81: =SUM(F82:F89) -> 589564815 | G81: =F81/$G$2 -> 23120.189
A82: Z21130P | B82: Phương tiện vận tải , truyền dẫn - SX 627 | C82: =SUBTOTAL(3,$E$82:E82) -> 1 | D82: 107000047 | E82: Xe nâng người GTJZ-10 (BYD) (PET) | F82: 290000000 | G82: =F82/$G$2 -> 11372.549
A83: Z21130P | B83: Phương tiện vận tải , truyền dẫn - SX 627 | C83: =SUBTOTAL(3,$E$82:E83) -> 2 | D83: 107000048 | E83: Xe AGV Chở hàng mẫu | F83: 70750000 | G83: =F83/$G$2 -> 2774.5098
A84: Z21130P | B84: Phương tiện vận tải , truyền dẫn - SX 627 | C84: =SUBTOTAL(3,$E$82:E84) -> 3 | D84: 107000049 | E84: Xe nâng tay điện HeliCBD20-ALH số 8 vị trí BORE-02 | F84: 37962963 | G84: =F84/$G$2 -> 1488.7436
A85: Z21130P | B85: Phương tiện vận tải , truyền dẫn - SX 627 | C85: =SUBTOTAL(3,$E$82:E85) -> 4 | D85: 107000050 | E85: Xe nâng tay điện Heli CBD20-ALH (F2-HD) (1) | F85: 37962963 | G85: =F85/$G$2 -> 1488.7436
A86: Z21130P | B86: Phương tiện vận tải , truyền dẫn - SX 627 | C86: =SUBTOTAL(3,$E$82:E86) -> 5 | D86: 107000051 | E86: Xe nâng tay điện Heli CBD20-ALH (F4-HD) (2) | F86: 37962963 | G86: =F86/$G$2 -> 1488.7436
A87: Z21130P | B87: Phương tiện vận tải , truyền dẫn - SX 627 | C87: =SUBTOTAL(3,$E$82:E87) -> 6 | D87: 107000052 | E87: Xe nâng tay điện Heli CBD20-ALH (MIX-09 -F3) | F87: 37962963 | G87: =F87/$G$2 -> 1488.7436
A88: Z21130P | B88: Phương tiện vận tải , truyền dẫn - SX 627 | C88: =SUBTOTAL(3,$E$82:E88) -> 7 | D88: 107000053 | E88: Xe nâng tay điện Heli CBD20-ALH (F5) | F88: 37962963 | G88: =F88/$G$2 -> 1488.7436
A89: Z21130P | B89: Phương tiện vận tải , truyền dẫn - SX 627 | C89: =SUBTOTAL(3,$E$82:E89) -> 8 | D89: 107000054 | E89: Xe nâng tay điện PTE20Q-A Noblelift (F5) | F89: 39000000 | G89: =F89/$G$2 -> 1529.4118
C90: 6 | E90: Thiết bị quản lý | F90: =SUM(F91:F92) -> 68076000 | G90: =SUM(G91:G92) -> 2669.6471
A91: Z21140A | B91: Thiết bị, dụng cụ quản lý - QL 642 | C91: =SUBTOTAL(3,$E$91:E91) -> 1 | D91: 112000019 | E91: Máy lạnh Daikin FTKY60WVMV/RKY60WVMV (HCNS) | F91: 34926000 | G91: =F91/$G$2 -> 1369.6471
A92: Z21140A | B92: Thiết bị, dụng cụ quản lý - QL 642 | C92: =SUBTOTAL(3,$E$91:E92) -> 2 | D92: 112000024 | E92: Máy tính bàn HP EliteOne 870 G9 AIO i7-1470/32G | F92: 33150000 | G92: =F92/$G$2 -> 1300
C93: 7 | E93: Phần mềm vi tính | F93: =SUM(F94:F96) -> 2485202733 | G93: =F93/$G$2 -> 97458.931
A94: Z21350A | B94: Phần mềm máy vi tính - QL 642 | C94: =SUBTOTAL(3,$E94:E$96) -> 3 | D94: 147000000 | E94: Dự án VMS Giai đoạn 1 (16 tablet) (Cung ứng) | F94: 487610783 | G94: =F94/$G$2 -> 19121.991
A95: Z21350S | B95: Phần mềm máy vi tính - BH 641 | C95: =SUBTOTAL(3,$E95:E$96) -> 2 | D95: 146000002 | E95: Dự án CRM | F95: 1938493958 | G95: =F95/$G$2 -> 76019.371
A96: Z15319A | B96: Công cụ, dụng cụ cho - QL 642 | C96: =SUBTOTAL(3,$E96:E$96) -> 1 | D96: 155000352 | E96: DỰ ÁN VMS (giai đoạn 2) | F96: 59097992 | G96: =F96/$G$2 -> 2317.5683
C97: 8 | E97: Khác | G97: =F97/$G$2 -> 0

Sheet Capex TT 2024
E1: ĐẦU TƯ CAPEX THỰC TẾ 2024
F2: Tỷ giá: | G2: 25000
F3: =SUM(F5,F12,F55,F66,F67,F74,F76,F79) -> 74499769001 | G3: =SUM(G5,G12,G55,G66,G67,G74,G76,G79) -> 2979990.8
A4: Nhóm tài sản (SAP) | B4: Tên Nhóm tài sản (SAP) | C4: STT | D4: Mã TS | E4: Nội dung | F4: số tiền VND | G4: số tiền USD
C5: 1 | E5: Nhà cửa, vật kiến trúc | F5: =SUM(F6:F11) -> 2816980160 | G5: =F5/$G$2 -> 112679.21
A6: Z21180P | B6: TSCĐ khác - SX 627 | C6: =SUBTOTAL(3,$E$6:E6) -> 1 | D6: 115000018 | E6: Cung cấp lắp đặt chiller mở rộng | F6: 1744151201 | G6: =F6/$G$2 -> 69766.048
A7: Z21180P | B7: TSCĐ khác - SX 627 | C7: =SUBTOTAL(3,$E$6:E7) -> 2 | D7: 115000017 | E7: Hệ thống làm mát nhà xưởng (Đợt 3) | F7: 185719645 | G7: =F7/$G$2 -> 7428.7858
A8: Z21110A | B8: Nhà cửa, vật kiến trúc - QL 642 | C8: =SUBTOTAL(3,$E$6:E8) -> 3 | D8: 103000014 | E8: Trồng cỏ, cây xung quanh nhà máy | F8: 160781500 | G8: =F8/$G$2 -> 6431.26
A9: Z21110P | B9: Nhà cửa, vật kiến trúc - SX 627 | C9: =SUBTOTAL(3,$E$6:E9) -> 4 | D9: 101000022 | E9: Phòng thử nghiệm F03 | F9: 33811200 | G9: =F9/$G$2 -> 1352.448
A10: Z21110P | B10: Nhà cửa, vật kiến trúc - SX 627 | C10: =SUBTOTAL(3,$E$6:E10) -> 5 | D10: 101000023 | E10: Lắp đặt mái bạt xếp giữa F2 và E3 | F10: 621093014 | G10: =F10/$G$2 -> 24843.721
A11: Z21110A | B11: Nhà cửa, vật kiến trúc - QL 642 | D11: 103000015 | E11: Phòng Kế toán kho TĐH | F11: 71423600 | G11: =F11/$G$2 -> 2856.944
C12: 2 | E12: Máy móc thiết bị | F12: =SUM(F13:F54) -> 69251846447 | G12: =F12/$G$2 -> 2770073.9
A13: Z21180P | B13: TSCĐ khác - SX 627 | C13: =SUBTOTAL(3,$E$13:E13) -> 1 | D13: 115000016 | E13: Hệ thống XLNT 500 m3/ngày đêm | F13: 22957791544 | G13: =F13/$G$2 -> 918311.66
A14: Z21120P | B14: Máy móc, thiết bị - SX 627 | C14: =SUBTOTAL(3,$E$13:E14) -> 2 | D14: 104000162 | E14: Máy lựa chai Tomra (F4) | F14: 7378320048 | G14: =F14/$G$2 -> 295132.8
A15: Z21120P | B15: Máy móc, thiết bị - SX 627 | C15: =SUBTOTAL(3,$E$13:E15) -> 3 | D15: 104000149 | E15: Trạm điện SX xưởng F03, 05 | F15: 6912429918 | G15: =F15/$G$2 -> 276497.2
A16: Z21120P | B16: Máy móc, thiết bị - SX 627 | C16: =SUBTOTAL(3,$E$13:E16) -> 4 | D16: 104000161 | E16: Máy trộn nhựa KN L10000KG+ | F16: 1896886694 | G16: =F16/$G$2 -> 75875.468
A17: Z211201P | B17: Máy móc, thiết bị phụ - SX 627 | C17: =SUBTOTAL(3,$E$13:E17) -> 5 | D17: 104600091 | E17: Thi công Chuyền máy rửa PP MOOGETECH | F17: 1500556886 | G17: =F17/$G$2 -> 60022.275
A18: Z21120P | B18: Máy móc, thiết bị - SX 627 | C18: =SUBTOTAL(3,$E$13:E18) -> 6 | D18: 104000154 | E18: Chuyền băm rửa PET 03 (Lê Trần) | F18: 1470802869 | G18: =F18/$G$2 -> 58832.115
A19: Z211201P | B19: Máy móc, thiết bị phụ - SX 627 | C19: =SUBTOTAL(3,$E$13:E19) -> 7 | D19: 104600103 | E19: Băng tải+Vít tải phân loại vảy đầu vào W800 (TC) | F19: 1256000000 | G19: =F19/$G$2 -> 50240
A20: Z21120P | B20: Máy móc, thiết bị - SX 627 | C20: =SUBTOTAL(3,$E$13:E20) -> 8 | D20: 104000159 | E20: Máy Tạo Hạt Xơ Sợi YPET-01 | F20: 1128375223 | G20: =F20/$G$2 -> 45135.009
A21: Z21120P | B21: Máy móc, thiết bị - SX 627 | C21: =SUBTOTAL(3,$E$13:E21) -> 9 | D21: 104000160 | E21: Máy Tạo Hạt rPP YEI PP-01 | F21: 936402136 | G21: =F21/$G$2 -> 37456.085
A22: Z21120P | B22: Máy móc, thiết bị - SX 627 | C22: =SUBTOTAL(3,$E$13:E22) -> 10 | D22: 104000150 | E22: Máy Zig-Zag Mooge | F22: 751500302 | G22: =F22/$G$2 -> 30060.012
A23: Z21120P | B23: Máy móc, thiết bị - SX 627 | C23: =SUBTOTAL(3,$E$13:E23) -> 11 | D23: 104000156 | E23: HT Máy tách vảy Taiho Phó sản HD 5 máy (Taiho 3) | F23: 700209603 | G23: =F23/$G$2 -> 28008.384
A24: Z211201P | B24: Máy móc, thiết bị phụ - SX 627 | C24: =SUBTOTAL(3,$E$13:E24) -> 12 | D24: 104600094 | E24: Máy tạo hạt rPP dùng cho phòng Lab | F24: 400000000 | G24: =F24/$G$2 -> 16000
... A53: Z21140A | B53: Thiết bị, dụng cụ quản lý - QL 642 | C53: =SUBTOTAL(3,$E$13:E53) -> 41 | D53: 112000021 | E53: Hệ thống camera DTR (49 cái) | F53: 351402508 | G53: =F53/$G$2 -> 14056.1
C55: 3 | E55: Khuôn đầu tư sản phẩm mới | F55: =SUM(F56:F65) -> 1164204641 | G55: =F55/$G$2 -> 46568.186
A56: Z21180A | B56: TSCĐ khác - QL 642 | C56: =SUBTOTAL(3,$E$56:E56) -> 1 | D56: 117000008 | E56: Khuôn Đầu bút & Thân bút (MIDA) | F56: 235000000 | G56: =F56/$G$2 -> 9400
A57: Z21180A | B57: TSCĐ khác - QL 642 | C57: =SUBTOTAL(3,$E$56:E57) -> 2 | D57: 117000010 | E57: Khuôn lõi bấm & lõi xoay (MIDA) | F57: 211500000 | G57: =F57/$G$2 -> 8460
A58: Z21180A | B58: TSCĐ khác - QL 642 | C58: =SUBTOTAL(3,$E$56:E58) -> 3 | D58: 117000009 | E58: Khuôn đầu ren | F58: 188000000 | G58: =F58/$G$2 -> 7520
A59: Z21180P | B59: TSCĐ khác - SX 627 | C59: =SUBTOTAL(3,$E$56:E59) -> 4 | D59: 115000013 | E59: Khuôn miếng lót ly(F03) | F59: 85500000 | G59: =F59/$G$2 -> 3420
A60: Z21120P | B60: Máy móc, thiết bị - SX 627 | C60: =SUBTOTAL(3,$E$56:E60) -> 5 | D60: 104000153 | E60: Khuôn phôi D28 P19.5 (F03) | F60: 82950000 | G60: =F60/$G$2 -> 3318
A61: Z21180P | B61: TSCĐ khác - SX 627 | C61: =SUBTOTAL(3,$E$56:E61) -> 6 | D61: 115000012 | E61: Khuôn chai nhớt(F02) | F61: 82154641 | G61: =F61/$G$2 -> 3286.1856
A62: Z21180P | B62: TSCĐ khác - SX 627 | C62: =SUBTOTAL(3,$E$56:E62) -> 7 | D62: 115000011 | E62: Khuôn chai nước sưới 350ml(F03) | F62: 62000000 | G62: =F62/$G$2 -> 2480
A63: Z21180P | B63: TSCĐ khác - SX 627 | C63: =SUBTOTAL(3,$E$56:E63) -> 8 | D63: 115000014 | E63: Khuôn chai coca(F03) | F63: 62000000 | G63: =F63/$G$2 -> 2480
A64: Z21180P | B64: TSCĐ khác - SX 627 | C64: =SUBTOTAL(3,$E$56:E64) -> 9 | D64: 115000022 | E64: Bơm chân không Vacuubrand MZ 2C NT+AK+EK | F64: 95100000 | G64: =F64/$G$2 -> 3804
A65: Z21180P | B65: TSCĐ khác - SX 627 | C65: =SUBTOTAL(3,$E$56:E65) -> 10 | D65: 115000024 | E65: Máy ghi điện 3P FLUKE 1730 iFlex6000-36 | F65: 60000000 | G65: =F65/$G$2 -> 2400
C66: 4 | E66: Khuôn đầu tư thay thế | F66: 0 | G66: =F66/$G$2 -> 0
C67: 5 | E67: Phương tiện vận tải | F67: =SUM(F68:F73) -> 306314815 | G67: =F67/$G$2 -> 12252.593
A68: Z21130P | B68: Phương tiện vận tải , truyền dẫn - SX 627 | C68: =SUBTOTAL(3,$E$68:E68) -> 1 | D68: 107000040 | E68: Xe nâng tay điện Heli CBD20-AliH 1 | F68: 37962963 | G68: =F68/$G$2 -> 1518.5185
A69: Z21130P | B69: Phương tiện vận tải , truyền dẫn - SX 627 | C69: =SUBTOTAL(3,$E$68:E69) -> 2 | D69: 107000042 | E69: Xe nâng tay điện Heli CBD20-AliH 2 | F69: 37962963 | G69: =F69/$G$2 -> 1518.5185
A70: Z21130P | B70: Phương tiện vận tải , truyền dẫn - SX 627 | C70: =SUBTOTAL(3,$E$68:E70) -> 3 | D70: 107000043 | E70: Xe nâng tay điện Heli CBD20-AliH 3 | F70: 37962963 | G70: =F70/$G$2 -> 1518.5185
A71: Z21130P | B71: Phương tiện vận tải , truyền dẫn - SX 627 | C71: =SUBTOTAL(3,$E$68:E71) -> 4 | D71: 107000044 | E71: Xe nâng tay điện Heli CBD20-AliH 4 | F71: 37962963 | G71: =F71/$G$2 -> 1518.5185
A72: Z21130P | B72: Phương tiện vận tải , truyền dẫn - SX 627 | C72: =SUBTOTAL(3,$E$68:E72) -> 5 | D72: 107000045 | E72: Xe nâng tay điện Heli CBD20-AliH 5 | F72: 37962963 | G72: =F72/$G$2 -> 1518.5185
A73: Z21130P | B73: Phương tiện vận tải , truyền dẫn - SX 627 | C73: =SUBTOTAL(3,$E$68:E73) -> 6 | D73: 107000046 | E73: XE KÉO NỘI BỘ | F73: 116500000 | G73: =F73/$G$2 -> 4660
C74: 6 | E74: Thiết bị quản lý | F74: =SUM(F75:F75) -> 0 | G74: =F74/$G$2 -> 0
C75: =SUBTOTAL(3,$E$75:E75) -> 0 | G75: =F75/$G$2 -> 0
C76: 7 | E76: Phần mềm vi tính | F76: =SUM(F77:F78) -> 960422938 | G76: =F76/$G$2 -> 38416.918
A77: Z21380A | B77: TSCĐ vô hình khác - QL 642 | C77: =SUBTOTAL(3,$E77:E$78) -> 2 | D77: 151000005 | E77: Gói phần mềm DELFICOM CUSTOMIZE | F77: 431300039 | G77: =F77/$G$2 -> 17252.002
A78: Z21380A | B78: TSCĐ vô hình khác - QL 642 | C78: =SUBTOTAL(3,$E$78:E78) -> 1 | D78: 151000006 | E78: License SAP 2024 | F78: 529122899 | G78: =F78/$G$2 -> 21164.916
C79: 8 | E79: Khác | G79: =F79/$G$2 -> 0

Sheet Capex TT 2023
E1: ĐẦU TƯ CAPEX THỰC TẾ 2023
F2: Tỷ giá: | G2: 24700
F3: =SUM(F5,F24,F86,F88,F89,F104,F110,F112) -> 57892496559 | G3: =SUM(G5,G24,G86,G88,G89,G104,G110,G112) -> 2343825.8
A4: Nhóm tài sản (SAP) | B4: Tên Nhóm tài sản (SAP) | C4: STT | D4: Mã TS | E4: Nội dung | F4: số tiền VND | G4: số tiền USD
C5: 1 | E5: Nhà cửa, vật kiến trúc | F5: =SUM(F6:F23) -> 4510827128 | G5: =F5/$G$2 -> 182624.58
A6: Z21110P | B6: Nhà cửa, vật kiến trúc - SX 627 | C6: =SUBTOTAL(3,$E$6:E6) -> 1 | D6: 101000019 | E6: Hệ thống làm mát nhà xưởng | F6: 958076791 | G6: =F6/$G$2 -> 38788.534
A7: Z21180A | B7: TSCĐ khác - QL 642 | C7: =SUBTOTAL(3,$E$6:E7) -> 2 | D7: 117000002 | E7: Hạng mục phụ nhà xưởng (VP F02, bó vĩa, điện, sơn) | F7: 807761229 | G7: =F7/$G$2 -> 32702.884
A8: Z21110A | B8: Nhà cửa, vật kiến trúc - QL 642 | C8: =SUBTOTAL(3,$E$6:E8) -> 3 | D8: 103000008 | E8: Ốp gạch và trồng cỏ nhà xưởng | F8: 309657600 | G8: =F8/$G$2 -> 12536.745
A9: Z21180A | B9: TSCĐ khác - QL 642 | C9: =SUBTOTAL(3,$E$6:E9) -> 4 | D9: 117000001 | E9: Nguồn bơm giếng và tưới cỏ | F9: 308593906 | G9: =F9/$G$2 -> 12493.68
A10: Z21110P | B10: Nhà cửa, vật kiến trúc - SX 627 | C10: =SUBTOTAL(3,$E$6:E10) -> 5 | D10: 101000018 | E10: Lắp vít tải phân loại vảy đầu vào | F10: 304857717 | G10: =F10/$G$2 -> 12342.418
A11: Z21110A | B11: Nhà cửa, vật kiến trúc - QL 642 | C11: =SUBTOTAL(3,$E$6:E11) -> 6 | D11: 103000009 | E11: Thi công các hạng mục xây dựng nhà xưởng | F11: 278150000 | G11: =F11/$G$2 -> 11261.134
A12: Z21110A | B12: Nhà cửa, vật kiến trúc - QL 642 | C12: =SUBTOTAL(3,$E$6:E12) -> 7 | D12: 103000007 | E12: Đường nước tưới cây xung quanh nhà máy | F12: 267942150 | G12: =F12/$G$2 -> 10847.86
A13: Z21180A | B13: TSCĐ khác - QL 642 | C13: =SUBTOTAL(3,$E$6:E13) -> 8 | D13: 117000007 | E13: Lắp đặt cáp thoại nhà bảo vệ 1 và 3 | F13: 261991507 | G13: =F13/$G$2 -> 10606.944
A14: Z21110A | B14: Nhà cửa, vật kiến trúc - QL 642 | C14: =SUBTOTAL(3,$E$6:E14) -> 9 | D14: 103000005 | E14: Cửa cổng chính số 02 và 03 | F14: 184508875 | G14: =F14/$G$2 -> 7469.9949
A15: Z21110A | B15: Nhà cửa, vật kiến trúc - QL 642 | C15: =SUBTOTAL(3,$E$6:E15) -> 10 | D15: 103000006 | E15: Lắp đặt nhôm kính phòng Kỹ Thuật | F15: 174699000 | G15: =F15/$G$2 -> 7072.834
A16: Z21110A | B16: Nhà cửa, vật kiến trúc - QL 642 | C16: =SUBTOTAL(3,$E$6:E16) -> 11 | D16: 103000010 | E16: Nhà chứa bùn F05 | F16: 118791283 | G16: =F16/$G$2 -> 4809.3637
A17: Z21110A | B17: Nhà cửa, vật kiến trúc - QL 642 | C17: =SUBTOTAL(3,$E$6:E17) -> 12 | D17: 103000011 | E17: Hệ thống giữ xe | F17: 117700000 | G17: =F17/$G$2 -> 4765.1822
... A23: Z21180P | B23: TSCĐ khác - SX 627 | C23: =SUBTOTAL(3,$E$6:E23) -> 18 | D23: 115000008 | E23: Thi công nhà bạt F6 | F23: 53030000 | G23: =F23/$G$2 -> 2146.9636
C24: 2 | E24: Máy móc thiết bị | F24: =SUM(F25:F85) -> 47513794431 | G24: =F24/$G$2 -> 1923635.4
A25: Z21180P | B25: TSCĐ khác - SX 627 | C25: =SUBTOTAL(3,$E$25:E25) -> 1 | D25: 115000010 | E25: Hệ thống XLNT 400m3/ngày đêm | F25: 6445602086 | G25: =F25/$G$2 -> 260955.55
A26: Z21120P | B26: Máy móc, thiết bị - SX 627 | C26: =SUBTOTAL(3,$E$25:E26) -> 2 | D26: 104000097 | E26: Thiết bị phụ chuyền máy Starlinger 2 | F26: 4460334770 | G26: =F26/$G$2 -> 180580.36
A27: Z21120P | B27: Máy móc, thiết bị - SX 627 | C27: =SUBTOTAL(3,$E$25:E27) -> 3 | D27: 104000125 | E27: Chuyền băm PET số 02 | F27: 3033103521 | G27: =F27/$G$2 -> 122797.71
A28: Z21120P | B28: Máy móc, thiết bị - SX 627 | C28: =SUBTOTAL(3,$E$25:E28) -> 4 | D28: 104000124 | E28: Máy lựa vảy UV Meyer | F28: 2396767041 | G28: =F28/$G$2 -> 97035.103
A29: Z21120P | B29: Máy móc, thiết bị - SX 627 | C29: =SUBTOTAL(3,$E$25:E29) -> 5 | D29: 104000126 | E29: Chuyền rửa vảy CW2 | F29: 2381394958 | G29: =F29/$G$2 -> 96412.751
A30: Z21120P | B30: Máy móc, thiết bị - SX 627 | C30: =SUBTOTAL(3,$E$25:E30) -> 6 | D30: 104000113 | E30: Hệ thống phối trộn tự động WSB - 3000T | F30: 2135314321 | G30: =F30/$G$2 -> 86449.973
A31: Z21120P | B31: Máy móc, thiết bị - SX 627 | C31: =SUBTOTAL(3,$E$25:E31) -> 7 | D31: 104000102 | E31: Máy tách màu Taiho 6SXM-10008FS | F31: 1885681729 | G31: =F31/$G$2 -> 76343.39
A32: Z21120P | B32: Máy móc, thiết bị - SX 627 | C32: =SUBTOTAL(3,$E$25:E32) -> 8 | D32: 104000098 | E32: Máy tách màu Taiho 6SXM-10008FS - 2 | F32: 1856733952 | G32: =F32/$G$2 -> 75171.415
A33: Z21120P | B33: Máy móc, thiết bị - SX 627 | C33: =SUBTOTAL(3,$E$25:E33) -> 9 | D33: 104000109 | E33: Máy tách màu Taiho số 3 | F33: 1849055197 | G33: =F33/$G$2 -> 74860.534
A34: Z21120P | B34: Máy móc, thiết bị - SX 627 | C34: =SUBTOTAL(3,$E$25:E34) -> 10 | D34: 104000140 | E34: Chuyền tạo hạt rPP số 2 (Yei) | F34: 1798575168 | G34: =F34/$G$2 -> 72816.808
A35: Z21120P | B35: Máy móc, thiết bị - SX 627 | C35: =SUBTOTAL(3,$E$25:E35) -> 11 | D35: 104000135 | E35: Trạm điện 4x3000kVA-22V/0,4kV | F35: 1782611000 | G35: =F35/$G$2 -> 72170.486
A36: Z211201P | B36: Máy móc, thiết bị phụ - SX 627 | C36: =SUBTOTAL(3,$E$25:E36) -> 12 | D36: 104600079 | E36: Máy đo độ nhớt nội hạt nhựa - 1 | F36: 1495635731 | G36: =F36/$G$2 -> 60552.054
... A45: Z21120P | B45: Máy móc, thiết bị - SX 627 | C45: =SUBTOTAL(3,$E$25:E45) -> 21 | D45: 104000121 | E45: Tủ điện 1600A (Yei) | F45: 460772000 | G45: =F45/$G$2 -> 18654.737
A46: Z211201P | B46: Máy móc, thiết bị phụ - SX 627 | C46: =SUBTOTAL(3,$E$25:E46) -> 22 | D46: 104600082 | E46: Chi phí vận chuyển lắp đặt máy | F46: 422500000 | G46: =F46/$G$2 -> 17105.263 | H46: ???
A47: Z21120P | B47: Máy móc, thiết bị - SX 627 | C47: =SUBTOTAL(3,$E$25:E47) -> 23 | D47: 104000141 | E47: Máy tạo hạt trục vít đôi CJWH25-42D-11Kw | F47: 411877593 | G47: =F47/$G$2 -> 16675.206
A48: Z21120P | B48: Máy móc, thiết bị - SX 627 | C48: =SUBTOTAL(3,$E$25:E48) -> 24 | D48: 104000130 | E48: Máy đo chỉ số chảy MI nhựa HDPE | F48: 409250000 | G48: =F48/$G$2 -> 16568.826
A49: Z21120P | B49: Máy móc, thiết bị - SX 627 | C49: =SUBTOTAL(3,$E$25:E49) -> 25 | D49: 104000112 | E49: Máy băm rửa Changwoen | F49: 380542065 | G49: =F49/$G$2 -> 15406.561
A50: Z21120P | B50: Máy móc, thiết bị - SX 627 | C50: =SUBTOTAL(3,$E$25:E50) -> 26 | D50: 104000139 | E50: Cấp nguồn xưởng F2 | F50: 374180000 | G50: =F50/$G$2 -> 15148.988
A51: Z21120P | B51: Máy móc, thiết bị - SX 627 | C51: =SUBTOTAL(3,$E$25:E51) -> 27 | D51: 104000132 | E51: Máy đo chỉ số chảy MI nhựa PP | F51: 366850000 | G51: =F51/$G$2 -> 14852.227
A52: Z21120P | B52: Máy móc, thiết bị - SX 627 | C52: =SUBTOTAL(3,$E$25:E52) -> 28 | D52: 104000115 | E52: Máy trộn nhựa KLN 500kg | F52: 365416370 | G52: =F52/$G$2 -> 14794.185
A53: Z21120P | B53: Máy móc, thiết bị - SX 627 | C53: =SUBTOTAL(3,$E$25:E53) -> 29 | D53: 104000119 | E53: Máy thổi Chumpower | F53: 360577908 | G53: =F53/$G$2 -> 14598.296
A54: Z21120P | B54: Máy móc, thiết bị - SX 627 | C54: =SUBTOTAL(3,$E$25:E54) -> 30 | D54: 104000128 | E54: Máy nghiền nhựa HGP-800-30HP-22.5KW | F54: 343273414 | G54: =F54/$G$2 -> 13897.709
A55: Z211201P | B55: Máy móc, thiết bị phụ - SX 627 | C55: =SUBTOTAL(3,$E$25:E55) -> 31 | D55: 104600075 | E55: Khuôn can chiếc lá Akei | F55: 333889440 | G55: =F55/$G$2 -> 13517.791
A56: Z21120P | B56: Máy móc, thiết bị - SX 627 | C56: =SUBTOTAL(3,$E$25:E56) -> 32 | D56: 104000114 | E56: Tủ điện bên trong xưởng F04 | F56: 321444214 | G56: =F56/$G$2 -> 13013.936
A57: Z21120A | B57: Máy móc, thiết bị - QL 642 | C57: =SUBTOTAL(3,$E$25:E57) -> 33 | D57: 106000008 | E57: Hệ lọc RO và hệ đóng nước bình | F57: 296505989 | G57: =F57/$G$2 -> 12004.291
A58: Z21120A | B58: Máy móc, thiết bị - QL 642 | C58: =SUBTOTAL(3,$E$25:E58) -> 34 | D58: 106000012 | E58: Máy làm đá Manitowoc IDT1500W-251 | F58: 267417833 | G58: =F58/$G$2 -> 10826.633
... A85: Z21120P | B85: Máy móc, thiết bị - SX 627 | C85: =SUBTOTAL(3,$E$25:E85) -> 61 | D85: 104000105 | E85: Cân 2 chữ số | F85: 8144000 | G85: =F85/$G$2 -> 329.7166
C86: 3 | E86: Khuôn đầu tư sản phẩm mới | F86: =F87 -> 79900000 | G86: =F86/$G$2 -> 3234.8178
C87: 1 | D87: 104600085 | E87: Khuôn Pilot Phôi ren D28 P18 1cav K1 | F87: 79900000 | G87: 3234.8178
C88: 4 | E88: Khuôn đầu tư thay thế | F88: 0 | G88: =F88/$G$2 -> 0
C89: 5 | E89: Phương tiện vận tải | F89: =SUM(F90:F103) -> 5418910000 | G89: =F89/$G$2 -> 219389.07
A90: Z21130P | B90: Phương tiện vận tải , truyền dẫn - SX 627 | C90: =SUBTOTAL(3,$E$90:E90) -> 1 | D90: 107000033 | E90: Xe nâng dầu 2,5 tấn Komatsu - 21 | F90: 515000000 | G90: =F90/$G$2 -> 20850.202
A91: Z21130P | B91: Phương tiện vận tải , truyền dẫn - SX 627 | C91: =SUBTOTAL(3,$E$90:E91) -> 2 | D91: 107000036 | E91: Xe nâng dầu 2,5 tấn Komatsu - 24 | F91: 515000000 | G91: =F91/$G$2 -> 20850.202
A92: Z21130P | B92: Phương tiện vận tải , truyền dẫn - SX 627 | C92: =SUBTOTAL(3,$E$90:E92) -> 3 | D92: 107000029 | E92: Xê nâng người SJ4726 | F92: 490110000 | G92: =F92/$G$2 -> 19842.51
A93: Z21130P | B93: Phương tiện vận tải , truyền dẫn - SX 627 | C93: =SUBTOTAL(3,$E$90:E93) -> 4 | D93: 107000031 | E93: Xe nâng dầu 2.5 tấn Komatsu - 18 | F93: 480000000 | G93: =F93/$G$2 -> 19433.198
A94: Z21130P | B94: Phương tiện vận tải , truyền dẫn - SX 627 | C94: =SUBTOTAL(3,$E$90:E94) -> 5 | D94: 107000034 | E94: Xe nâng dầu 2,5 tấn Komatsu - 22 | F94: 465000000 | G94: =F94/$G$2 -> 18825.911
A95: Z21130P | B95: Phương tiện vận tải , truyền dẫn - SX 627 | C95: =SUBTOTAL(3,$E$90:E95) -> 6 | D95: 107000035 | E95: Xe nâng dầu 2,5 tấn Komatsu - 23 | F95: 465000000 | G95: =F95/$G$2 -> 18825.911
A96: Z21130P | B96: Phương tiện vận tải , truyền dẫn - SX 627 | C96: =SUBTOTAL(3,$E$90:E96) -> 7 | D96: 107000038 | E96: Xe nâng dầu 2,5 tấn Komatsu - Nhật Bản | F96: 465000000 | G96: =F96/$G$2 -> 18825.911
A97: Z21130P | B97: Phương tiện vận tải , truyền dẫn - SX 627 | C97: =SUBTOTAL(3,$E$90:E97) -> 8 | D97: 107000026 | E97: Xe nâng dầu 2.5 tấn Komatsu - 16 | F97: 450000000 | G97: =F97/$G$2 -> 18218.623
A98: Z21130P | B98: Phương tiện vận tải , truyền dẫn - SX 627 | C98: =SUBTOTAL(3,$E$90:E98) -> 9 | D98: 107000030 | E98: Xe nâng dầu 2.5 tấn Komatsu - 17 | F98: 450000000 | G98: =F98/$G$2 -> 18218.623
A99: Z21130P | B99: Phương tiện vận tải , truyền dẫn - SX 627 | C99: =SUBTOTAL(3,$E$90:E99) -> 10 | D99: 107000013 | E99: Xe nâng hiệu Komatsu FD25T-17,khung :M228-307295 | F99: 430000000 | G99: =F99/$G$2 -> 17408.907
A100: Z21130A | B100: Phương tiện vận tải , truyền dẫn - QL 642 | C100: =SUBTOTAL(3,$E$90:E100) -> 11 | D100: 109000001 | E100: Xe chở khách LVTONG model: LT-S14 | F100: 280000000 | G100: =F100/$G$2 -> 11336.032
A101: Z21130A | B101: Phương tiện vận tải , truyền dẫn - QL 642 | C101: =SUBTOTAL(3,$E$90:E101) -> 12 | D101: 109000002 | E101: Xe chở khách LVTONG model: LT-S08 | F101: 210000000 | G101: =F101/$G$2 -> 8502.0243
... A103: Z21130P | B103: Phương tiện vận tải , truyền dẫn - SX 627 | C103: =SUBTOTAL(3,$E$90:E103) -> 14 | D103: 107000039 | E103: Xe nâng điện PSE12N36 | F103: 81300000 | G103: =F103/$G$2 -> 3291.498
C104: 6 | E104: Thiết bị quản lý | F104: =SUM(F105:F109) -> 369065000 | G104: =F104/$G$2 -> 14941.903
A105: Z21140A | B105: Thiết bị, dụng cụ quản lý - QL 642 | C105: =SUBTOTAL(3,$E$105:E105) -> 1 | D105: 112000013 | E105: Hệ thống bảng hiệu, logo nhà máy | F105: 110306000 | G105: =F105/$G$2 -> 4465.83
A106: Z21120A | B106: Máy móc, thiết bị - QL 642 | C106: =SUBTOTAL(3,$E$105:E106) -> 2 | D106: 106000010 | E106: Mobility Cotroller - 1 | F106: 85559000 | G106: =F106/$G$2 -> 3463.9271
A107: Z21120A | B107: Máy móc, thiết bị - QL 642 | C107: =SUBTOTAL(3,$E$105:E107) -> 3 | D107: 106000011 | E107: Mobility Cotroller - 2 | F107: 85559000 | G107: =F107/$G$2 -> 3463.9271
A108: Z21140A | B108: Thiết bị, dụng cụ quản lý - QL 642 | C108: =SUBTOTAL(3,$E$105:E108) -> 4 | D108: 112000012 | E108: Máy tính Dell XPS 15 9520 | F108: 53420000 | G108: =F108/$G$2 -> 2162.753
A109: Z21140A | B109: Thiết bị, dụng cụ quản lý - QL 642 | C109: =SUBTOTAL(3,$E$105:E109) -> 5 | D109: 112000018 | E109: Máy lạnh FTKY60WVMV/RKY60WVMV | F109: 34221000 | G109: =F109/$G$2 -> 1385.4656
C110: 7 | E110: Phần mềm vi tính | F110: =SUM(F111:F111) -> 0 | G110: =F110/$G$2 -> 0
C111: =SUBTOTAL(3,$E$111:E111) -> 0 | G111: =F111/$G$2 -> 0
C112: 8 | E112: Khác | G112: =F112/$G$2 -> 0

Sheet Capex TT 2022
E1: ĐẦU TƯ CAPEX THỰC TẾ 2022
F2: Tỷ giá: | G2: 24500
F3: =SUM(F5,F9,F57,F59,F60,F72,F80,F85) -> 46331487657 | G3: =SUM(G5,G9,G57,G59,G60,G72,G80,G85) -> 1891081.1
A4: Nhóm tài sản (SAP) | B4: Tên Nhóm tài sản (SAP) | C4: STT | D4: Mã TS | E4: Nội dung | F4: số tiền VND | G4: số tiền USD
C5: 1 | E5: Nhà cửa, vật kiến trúc | F5: =SUM(F6:F8) -> 430790000 | G5: =F5/$G$2 -> 17583.265
A6: Z21140A | B6: Thiết bị, dụng cụ quản lý - QL 642 | C6: 1 | D6: 113000001 | E6: Thi công hồ cá | F6: 322740000 | G6: =F6/$G$2 -> 13173.061
A7: Z21140A | B7: Thiết bị, dụng cụ quản lý - QL 642 | C7: 2 | D7: 115000004 | E7: Mái che xếp di động (Nam Trần) | F7: 60800000 | G7: =F7/$G$2 -> 2481.6327
A8: Z21140A | B8: Thiết bị, dụng cụ quản lý - QL 642 | C8: 3 | D8: 159000058 | E8: Thi công đường bê tông nhựa | F8: 47250000 | G8: =F8/$G$2 -> 1928.5714
C9: 2 | E9: Máy móc thiết bị | F9: =SUM(F10:F56) -> 36050065845 | G9: =F9/$G$2 -> 1471431.3
A10: Z21140P | B10: Thiết bị, dụng cụ quản lý - SX 627 | C10: =SUBTOTAL(3,$E$10:E10) -> 1 | D10: 158000050 | E10: Chuyền băm rửa Boretech | F10: 16147060879 | G10: =F10/$G$2 -> 659063.71
A11: Z21120P | B11: Máy móc, thiết bị - SX 627 | C11: =SUBTOTAL(3,$E$10:E11) -> 2 | D11: 104000094 | E11: Chuyền băm rửa chai HDPE | F11: 4051850083 | G11: =F11/$G$2 -> 165381.64
A12: Z211201P | B12: Máy móc, thiết bị phụ - SX 627 | C12: =SUBTOTAL(3,$E$10:E12) -> 3 | D12: 104600058 | E12: Máy làm lạnh nước- nước giải nhiệt | F12: 1667705806 | G12: =F12/$G$2 -> 68069.625
A13: Z21120P | B13: Máy móc, thiết bị - SX 627 | C13: =SUBTOTAL(3,$E$10:E13) -> 4 | D13: 104000084 | E13: Máy tạo hạt rHDPE 03 (Polystar) | F13: 1414330740 | G13: =F13/$G$2 -> 57727.785
A14: Z211201P | B14: Máy móc, thiết bị phụ - SX 627 | C14: =SUBTOTAL(3,$E$10:E14) -> 5 | D14: 104600067 | E14: Hệ thống Silo vảy PET | F14: 1119518319 | G14: =F14/$G$2 -> 45694.625
A15: Z211201P | B15: Máy móc, thiết bị phụ - SX 627 | C15: =SUBTOTAL(3,$E$10:E15) -> 6 | D15: 104600059 | E15: Thiết bị cân xe Mettler Toledo | F15: 1067096720 | G15: =F15/$G$2 -> 43554.968
A16: Z21120P | B16: Máy móc, thiết bị - SX 627 | C16: =SUBTOTAL(3,$E$10:E16) -> 7 | D16: 104000080 | E16: Kính hiển vi Keyence | F16: 1062500000 | G16: =F16/$G$2 -> 43367.347
A17: Z21120P | B17: Máy móc, thiết bị - SX 627 | C17: =SUBTOTAL(3,$E$10:E17) -> 8 | D17: 104000092 | E17: Máy ép kiện XTY-600WB10080, seri 22203835 | F17: 941175390 | G17: =F17/$G$2 -> 38415.322
A18: Z21130P | B18: Phương tiện vận tải , truyền dẫn - SX 627 | C18: =SUBTOTAL(3,$E$10:E18) -> 9 | D18: 107000018 | E18: Băng tải nghiêng cấp chai vào máy 21108 | F18: 600000000 | G18: =F18/$G$2 -> 24489.796
A19: Z211201P | B19: Máy móc, thiết bị phụ - SX 627 | C19: =SUBTOTAL(3,$E$10:E19) -> 10 | D19: 104600074 | E19: Máy phân tích màu quang phổ CM-36DG | F19: 559630200 | G19: =F19/$G$2 -> 22842.049
A20: Z21120P | B20: Máy móc, thiết bị - SX 627 | C20: =SUBTOTAL(3,$E$10:E20) -> 11 | D20: 104000081 | E20: Phòng tiêu âm máy nghiền nhựa | F20: 551292212 | G20: =F20/$G$2 -> 22501.723
A21: Z21130P | B21: Phương tiện vận tải , truyền dẫn - SX 627 | C21: =SUBTOTAL(3,$E$10:E21) -> 12 | D21: 107000021 | E21: Băng tải nối tiếp chuyền lựa chai CW (Plenma) | F21: 472000000 | G21: =F21/$G$2 -> 19265.306
... A56: Z21120P | B56: Máy móc, thiết bị - SX 627 | C56: =SUBTOTAL(3,$E$10:E56) -> 47 | D56: 104000074 | E56: Máy khuấy đũa (cơ) | F56: 33250000 | G56: =F56/$G$2 -> 1357.1429
C57: 3 | E57: Khuôn đầu tư sản phẩm mới | F57: =F58 -> 60000000 | G57: =F57/$G$2 -> 2448.9796
A58: Z211201P | B58: Máy móc, thiết bị phụ - SX 627 | C58: =SUBTOTAL(3,$E$10:E58) -> 49 | D58: 104600049 | E58: Khuôn thẻ nhựa PET | F58: 60000000 | G58: =F58/$G$2 -> 2448.9796
C59: 4 | E59: Khuôn đầu tư thay thế | F59: 0 | G59: =F59/$G$2 -> 0
C60: 5 | E60: Phương tiện vận tải | F60: =SUM(F61:F71) -> 7797835728 | G60: =F60/$G$2 -> 318279.01
A61: Z21130P | B61: Phương tiện vận tải , truyền dẫn - SX 627 | C61: =SUBTOTAL(3,$E$61:E61) -> 1 | D61: 107000027 | E61: Xe ô tô tải ISUZU FVR34UE4 - 62C-179.12 | F61: 1309027251 | G61: =F61/$G$2 -> 53429.684
A62: Z21130P | B62: Phương tiện vận tải , truyền dẫn - SX 627 | C62: =SUBTOTAL(3,$E$61:E62) -> 2 | D62: 107000028 | E62: Xe ô tô tải ISUZU FVR34UE4 - 62C-179.36 | F62: 1309027247 | G62: =F62/$G$2 -> 53429.684
A63: Z21130P | B63: Phương tiện vận tải , truyền dẫn - SX 627 | C63: =SUBTOTAL(3,$E$61:E63) -> 3 | D63: 107000020 | E63: Xe ôtô tải hiệu Chenglong LZ1250M5DBT | F63: 1191602171 | G63: =F63/$G$2 -> 48636.823
A64: Z21130P | B64: Phương tiện vận tải , truyền dẫn - SX 627 | C64: =SUBTOTAL(3,$E$61:E64) -> 4 | D64: 107000022 | E64: Xe nâng hiệu KomatsuFD25C-16 M228-742540 | F64: 877179059 | G64: =F64/$G$2 -> 35803.227
A65: Z21130P | B65: Phương tiện vận tải , truyền dẫn - SX 627 | C65: =SUBTOTAL(3,$E$61:E65) -> 5 | D65: 107000010 | E65: Xe nâng hiệu Komatsu, Model:FD30T-17 (Nhật Bản) | F65: 555000000 | G65: =F65/$G$2 -> 22653.061
A66: Z21130P | B66: Phương tiện vận tải , truyền dẫn - SX 627 | C66: =SUBTOTAL(3,$E$61:E66) -> 6 | D66: 107000023 | E66: Xe nâng dầu Komatsu 3 tấn - xe 13 | F66: 480000000 | G66: =F66/$G$2 -> 19591.837
A67: Z21130P | B67: Phương tiện vận tải , truyền dẫn - SX 627 | C67: =SUBTOTAL(3,$E$61:E67) -> 7 | D67: 107000024 | E67: Xe nâng dầu Komatsu 3 tấn - xe 14 | F67: 475000000 | G67: =F67/$G$2 -> 19387.755
A68: Z21130P | B68: Phương tiện vận tải , truyền dẫn - SX 627 | C68: =SUBTOTAL(3,$E$61:E68) -> 8 | D68: 107000017 | E68: Xe nâng dầu Komatsu FD30C-17, M229-319893, 4D94LE | F68: 470000000 | G68: =F68/$G$2 -> 19183.673
A69: Z21130P | B69: Phương tiện vận tải , truyền dẫn - SX 627 | C69: =SUBTOTAL(3,$E$61:E69) -> 9 | D69: 107000025 | E69: Xe nâng dầu 2.5 tấn Komatsu - 15 | F69: 450000000 | G69: =F69/$G$2 -> 18367.347
A70: Z21130P | B70: Phương tiện vận tải , truyền dẫn - SX 627 | C70: =SUBTOTAL(3,$E$61:E70) -> 10 | D70: 108000000 | E70: Xe nâng hiệu Komatsu đã qua sử dụng FD30T-17 | F70: 390000000 | G70: =F70/$G$2 -> 15918.367
A71: Z21130P | B71: Phương tiện vận tải , truyền dẫn - SX 627 | C71: =SUBTOTAL(3,$E$61:E71) -> 11 | D71: 107000016 | E71: Xe nâng điện Komatsu Model : FB18RL-15 | F71: 291000000 | G71: =F71/$G$2 -> 11877.551
C72: 6 | E72: Thiết bị quản lý | F72: =SUM(F73:F79) -> 1208647832 | G72: =F72/$G$2 -> 49332.565
A73: Z21140A | B73: Thiết bị, dụng cụ quản lý - QL 642 | C73: =SUBTOTAL(3,$E$11:E73) -> 63 | D73: 151000004 | E73: Hệ thống Server ERP SAP và Network SDWAN | F73: 987208013 | G73: =F73/$G$2 -> 40294.205
A74: Z21140A | B74: Thiết bị, dụng cụ quản lý - QL 642 | C74: =SUBTOTAL(3,$E$11:E74) -> 64 | D74: 112000003 | E74: Tivi Sony 4K 85 inch KD-85X86J+vật tư - số 1 | F74: 46318182 | G74: =F74/$G$2 -> 1890.538
A75: Z21150A | B75: Cây lâu năm, súc vật làm việc và cho sản phẩm | C75: =SUBTOTAL(3,$E$11:E75) -> 65 | D75: 112000004 | E75: Tivi Sony 4K 85 inch KD-85X86J+vật tư - số 2 | F75: 46318182 | G75: =F75/$G$2 -> 1890.538
A76: Z21180P | B76: TSCĐ khác - SX 627 | C76: =SUBTOTAL(3,$E$11:E76) -> 66 | D76: 112000006 | E76: iPad Pro 12.9 2021+phím+bút - GĐNM | F76: 43445455 | G76: =F76/$G$2 -> 1773.2839
A77: Z21380A | B77: TSCĐ vô hình khác - QL 642 | C77: =SUBTOTAL(3,$E$11:E77) -> 67 | D77: 110000003 | E77: Đèn diệt côn trùng ZE-122 (20 cái) | F77: 42000000 | G77: =F77/$G$2 -> 1714.2857
A78: Z24110 | B78: XDCB dở dang: Đầu tư chế tạo TCSĐ | C78: =SUBTOTAL(3,$E$11:E78) -> 68 | D78: 112000005 | E78: Thiết bị Logitech Group video,loa,mic,cáp+lắp đặt | F78: 35838000 | G78: =F78/$G$2 -> 1462.7755
A79: Z24120 | B79: XDCB dở dang: Xây dựng cơ bản | C79: =SUBTOTAL(3,$E$11:E79) -> 69 | D79: 112000002 | E79: Máy in đa chức năng HP LaserJet Pro MFP M428FDW | F79: 7520000 | G79: =F79/$G$2 -> 306.93878
C80: 7 | E80: Phần mềm vi tính | F80: =SUM(F81:F84) -> 784148252 | G80: =F80/$G$2 -> 32006.051
A81: Z21350S | B81: Phần mềm máy vi tính - BH 641 | C81: =SUBTOTAL(3,$E$81:E81) -> 1 | D81: 151000003 | E81: Phần mềm SQL Server và Backup Commvault | F81: 303920466 | G81: =F81/$G$2 -> 12404.917
A82: Z21380A | B82: TSCĐ vô hình khác - QL 642 | C82: =SUBTOTAL(3,$E$81:E82) -> 2 | D82: 151000002 | E82: Phần mềm SAP | F82: 215935347 | G82: =F82/$G$2 -> 8813.6876
A83: Z21380A | B83: TSCĐ vô hình khác - QL 642 | C83: =SUBTOTAL(3,$E$81:E83) -> 3 | D83: 146000001 | E83: Phần mềm Base Chuyên sâu | F83: 211690000 | G83: =F83/$G$2 -> 8640.4082
A84: Z21380A | B84: TSCĐ vô hình khác - QL 642 | C84: =SUBTOTAL(3,$E$81:E84) -> 4 | D84: 151000001 | E84: Phần mềm QL nhân sự & tiền lương FPT.iHRP | F84: 52602439 | G84: =F84/$G$2 -> 2147.0383
C85: 8 | E85: Khác | G85: =F85/$G$2 -> 0

Sheet Capex TT 2021
E1: ĐẦU TƯ CAPEX THỰC TẾ 2021
F2: Tỷ giá: | G2: 24300
F3: =SUM(F5,F13,F53,F55,F56,F64,F68,F71) -> 262891909295 | G3: =SUM(G5,G13,G53,G55,G56,G64,G68,G71) -> 10818597
A4: Nhóm tài sản (SAP) | B4: Tên Nhóm tài sản (SAP) | C4: STT | D4: Mã TS | E4: Nội dung | F4: số tiền VND | G4: số tiền USD
C5: 1 | E5: Nhà cửa, vật kiến trúc | F5: =SUM(F6:F12) -> 43511003207 | G5: =F5/$G$2 -> 1790576.3
A6: Z21110P | B6: Nhà cửa, vật kiến trúc - SX 627 | D6: 101000000 | E6: Nhà xưởng số 03 | F6: 23455092161 | G6: =F6/$G$2 -> 965230.13 | I6: Có trong file Thạnh Phát
A7: Z21110P | B7: Nhà cửa, vật kiến trúc - SX 627 | D7: 103000002 | E7: Văn phòng xưởng 03 | F7: 13526642799 | G7: =F7/$G$2 -> 556651.97 | I7: Có trong file Thạnh Phát
A8: Z21110P | B8: Nhà cửa, vật kiến trúc - SX 627 | D8: 101000001 | E8: Hạng mục làm đường nhà máy | F8: 3206333890 | G8: =F8/$G$2 -> 131947.9 | I8: Có trong file Thạnh Phát
A9: Z21110P | B9: Nhà cửa, vật kiến trúc - SX 627 | D9: 103000001 | E9: Thiết kế nội thất văn phòng xưởng 03 | F9: 2813240158 | G9: =F9/$G$2 -> 115771.2 | I9: Có trong file Thạnh Phát
A10: Z21110P | B10: Nhà cửa, vật kiến trúc - SX 627 | D10: 101000002 | E10: Nhà kho lều bạt | F10: 445541459 | G10: =F10/$G$2 -> 18335.039 | I10: Có trong file Thạnh Phát
A11: Z21110P | B11: Nhà cửa, vật kiến trúc - SX 627 | D11: 103000000 | E11: Nhà để xe CNV | F11: 36001880 | G11: =F11/$G$2 -> 1481.5588 | I11: Có trong file Thạnh Phát
A12: Z21180A | B12: TSCĐ khác - QL 642 | D12: 117000000 | E12: Nhà chứa rác thải nguy hại | F12: 28150860 | G12: =F12/$G$2 -> 1158.4716 | I12: Có trong file Thạnh Phát
C13: 2 | E13: Máy móc thiết bị | F13: =SUM(F14:F52) -> 214888211254 | G13: =F13/$G$2 -> 8843136.3
A14: Z21120P | B14: Máy móc, thiết bị - SX 627 | D14: 104000068 | E14: Hệ thống xử lý nước thải ChengWoen | F14: 46273512763 | G14: =F14/$G$2 -> 1904259.8
A15: Z21120P | B15: Máy móc, thiết bị - SX 627 | D15: 104000070 | E15: Máy nâng IV Starlinger (SSP) | F15: 42617633391 | G15: =F15/$G$2 -> 1753812.1
A16: Z21120P | B16: Máy móc, thiết bị - SX 627 | D16: 104000069 | E16: Máy tạo hạt Starlinger (PET02) | F16: 40239524497 | G16: =F16/$G$2 -> 1655947.5
A17: Z21120P | B17: Máy móc, thiết bị - SX 627 | D17: 104000067 | E17: Chuyền tạo vảy rPET - ChengWoen | F17: 37079055498 | G17: =F17/$G$2 -> 1525887.1
A18: Z21120P | B18: Máy móc, thiết bị - SX 627 | D18: 104000071 | E18: Máy tạo hạt rHDPE - 01 | F18: 8257058918 | G18: =F18/$G$2 -> 339796.66
A19: Z21120P | B19: Máy móc, thiết bị - SX 627 | D19: 104000065 | E19: Máy Tách màu Taiho | F19: 1871585340 | G19: =F19/$G$2 -> 77019.973
A20: Z21120P | B20: Máy móc, thiết bị - SX 627 | D20: 104000066 | E20: Máy trộn hạt nhựa 2 tấn | F20: 150000000 | G20: =F20/$G$2 -> 6172.8395
A21: Z211201P | B21: Máy móc, thiết bị phụ - SX 627 | D21: 104600019 | E21: Máy lựa vảy Tomra (FOS) | F21: 7826007822 | G21: =F21/$G$2 -> 322057.94
A22: Z211201P | B22: Máy móc, thiết bị phụ - SX 627 | D22: 104600031 | E22: Hệ thống Chiller nước lạnh | F22: 4641978681 | G22: =F22/$G$2 -> 191027.93
A23: Z211201P | B23: Máy móc, thiết bị phụ - SX 627 | D23: 104600021 | E23: Hệ thống cách nhiệt bể nước ngầm, Hệ thống PCCC | F23: 3682105850 | G23: =F23/$G$2 -> 151526.99
A24: Z211201P | B24: Máy móc, thiết bị phụ - SX 627 | D24: 104600024 | E24: Trạm điện 3.000 KVA | F24: 3298619772 | G24: =F24/$G$2 -> 135745.67
A25: Z211201P | B25: Máy móc, thiết bị phụ - SX 627 | D25: 104600025 | E25: Tủ điện động lực MSB-1 (3200A) | F25: 2414319168 | G25: =F25/$G$2 -> 99354.698
... A52: Z21120A | B52: Máy móc, thiết bị - QL 642 | D52: 106000002 | E52: Bộ lưu điện UPS 10KVA | F52: 72000000 | G52: =F52/$G$2 -> 2962.963
C53: 3 | E53: Khuôn đầu tư sản phẩm mới | F53: =F54 -> 0 | G53: =F53/$G$2 -> 0
G54: =F54/$G$2 -> 0
C55: 4 | E55: Khuôn đầu tư thay thế | F55: 0 | G55: =F55/$G$2 -> 0
C56: 5 | E56: Phương tiện vận tải | F56: =SUM(F57:F63) -> 2573766789 | G56: =F56/$G$2 -> 105916.33
A57: Z21130P | B57: Phương tiện vận tải , truyền dẫn - SX 627 | D57: 107000002 | E57: Xe nâng dầu 2,5 tấn (Xe số 4) | F57: 800000000 | G57: =F57/$G$2 -> 32921.811
A58: Z21130P | B58: Phương tiện vận tải , truyền dẫn - SX 627 | D58: 107000004 | E58: Xe nâng dầu 2.5 Tấn TCM Unicarriers FD25T4 | F58: 400000000 | G58: =F58/$G$2 -> 16460.905
A59: Z21130P | B59: Phương tiện vận tải , truyền dẫn - SX 627 | D59: 107000003 | E59: Xe nâng dầu 2.5 Tấn TCM FD25T3 (Xe số 6) | F59: 390000000 | G59: =F59/$G$2 -> 16049.383
A60: Z21130P | B60: Phương tiện vận tải , truyền dẫn - SX 627 | D60: 107000007 | E60: Hệ thống băng tải cân & may bao cho chuyền HDPE | F60: 165000000 | G60: =F60/$G$2 -> 6790.1235
A61: Z21130P | B61: Phương tiện vận tải , truyền dẫn - SX 627 | D61: 107000006 | E61: Thang máng cáp | F61: 127934000 | G61: =F61/$G$2 -> 5264.7737
A62: Z21130P | B62: Phương tiện vận tải , truyền dẫn - SX 627 | D62: 107000005 | E62: Cầu xe nâng | F62: 125000000 | G62: =F62/$G$2 -> 5144.0329
A63: Z21130A | B63: Phương tiện vận tải , truyền dẫn - QL 642 | D63: 109000000 | E63: Xe ôtô tải hiệu HINO (62C-131.00) | F63: 565832789 | G63: =F63/$G$2 -> 23285.3
C64: 6 | E64: Thiết bị quản lý | F64: =SUM(F65:F67) -> 105866000 | G64: =F64/$G$2 -> 4356.6255
A65: Z21140P | B65: Thiết bị, dụng cụ quản lý - SX 627 | D65: 110000002 | E65: Cân phân tích + Cốc đo tỉ trọng (Mettler Toledo) | F65: 53350000 | G65: =F65/$G$2 -> 2195.4733
A66: Z21140A | B66: Thiết bị, dụng cụ quản lý - QL 642 | D66: 112000001 | E66: Bộ máy tính Dell Presicion 3640 Tower | F66: 52516000 | G66: =F66/$G$2 -> 2161.1523
G67: =F67/$G$2 -> 0
C68: 7 | E68: Phần mềm vi tính | F68: =SUM(F69:F70) -> 0 | G68: =F68/$G$2 -> 0
G69: =F69/$G$2 -> 0
G70: =F70/$G$2 -> 0
C71: 8 | E71: Khác | F71: =SUM(F72:F79) -> 1813062045 | G71: =F71/$G$2 -> 74611.607
A72: Z21380P | B72: TSCĐ vô hình khác - SX 627 | D72: 149000000 | E72: Chứng nhận chất lượng ISO | F72: 275200000 | G72: =F72/$G$2 -> 11325.103
A73: Z21380A | B73: TSCĐ vô hình khác - QL 642 | D73: 151000000 | E73: Tư vấn, lập hồ sơ dự án | F73: 468054545 | G73: =F73/$G$2 -> 19261.504
A74: Z21180P | B74: TSCĐ khác - SX 627 | D74: 115000000 | E74: Pallet D4-0896-Đỏ- Mega Market | F74: 422000000 | G74: =F74/$G$2 -> 17366.255
A75: Z21180P | B75: TSCĐ khác - SX 627 | D75: 115000003 | E75: Pallet D4-0896-Dương-Mega Market | F75: 327600000 | G75: =F75/$G$2 -> 13481.481
A76: Z21180P | B76: TSCĐ khác - SX 627 | D76: 115000002 | E76: Pallet D4-0896-Đỏ-Mega Market | F76: 165107500 | G76: =F76/$G$2 -> 6794.5473
A77: Z21180P | B77: TSCĐ khác - SX 627 | D77: 115000001 | E77: Pallet D4-0896-Dương | F77: 155100000 | G77: =F77/$G$2 -> 6382.716

Sheet  2021 Kim ANh
A5: Nhóm tài sản | B5: Tên Nhóm tài sản | C5: Mã tài sản | D5: Diễn giải tài sản 1 | E5: TT sở hữu | F5: Ngày ghi nhận TS | G5: Ngày bắt đầu KH | H5: T/G Khấu hao | I5: Cost center | J5: Tài khoản KH | K5: Nguyên giá đầu kỳ | L5: Tăng TS | M5: Chuyển TS | N5: Thanh lý | O5: Nguyên giá cuối kỳ | P5: KHLK – Năm trước | Q5: KH – Kỳ này | R5: KHLK –Năm nay | S5: GTCL – Năm nay | T5: Tình trạng sở hữu | U5: Nguyên giá USD | V5: Ngày ngưng SD
A6: Z21110P | B6: Nhà cửa, vật kiến trúc - SX 627 | L6: =SUM(L7:L12) -> 43482852347 | N6: 0
C7: 101000000 | D7: Nhà xưởng số 03 | E7: DH01 | F7: 44288 | G7: 44287 | H7: 300 | I7: 1001602000 | J7: 6274001901 | K7: 0 | L7: 23455092161 | M7: 0 | N7: 0 | O7: 23455092161 | P7: 0 | Q7: -703652765 | R7: -703652765 | S7: 22751439396 | T7: NM Đức Hòa | U7: 0 | V7: 44910
C8: 103000002 | D8: Văn phòng xưởng 03 | E8: DH01 | F8: 44439 | G8: 44438 | H8: 240 | I8: 1001202000 | J8: 6424001901 | K8: 0 | L8: 13526642799 | M8: 0 | N8: 0 | O8: 3206333890 | P8: 0 | Q8: -66798623 | R8: -66798623 | S8: 3139535267 | T8: NM Đức Hòa | U8: 0 | V8: 44910
C9: 101000001 | D9: Hạng mục làm đường nhà máy | E9: DH01 | F9: 44439 | G9: 44438 | H9: 240 | I9: 1001602000 | J9: 6274001901 | K9: 0 | L9: 3206333890 | M9: 0 | N9: 0 | O9: 445541459 | P9: 0 | Q9: -37128455 | R9: -37128455 | S9: 408413004 | T9: NM Đức Hòa | U9: 0 | V9: 44909
C10: 103000001 | D10: Thiết kế nội thất văn phòng xưởng 03 | E10: DH01 | F10: 44439 | G10: 44438 | H10: 120 | I10: 1001202000 | J10: 6424001901 | K10: 0 | L10: 2813240158 | M10: 0 | N10: 0 | O10: 36001880 | P10: 0 | Q10: -3000157 | R10: -3000157 | S10: 33001723 | T10: NM Đức Hòa | U10: 0 | V10: 44910
C11: 101000002 | D11: Nhà kho lều bạt | E11: DH01 | F11: 44439 | G11: 44438 | H11: 60 | I11: 1001602000 | J11: 6274001901 | K11: 0 | L11: 445541459 | M11: 0 | N11: 0 | O11: 2813240158 | P11: 0 | Q11: -117218340 | R11: -117218340 | S11: 2696021818 | T11: NM Đức Hòa | U11: 0 | V11: 44910
C12: 103000000 | D12: Nhà để xe CNV | E12: DH01 | F12: 44439 | G12: 44438 | H12: 60 | I12: 1001202000 | J12: 6424001901 | K12: 0 | L12: 36001880 | M12: 0 | N12: 0 | O12: 13526642799 | P12: 0 | Q12: -281805058 | R12: -281805058 | S12: 13244837741 | T12: NM Đức Hòa | U12: 0 | V12: 44910
A13: Z21120P | B13: Máy móc, thiết bị - SX 627 | L13: =SUM(L14:L20) -> 176488370407 | N13: 0
C14: 104000068 | D14: Hệ thống xử lý nước thải ChengWoen | E14: DH01 | F14: 44417 | G14: 44417 | H14: 120 | I14: 1001602101 | J14: 6274001903 | K14: 0 | L14: 46273512763 | M14: 0 | N14: 0 | O14: 1871585340 | P14: 0 | Q14: -124772356 | R14: -124772356 | S14: 1746812984 | T14: NM Đức Hòa | U14: 0
C15: 104000070 | D15: Máy nâng IV Starlinger (SSP) | E15: DH01 | F15: 44417 | G15: 44417 | H15: 120 | I15: 1001602105 | J15: 6274001903 | K15: 0 | L15: 42617633391 | M15: 0 | N15: 0 | O15: 150000000 | P15: 0 | Q15: -10000000 | R15: -10000000 | S15: 140000000 | T15: NM Đức Hòa | U15: 0
C16: 104000069 | D16: Máy tạo hạt Starlinger (PET02) | E16: DH01 | F16: 44417 | G16: 44417 | H16: 120 | I16: 1001602104 | J16: 6274001903 | K16: 0 | L16: 40239524497 | M16: 0 | N16: 0 | O16: 37079055498 | P16: 0 | Q16: -1544960646 | R16: -1544960646 | S16: 35534094852 | T16: NM Đức Hòa | U16: 0
C17: 104000067 | D17: Chuyền tạo vảy rPET - ChengWoen | E17: DH01 | F17: 44417 | G17: 44417 | H17: 120 | I17: 1001602101 | J17: 6274001903 | K17: 0 | L17: 37079055498 | M17: 0 | N17: 0 | O17: 46273512763 | P17: 0 | Q17: -1928063032 | R17: -1928063032 | S17: 44345449731 | T17: NM Đức Hòa | U17: 0 | V17: 44910
C18: 104000071 | D18: Máy tạo hạt rHDPE - 01 | E18: DH01 | F18: 44417 | G18: 44417 | H18: 120 | I18: 1001602103 | J18: 6274001903 | K18: 0 | L18: 8257058918 | M18: 0 | N18: 0 | O18: 40239524497 | P18: 0 | Q18: -1676646854 | R18: -1676646854 | S18: 38562877643 | T18: NM Đức Hòa | U18: 0
C19: 104000065 | D19: Máy Tách màu Taiho | E19: DH01 | F19: 44408 | G19: 44378 | H19: 90 | I19: 1001602107 | J19: 6274001903 | K19: 0 | L19: 1871585340 | M19: 0 | N19: 0 | O19: 42617633391 | P19: 0 | Q19: -1775734725 | R19: -1775734725 | S19: 40841898666 | T19: NM Đức Hòa | U19: 0
C20: 104000066 | D20: Máy trộn hạt nhựa 2 tấn | E20: DH01 | F20: 44378 | G20: 44389 | H20: 90 | I20: 1001602116 | J20: 6274001903 | K20: 0 | L20: 150000000 | M20: 0 | N20: 0 | O20: 8257058918 | P20: 0 | Q20: -344044122 | R20: -344044122 | S20: 7913014796 | T20: NM Đức Hòa | U20: 0
A21: Z211201P | B21: Máy móc, thiết bị phụ - SX 627 | L21: =SUM(L22:L50) -> 35953846529 | N21: =SUM(N22:N50) -> 875679600
C22: 104600019 | D22: Máy lựa vảy Tomra (FOS) | E22: DH01 | F22: 44417 | G22: 44417 | H22: 120 | I22: 1001602101 | J22: 6274001906 | K22: 0 | L22: 7826007822 | M22: 0 | N22: 0 | O22: 125658000 | P22: 0 | Q22: -25131600 | R22: -25131600 | S22: 100526400 | T22: NM Đức Hòa | U22: 0
C23: 104600031 | D23: Hệ thống Chiller nước lạnh | E23: DH01 | F23: 44439 | G23: 44438 | H23: 120 | I23: 1001602000 | J23: 6274001906 | K23: 0 | L23: 4641978681 | M23: 0 | N23: 0 | O23: 130079300 | P23: 0 | Q23: -26015860 | R23: -26015860 | S23: 104063440 | T23: NM Đức Hòa | U23: 0
C24: 104600021 | D24: Hệ thống cách nhiệt bể nước ngầm, Hệ thống PCCC | E24: DH01 | F24: 44439 | G24: 44438 | H24: 120 | I24: 1001602000 | J24: 6274001906 | K24: 0 | L24: 3682105850 | M24: 0 | N24: 0 | O24: 146100000 | P24: 0 | Q24: -26785000 | R24: -26785000 | S24: 119315000 | T24: NM Đức Hòa | U24: 0
C25: 104600024 | D25: Trạm điện 3.000 KVA | E25: DH01 | F25: 44439 | G25: 44438 | H25: 120 | I25: 1001602000 | J25: 6274001906 | K25: 0 | L25: 3298619772 | M25: 0 | N25: 0 | O25: 616655000 | P25: 0 | Q25: -68517222 | R25: -68517222 | S25: 548137778 | T25: NM Đức Hòa | U25: 0 | V25: 45525
C26: 104600025 | D26: Tủ điện động lực MSB-1 (3200A) | E26: DH01 | F26: 44439 | G26: 44438 | H26: 120 | I26: 1001602000 | J26: 6274001906 | K26: 0 | L26: 2414319168 | M26: 0 | N26: 0 | O26: 1129934700 | P26: 0 | Q26: -112993470 | R26: -112993470 | S26: 1016941230 | T26: NM Đức Hòa | U26: 0
C27: 104600026 | D27: Hệ thống điện xưởng 03 | E27: DH01 | F27: 44439 | G27: 44438 | H27: 120 | I27: 1001602000 | J27: 6274001906 | K27: 0 | L27: 1931331475 | M27: 0 | N27: 0 | O27: 60000000 | P27: 0 | Q27: -13333333 | R27: -13333333 | S27: 46666667 | T27: NM Đức Hòa | U27: 0
C28: 104600016 | D28: Hệ thống sắc ký khí ghép nối khối phổ GC/MS - USA | E28: DH01 | F28: 44397 | G28: 44397 | H28: 90 | I28: 1001602000 | J28: 6274001906 | K28: 0 | L28: 1818450000 | M28: 0 | N28: 0 | O28: 319400000 | P28: 0 | Q28: -21293333 | R28: -21293333 | S28: 298106667 | T28: NM Đức Hòa | U28: 0
C29: 104600022 | D29: Hệ thống Điện, cấp thoát Nước xưởng 03 | E29: DH01 | F29: 44439 | G29: 44438 | H29: 120 | I29: 1001602000 | J29: 6274001906 | K29: 0 | L29: 1729306981 | M29: 0 | N29: 0 | O29: 1818450000 | P29: 0 | Q29: -121230000 | R29: -121230000 | S29: 1697220000 | T29: NM Đức Hòa | U29: 0
C30: 104600028 | D30: Lò nước nóng Martech | E30: DH01 | F30: 44439 | G30: 44438 | H30: 120 | I30: 1001602000 | J30: 6274001906 | K30: 0 | L30: 1577222005 | M30: 0 | N30: 0 | O30: 433134526 | P30: 0 | Q30: -43313453 | R30: -43313453 | S30: 389821073 | T30: NM Đức Hòa | U30: 0
C31: 104600013 | D31: Máy nén khí Ingersol Rand | E31: DH01 | F31: 44288 | G31: 44287 | H31: 90 | I31: 1001602000 | J31: 6274001906 | K31: 0 | L31: 1129934700 | M31: 0 | N31: 0 | O31: 350000000 | P31: 0 | Q31: -14583333 | R31: -14583333 | S31: 335416667 | T31: NM Đức Hòa | U31: 0
C32: 104600037 | D32: Máy ép kiện XTY-600WB10080+ băng tải XTS-1000T | E32: DH01 | F32: 44554 | G32: 44562 | H32: 72 | I32: 1001602000 | J32: 6274001906 | K32: 0 | L32: 875679600 | M32: 0 | N32: 875679600 | O32: 7826007822 | P32: 0 | Q32: -326083659 | R32: -326083659 | S32: 7499924163 | T32: NM Đức Hòa | U32: 0
C33: 104600020 | D33: Đường ống nén khí xưởng 03 | E33: DH01 | F33: 44439 | G33: 44438 | H33: 120 | I33: 1001602000 | J33: 6274001906 | K33: 0 | L33: 758031567 | M33: 0 | N33: 0 | O33: 758031567 | P33: 0 | Q33: -31584649 | R33: -31584649 | S33: 726446918 | T33: NM Đức Hòa | U33: 0 | V33: 44910
C34: 104600012 | D34: Máy tách nhãn PVN-600, Băng tải nạp liệu | E34: DH01 | F34: 44263 | G34: 44263 | H34: 90 | I34: 1001602101 | J34: 6274001906 | K34: 0 | L34: 616655000 | M34: 0 | N34: 0 | O34: 3682105850 | P34: 0 | Q34: -153421077 | R34: -153421077 | S34: 3528684773 | T34: NM Đức Hòa | U34: 0 | V34: 44910
C35: 104600023 | D35: Tủ điện động lực MSB-2 | E35: DH01 | F35: 44439 | G35: 44438 | H35: 120 | I35: 1001602000 | J35: 6274001906 | K35: 0 | L35: 558511800 | M35: 0 | N35: 0 | O35: 1729306981 | P35: 0 | Q35: -72054458 | R35: -72054458 | S35: 1657252523 | T35: NM Đức Hòa | U35: 0 | V35: 44910
C36: 104600038 | D36: Máy đo độ nhớt IV LOVIS 2000 M/ME(Model:LOVIS 2000 | E36: DH01 | F36: 44531 | G36: 44531 | H36: 72 | I36: 1001602000 | J36: 6274001906 | K36: 0 | L36: 439248612 | M36: 0 | N36: 0 | O36: 558511800 | P36: 0 | Q36: -23271325 | R36: -23271325 | S36: 535240475 | T36: NM Đức Hòa | U36: 0
C37: 104600017 | D37: Thiết bị phòng LAB | E37: DH01 | F37: 44408 | G37: 44378 | H37: 60 | I37: 1001602000 | J37: 6274001906 | K37: 0 | L37: 433134526 | M37: 0 | N37: 0 | O37: 3298619772 | P37: 0 | Q37: -137442491 | R37: -137442491 | S37: 3161177281 | T37: NM Đức Hòa | U37: 0
C38: 104600029 | D38: Tháp giải nhiệt LRC-N-200 | F38: 44439 | G38: 44438 | H38: 120 | I38: 1001602000 | J38: 6274001906 | K38: 0 | L38: 397073670 | M38: 0 | N38: 0 | O38: 2414319168 | P38: 0 | Q38: -100596632 | R38: -100596632 | S38: 2313722536 | T38: NM Đức Hòa | U38: 0
C39: 104600018 | D39: Bồn SILO | E39: DH01 | F39: 44417 | G39: 44417 | H39: 120 | I39: 1001602101 | J39: 6274001906 | K39: 0 | L39: 350000000 | M39: 0 | N39: 0 | O39: 1931331475 | P39: 0 | Q39: -80472145 | R39: -80472145 | S39: 1850859330 | T39: NM Đức Hòa | U39: 0 | V39: 44910
C40: 104600015 | D40: Máy nghiền mẫu thí nghiệm Model CryoMill - Đức | E40: DH01 | F40: 44397 | G40: 44397 | H40: 90 | I40: 1001602000 | J40: 6274001906 | K40: 0 | L40: 319400000 | M40: 0 | N40: 0 | O40: 310000000 | P40: 0 | Q40: -25833333 | R40: -25833333 | S40: 284166667 | T40: NM Đức Hòa | U40: 0
C41: 104600027 | D41: Máy ép kiện (BLR) | E41: DH01 | F41: 44439 | G41: 44438 | H41: 60 | I41: 1001602000 | J41: 6274001906 | K41: 0 | L41: 310000000 | M41: 0 | N41: 0 | O41: 1577222005 | P41: 0 | Q41: -65717584 | R41: -65717584 | S41: 1511504421 | T41: NM Đức Hòa | U41: 0
C42: 104600011 | D42: Bồn chứa Inox 0,3m3 cân tự động + Thiết bị tủ điện | E42: DH01 | F42: 44228 | G42: 44228 | H42: 60 | I42: 1001602102 | J42: 6274001906 | K42: 0 | L42: 146100000 | M42: 0 | N42: 0 | O42: 397073670 | P42: 0 | Q42: -16544736 | R42: -16544736 | S42: 380528934 | U42: 0
C43: 104600010 | D43: Silo 1000L, Quạt thổi, Phễu chứa liệu, Đường ống | E43: DH01 | F43: 44198 | G43: 44198 | H43: 60 | I43: 1001602102 | J43: 6274001906 | K43: 0 | L43: 130079300 | M43: 0 | N43: 0 | O43: 73500000 | P43: 0 | Q43: -6125000 | R43: -6125000 | S43: 67375000 | T43: NM Đức Hòa | U43: 0
C44: 104600009 | D44: Vít tải liệu AF-4600 | E44: DH01 | F44: 44198 | G44: 44198 | H44: 60 | I44: 1001602102 | J44: 6274001906 | K44: 0 | L44: 125658000 | M44: 0 | N44: 0 | O44: 4641978681 | P44: 0 | Q44: -193415778 | R44: -193415778 | S44: 4448562903 | T44: NM Đức Hòa | U44: 0
C45: 104600034 | D45: Máy quấn màng Pallet tự động (Model: MQ1650-B) | E45: DH01 | F45: 44501 | G45: 44519 | H45: 72 | I45: 1001602000 | J45: 6274001906 | K45: 0 | L45: 88000000 | M45: 0 | N45: 0 | O45: 81000000 | P45: 0 | Q45: -3375000 | R45: -3375000 | S45: 77625000 | T45: NM Đức Hòa | U45: 0
C46: 104600032 | D46: Bình nén khí 8000L | E46: DH01 | F46: 44439 | G46: 44438 | H46: 120 | I46: 1001602000 | J46: 6274001906 | K46: 0 | L46: 81000000 | M46: 0 | N46: 0 | O46: 76120000 | P46: 0 | Q46: -8457778 | R46: -8457778 | S46: 67662222 | T46: NM Đức Hòa | U46: 0
C47: 104600033 | D47: Bơm màng 1 Inch ARO-Polypropylene (PD10P-YPS-PTT1) | E47: DH01 | F47: 44440 | G47: 44440 | H47: 36 | I47: 1001602101 | J47: 6274001906 | K47: 0 | L47: 76120000 | M47: 0 | N47: 0 | O47: 88000000 | P47: 0 | Q47: -2444444 | R47: -2444444 | S47: 85555556 | T47: NM Đức Hòa | U47: 0
C48: 104600030 | D48: Bàn cân điện tử FWS (1EA1.5m) &(2EA1.2m) | E48: DH01 | F48: 44439 | G48: 44438 | H48: 60 | I48: 1001602000 | J48: 6274001906 | K48: 0 | L48: 73500000 | M48: 0 | N48: 0 | O48: 66378000 | P48: 0 | Q48: -1843833 | R48: -1843833 | S48: 64534167 | T48: NM Đức Hòa | U48: 0
C49: 104600035 | D49: Bộ thiết bị tai nghe HMT-1 (Mã hiệu 171131G) 9LK | E49: DH01 | F49: 44532 | G49: 44532 | H49: 36 | I49: 1001602000 | J49: 6274001906 | K49: 0 | L49: 66378000 | M49: 0 | N49: 0 | O49: 0 | P49: 0 | Q49: 0 | R49: 0 | S49: 0 | T49: NM Đức Hòa | U49: 0 | V49: 44554
C50: 104600014 | D50: Van xoay định lượng DN150-SUS304 | E50: DH01 | F50: 44322 | G50: 44322 | H50: 36 | I50: 1001602101 | J50: 6274001906 | K50: 0 | L50: 60000000 | M50: 0 | N50: 0 | O50: 439248612 | P50: 0 | Q50: -6100675 | R50: -6100675 | S50: 433147937 | T50: NM Đức Hòa | U50: 0
A51: Z21120A | B51: Máy móc, thiết bị - QL 642 | L51: =SUM(L52:L54) -> 2445994318 | N51: 0
C52: 106000004 | D52: Hệ thống IT | E52: DH01 | F52: 44439 | G52: 44438 | H52: 120 | I52: 1001202000 | J52: 6424001903 | K52: 0 | L52: 1971544318 | M52: 0 | N52: 0 | O52: 72000000 | P52: 0 | Q52: -18000000 | R52: -18000000 | S52: 54000000 | T52: NM Đức Hòa | U52: 0
C53: 106000003 | D53: Hệ thống máy lạnh âm trần DAIKIN (1.5HP-3.5HP) | E53: DH01 | F53: 44439 | G53: 44438 | H53: 60 | I53: 1001202000 | J53: 6424001903 | K53: 0 | L53: 402450000 | M53: 0 | N53: 0 | O53: 402450000 | P53: 0 | Q53: -33537500 | R53: -33537500 | S53: 368912500 | T53: NM Đức Hòa | U53: 0 | V53: 44910
C54: 106000002 | D54: Bộ lưu điện UPS 10KVA | E54: DH01 | F54: 44299 | G54: 44299 | H54: 36 | I54: 1001202000 | J54: 6424001903 | K54: 0 | L54: 72000000 | M54: 0 | N54: 0 | O54: 1971544318 | P54: 0 | Q54: -82147680 | R54: -82147680 | S54: 1889396638 | T54: NM Đức Hòa | U54: 0
A55: Z21130P | B55: Phương tiện vận tải , truyền dẫn - SX 627 | L55: =SUM(L56:L61) -> 2007934000 | N55: 0
C56: 107000002 | D56: Xe nâng dầu 2,5 tấn (Xe số 4) | E56: DH01 | F56: 44228 | G56: 44189 | H56: 60 | I56: 1001602000 | J56: 6274001905 | K56: 0 | L56: 800000000 | M56: 0 | N56: 0 | O56: 800000000 | P56: 0 | Q56: -140350877 | R56: -140350877 | S56: 659649123 | T56: NM Đức Hòa | U56: 0
C57: 107000004 | D57: Xe nâng dầu 2.5 Tấn TCM Unicarriers FD25T4 | E57: DH01 | F57: 44337 | G57: 44337 | H57: 60 | I57: 1001602000 | J57: 6274001905 | K57: 0 | L57: 400000000 | M57: 0 | N57: 0 | O57: 390000000 | P57: 0 | Q57: -52000000 | R57: -52000000 | S57: 338000000 | T57: NM Đức Hòa | U57: 0
C58: 107000003 | D58: Xe nâng dầu 2.5 Tấn TCM FD25T3 (Xe số 6) | E58: DH01 | F58: 44337 | G58: 44337 | H58: 60 | I58: 1001602000 | J58: 6274001905 | K58: 0 | L58: 390000000 | M58: 0 | N58: 0 | O58: 400000000 | P58: 0 | Q58: -53333333 | R58: -53333333 | S58: 346666667 | T58: NM Đức Hòa | U58: 0 | V58: 44620
C59: 107000007 | D59: Hệ thống băng tải cân & may bao cho chuyền HDPE | E59: DH01 | F59: 44510 | G59: 44510 | H59: 72 | I59: 1001602103 | J59: 6274001905 | K59: 0 | L59: 165000000 | M59: 0 | N59: 0 | O59: 125000000 | P59: 0 | Q59: -10416667 | R59: -10416667 | S59: 114583333 | T59: NM Đức Hòa | U59: 0
C60: 107000006 | D60: Thang máng cáp | E60: DH01 | F60: 44501 | G60: 44501 | H60: 72 | I60: 1001602000 | J60: 6274001905 | K60: 0 | L60: 127934000 | M60: 0 | N60: 0 | O60: 127934000 | P60: 0 | Q60: -3553722 | R60: -3553722 | S60: 124380278 | T60: NM Đức Hòa | U60: 0
C61: 107000005 | D61: Cầu xe nâng | E61: DH01 | F61: 44414 | G61: 44414 | H61: 60 | I61: 1001602000 | J61: 6274001905 | K61: 0 | L61: 125000000 | M61: 0 | N61: 0 | O61: 165000000 | P61: 0 | Q61: -4583333 | R61: -4583333 | S61: 160416667 | T61: NM Đức Hòa | U61: 0
A62: Z21130A | B62: Phương tiện vận tải , truyền dẫn - QL 642 | L62: =L63 -> 565832789 | N62: 0
C63: 109000000 | D63: Xe ôtô tải hiệu HINO (62C-131.00) | E63: DH01 | F63: 44334 | G63: 44334 | H63: 96 | I63: 1001202000 | J63: 6424001905 | K63: 0 | L63: 565832789 | M63: 0 | N63: 0 | O63: 565832789 | P63: 0 | Q63: -47152732 | R63: -47152732 | S63: 518680057 | T63: NM Đức Hòa | U63: 0
A64: Z21140P | B64: Thiết bị, dụng cụ quản lý - SX 627 | L64: =L65 -> 53350000 | N64: 0
C65: 110000002 | D65: Cân phân tích + Cốc đo tỉ trọng (Mettler Toledo) | E65: DH01 | F65: 44515 | G65: 44515 | H65: 60 | I65: 1001602000 | J65: 6274001904 | K65: 0 | L65: 53350000 | M65: 0 | N65: 0 | O65: 53350000 | P65: 0 | Q65: -1778333 | R65: -1778333 | S65: 51571667 | T65: NM Đức Hòa | U65: 0
A66: Z21140A | B66: Thiết bị, dụng cụ quản lý - QL 642 | L66: =L67 -> 52516000 | N66: 0
C67: 112000001 | D67: Bộ máy tính Dell Presicion 3640 Tower | E67: DH01 | F67: 44368 | G67: 44368 | H67: 36 | I67: 1001202000 | J67: 6424001904 | K67: 0 | L67: 52516000 | M67: 0 | N67: 0 | O67: 52516000 | P67: 0 | Q67: -10211444 | R67: -10211444 | S67: 42304556 | T67: NM Đức Hòa | U67: 0
A68: Z21180P | B68: TSCĐ khác - SX 627 | L68: =SUM(L69:L72) -> 1069807500 | N68: 0
C69: 115000000 | D69: Pallet D4-0896-Đỏ- Mega Market | E69: DH01 | F69: 44228 | G69: 44228 | H69: 60 | I69: 1001602000 | J69: 6274001909 | K69: 0 | L69: 422000000 | M69: 0 | N69: 0 | O69: 422000000 | P69: 0 | Q69: -77366667 | R69: -77366667 | S69: 344633333 | T69: NM Đức Hòa | U69: 0
C70: 115000003 | D70: Pallet D4-0896-Dương-Mega Market | E70: DH01 | F70: 44561 | G70: 44561 | H70: 72 | I70: 1001602000 | J70: 6274001909 | K70: 0 | L70: 327600000 | M70: 0 | N70: 0 | O70: 155100000 | P70: 0 | Q70: -28435000 | R70: -28435000 | S70: 126665000 | T70: NM Đức Hòa | U70: 0
C71: 115000002 | D71: Pallet D4-0896-Đỏ-Mega Market | E71: DH01 | F71: 44327 | G71: 44327 | H71: 60 | I71: 1001602000 | J71: 6274001909 | K71: 0 | L71: 165107500 | M71: 0 | N71: 0 | O71: 165107500 | P71: 0 | Q71: -22014333 | R71: -22014333 | S71: 143093167 | T71: NM Đức Hòa | U71: 0
C72: 115000001 | D72: Pallet D4-0896-Dương | E72: DH01 | F72: 44228 | G72: 44228 | H72: 60 | I72: 1001602000 | J72: 6274001909 | K72: 0 | L72: 155100000 | M72: 0 | N72: 0 | O72: 327600000 | P72: 0 | Q72: -4550000 | R72: -4550000 | S72: 323050000 | T72: NM Đức Hòa | U72: 0
A73: Z21180A | B73: TSCĐ khác - QL 642 | L73: =L74 -> 28150860 | N73: 0
C74: 117000000 | D74: Nhà chứa rác thải nguy hại | E74: DH01 | F74: 44405 | G74: 44385 | H74: 24 | I74: 1001202000 | J74: 6424001909 | K74: 0 | L74: 28150860 | M74: 0 | N74: 0 | O74: 28150860 | P74: 0 | Q74: -7037715 | R74: -7037715 | S74: 21113145 | T74: NM Đức Hòa | U74: 0 | V74: 44910
A75: Z21380P | B75: TSCĐ vô hình khác - SX 627 | L75: =L76 -> 275200000 | N75: 0
C76: 149000000 | D76: Chứng nhận chất lượng ISO | E76: DH01 | F76: 44439 | G76: 44438 | H76: 60 | I76: 1001602000 | J76: 6274001915 | K76: 0 | L76: 275200000 | M76: 0 | N76: 0 | O76: 275200000 | P76: 0 | Q76: -22933333 | R76: -22933333 | S76: 252266667 | T76: NM Đức Hòa | U76: 0
A77: Z21380A | B77: TSCĐ vô hình khác - QL 642 | L77: =L78 -> 468054545 | N77: 0
C78: 151000000 | D78: Tư vấn, lập hồ sơ dự án | E78: DH01 | F78: 44439 | G78: 44438 | H78: 60 | I78: 1001101000 | J78: 6424001915 | K78: 0 | L78: 468054545 | M78: 0 | N78: 0 | O78: 468054545 | P78: 0 | Q78: -39004545 | R78: -39004545 | S78: 429050000 | T78: NM Đức Hòa | U78: 0
A79: TỔNG TĂNG TSCĐ 2021 | L79: =L6+L13+L21+L51+L55+L62+L64+L66+L68+L73+L75+L77 -> 262891909295 | N79: =N21 -> 875679600

Sheet Capex TT 2020
E1: ĐẦU TƯ CAPEX THỰC TẾ 2020
F2: Tỷ giá: | G2: 24000
F3: =SUM(F5,F8,F23,F25,F26,F29,F31,F33) -> 4697651482 | G3: =SUM(G5,G8,G23,G25,G26,G29,G31,G33) -> 195735.48
A4: Nhóm tài sản (SAP) | B4: Tên Nhóm tài sản (SAP) | C4: STT | D4: Mã TS | E4: Nội dung | F4: số tiền VND | G4: số tiền USD
C5: 1 | E5: Nhà cửa, vật kiến trúc | F5: =SUM(F6:F7) -> 0 | G5: =F5/$G$2 -> 0
G6: =F6/$G$2 -> 0
G7: =F7/$G$2 -> 0
C8: 2 | E8: Máy móc thiết bị | F8: =SUM(F9:F22) -> 4317651482 | G8: =F8/$G$2 -> 179902.15
A9: Z21120P | B9: Máy móc, thiết bị - SX 627 | D9: 104000062 | E9: Máy tạo hạt rPET HTL 1 | F9: 1985420682 | G9: =F9/$G$2 -> 82725.862
A10: Z21120P | B10: Máy móc, thiết bị - SX 627 | D10: 104000063 | E10: Bộ dao cắt hạt và máy thổi khô (YE I) | F10: 465140000 | G10: =F10/$G$2 -> 19380.833
A11: Z21120P | B11: Máy móc, thiết bị - SX 627 | D11: 104000064 | E11: Máy nghiền nhựa HGP-800 | F11: 140400000 | G11: =F11/$G$2 -> 5850
A12: Z211201P | B12: Máy móc, thiết bị phụ - SX 627 | D12: 104600008 | E12: Máy tách kim loại Sesotec | F12: 365324800 | G12: =F12/$G$2 -> 15221.867
A13: Z211201P | B13: Máy móc, thiết bị phụ - SX 627 | D13: 104600003 | E13: Máy đo cường lực vạn năng, AI-7000M | F13: 330000000 | G13: =F13/$G$2 -> 13750
A14: Z211201P | B14: Máy móc, thiết bị phụ - SX 627 | D14: 104600006 | E14: Máy đo HDT/VICAT, HV-3000-P3C | F14: 250000000 | G14: =F14/$G$2 -> 10416.667
A15: Z211201P | B15: Máy móc, thiết bị phụ - SX 627 | D15: 104600004 | E15: Máy đo bền va đập, GT-7045HMH | F15: 199000000 | G15: =F15/$G$2 -> 8291.6667
A16: Z211201P | B16: Máy móc, thiết bị phụ - SX 627 | D16: 104600002 | E16: Bộ lọc bụi SHINI ACF 8 | F16: 187612000 | G16: =F16/$G$2 -> 7817.1667
A17: Z211201P | B17: Máy móc, thiết bị phụ - SX 627 | D17: 104600001 | E17: Bộ hút AV-2 1to2, thùng chứa 200+150L, máy sấy dây | F17: 144274000 | G17: =F17/$G$2 -> 6011.4167
A18: Z211201P | B18: Máy móc, thiết bị phụ - SX 627 | D18: 104600000 | E18: Bộ hút AV-3, AV-2, bồn làm mát (PET 01) | F18: 114480000 | G18: =F18/$G$2 -> 4770
A19: Z211201P | B19: Máy móc, thiết bị phụ - SX 627 | D19: 104600005 | E19: Máy cắt góc, GT-7016-A3 | F19: 51000000 | G19: =F19/$G$2 -> 2125
A20: Z211201P | B20: Máy móc, thiết bị phụ - SX 627 | D20: 104600007 | E20: Máy đo độ cứng, GS-702N | F20: 28000000 | G20: =F20/$G$2 -> 1166.6667
A21: Z21120A | B21: Máy móc, thiết bị - QL 642 | D21: 106000001 | E21: Máy chà sàn công nghiệp Pullman PMA510B, ắc quy | F21: 57000000 | G21: =F21/$G$2 -> 2375
G22: =F22/$G$2 -> 0
C23: 3 | E23: Khuôn đầu tư sản phẩm mới | F23: =F24 -> 0 | G23: =F23/$G$2 -> 0
G24: =F24/$G$2 -> 0
C25: 4 | E25: Khuôn đầu tư thay thế | F25: 0 | G25: =F25/$G$2 -> 0
C26: 5 | E26: Phương tiện vận tải | F26: =SUM(F27:F28) -> 380000000 | G26: =F26/$G$2 -> 15833.333
A27: Z21130P | B27: Phương tiện vận tải , truyền dẫn - SX 627 | D27: 107000001 | E27: Xe nâng dầu Komatsu 2500kg (Xe số 3) | F27: 380000000 | G27: =F27/$G$2 -> 15833.333
G28: =F28/$G$2 -> 0
C29: 6 | E29: Thiết bị quản lý | F29: =SUM(F30:F30) -> 0 | G29: =F29/$G$2 -> 0
G30: =F30/$G$2 -> 0
C31: 7 | E31: Phần mềm vi tính | F31: =SUM(F32:F32) -> 0 | G31: =F31/$G$2 -> 0
G32: =F32/$G$2 -> 0
C33: 8 | E33: Khác | F33: =SUM(F34:F35) -> 0 | G33: =F33/$G$2 -> 0
G34: =F34/$G$2 -> 0

Sheet 2020 Kim ANh
A1: Nhóm tài sản | B1: Tên Nhóm tài sản | C1: Mã tài sản | D1: Diễn giải tài sản 1 | E1: TT sở hữu | F1: Ngày ghi nhận TS | G1: Ngày bắt đầu KH | H1: T/G Khấu hao | I1: Cost center | J1: Tài khoản KH | K1: Nguyên giá đầu kỳ | L1: Tăng TS | M1: Chuyển TS | N1: Thanh lý | O1: Nguyên giá cuối kỳ | P1: KHLK – Năm trước | Q1: KH – Kỳ này | R1: KHLK –Năm nay | S1: GTCL – Năm nay | T1: Tình trạng sở hữu | U1: Nguyên giá USD | V1: Ngày ngưng SD
A2: Z21120P | B2: Máy móc, thiết bị - SX 627 | L2: =SUM(L3:L5) -> 2590960682 | N2: 0
C3: 104000062 | D3: Máy tạo hạt rPET HTL 1 | E3: DH01 | F3: 44074 | G3: 44074 | H3: 90 | I3: 1001602102 | J3: 6274001903 | K3: 0 | L3: 1985420682 | M3: 0 | N3: 0 | O3: 1985420682 | P3: 0 | Q3: -110301149 | R3: -110301149 | S3: 1875119533 | T3: NM Đức Hòa | U3: 0
C4: 104000063 | D4: Bộ dao cắt hạt và máy thổi khô (YE I) | E4: DH01 | F4: 44111 | G4: 44114 | H4: 90 | I4: 1001602102 | J4: 6274001903 | K4: 0 | L4: 465140000 | M4: 0 | N4: 0 | O4: 465140000 | P4: 0 | Q4: -15504667 | R4: -15504667 | S4: 449635333 | T4: NM Đức Hòa | U4: 0
C5: 104000064 | D5: Máy nghiền nhựa HGP-800 | E5: DH01 | F5: 44169 | G5: 44166 | H5: 90 | I5: 1001602106 | J5: 6274001903 | K5: 0 | L5: 140400000 | M5: 0 | N5: 0 | O5: 140400000 | P5: 0 | Q5: -1560000 | R5: -1560000 | S5: 138840000 | T5: NM Đức Hòa | U5: 0
A6: Z211201P | B6: Máy móc, thiết bị phụ - SX 627 | L6: =SUM(L7:L15) -> 1669690800 | N6: 0
C7: 104600008 | D7: Máy tách kim loại Sesotec | E7: DH01 | F7: 44189 | G7: 44189 | H7: 60 | I7: 1001602102 | J7: 6274001906 | K7: 0 | L7: 365324800 | M7: 0 | N7: 0 | O7: 114480000 | P7: 0 | Q7: -3816000 | R7: -3816000 | S7: 110664000 | T7: NM Đức Hòa | U7: 0
C8: 104600003 | D8: Máy đo cường lực vạn năng, AI-7000M | E8: DH01 | F8: 44177 | G8: 44177 | H8: 60 | I8: 1001602000 | J8: 6274001906 | K8: 0 | L8: 330000000 | M8: 0 | N8: 0 | O8: 144274000 | P8: 0 | Q8: -4809133 | R8: -4809133 | S8: 139464867 | T8: NM Đức Hòa | U8: 0
C9: 104600006 | D9: Máy đo HDT/VICAT, HV-3000-P3C | E9: DH01 | F9: 44177 | G9: 44177 | H9: 60 | I9: 1001602000 | J9: 6274001906 | K9: 0 | L9: 250000000 | M9: 0 | N9: 0 | O9: 187612000 | P9: 0 | Q9: -2084578 | R9: -2084578 | S9: 185527422 | T9: NM Đức Hòa | U9: 0
C10: 104600004 | D10: Máy đo bền va đập, GT-7045HMH | E10: DH01 | F10: 44177 | G10: 44177 | H10: 60 | I10: 1001602000 | J10: 6274001906 | K10: 0 | L10: 199000000 | M10: 0 | N10: 0 | O10: 330000000 | P10: 0 | Q10: -5500000 | R10: -5500000 | S10: 324500000 | T10: NM Đức Hòa | U10: 0
C11: 104600002 | D11: Bộ lọc bụi SHINI ACF 8 | E11: DH01 | F11: 44166 | G11: 44166 | H11: 90 | I11: 1001602000 | J11: 6274001906 | K11: 0 | L11: 187612000 | M11: 0 | N11: 0 | O11: 199000000 | P11: 0 | Q11: -3316667 | R11: -3316667 | S11: 195683333 | T11: NM Đức Hòa | U11: 0
C12: 104600001 | D12: Bộ hút AV-2 1to2, thùng chứa 200+150L, máy sấy dây | E12: DH01 | F12: 44110 | G12: 44110 | H12: 90 | I12: 1001602102 | J12: 6274001906 | K12: 0 | L12: 144274000 | M12: 0 | N12: 0 | O12: 51000000 | P12: 0 | Q12: -850000 | R12: -850000 | S12: 50150000 | T12: NM Đức Hòa | U12: 0
C13: 104600000 | D13: Bộ hút AV-3, AV-2, bồn làm mát (PET 01) | E13: DH01 | F13: 44110 | G13: 44110 | H13: 90 | I13: 1001602102 | J13: 6274001906 | K13: 0 | L13: 114480000 | M13: 0 | N13: 0 | O13: 250000000 | P13: 0 | Q13: -4166667 | R13: -4166667 | S13: 245833333 | T13: NM Đức Hòa | U13: 0
C14: 104600005 | D14: Máy cắt góc, GT-7016-A3 | E14: DH01 | F14: 44177 | G14: 44177 | H14: 60 | I14: 1001602000 | J14: 6274001906 | K14: 0 | L14: 51000000 | M14: 0 | N14: 0 | O14: 28000000 | P14: 0 | Q14: -466667 | R14: -466667 | S14: 27533333 | T14: NM Đức Hòa | U14: 0
C15: 104600007 | D15: Máy đo độ cứng, GS-702N | E15: DH01 | F15: 44177 | G15: 44177 | H15: 60 | I15: 1001602000 | J15: 6274001906 | K15: 0 | L15: 28000000 | M15: 0 | N15: 0 | O15: 365324800 | P15: 0 | Q15: -6088747 | R15: -6088747 | S15: 359236053 | T15: NM Đức Hòa | U15: 0
A16: Z21120A | B16: Máy móc, thiết bị - QL 642 | L16: =L17 -> 57000000 | N16: 0
C17: 106000001 | D17: Máy chà sàn công nghiệp Pullman PMA510B, ắc quy | E17: DH01 | F17: 43843 | G17: 43843 | H17: 60 | I17: 1001202000 | J17: 6424001903 | K17: 0 | L17: 57000000 | M17: 0 | N17: 0 | O17: 57000000 | P17: 0 | Q17: -11400000 | R17: -11400000 | S17: 45600000 | T17: NM Đức Hòa | U17: 0
A18: Z21130P | B18: Phương tiện vận tải , truyền dẫn - SX 627 | L18: =L19 -> 380000000 | N18: 0
C19: 107000001 | D19: Xe nâng dầu Komatsu 2500kg (Xe số 3) | E19: DH01 | F19: 44105 | G19: 44118 | H19: 60 | I19: 1001602000 | J19: 6274001905 | K19: 0 | L19: 380000000 | M19: 0 | N19: 0 | O19: 380000000 | P19: 0 | Q19: -19000000 | R19: -19000000 | S19: 361000000 | T19: NM Đức Hòa | U19: 0
A20: TỔNG TSCĐ TĂNG 2020 | K20: 100353197101 | L20: =L2+L6+L16+L18 -> 4697651482 | M20: -1907602500 | N20: 0 | O20: 85841944994 | P20: -64795216716 | Q20: -2454814695 | R20: -2454814695 | S20: 80035321837 | U20: 0

Sheet Nhà cửa vật kiến trúc (VNĐ)
F1: =SUM(F2:F5) -> 205439155712
A2: ĐẦU TƯ NHÀ CỬA VẬT KIẾN TRÚC 2010 -> 2024 | E2: 2021 | F2: =SUMIF($B$11:$B$1003,E2,$F$11:$F$1003) -> 98740200260
E3: 2022 | F3: =SUMIF($B$11:$B$1003,E3,$F$11:$F$1003) -> 45313950003
E4: 2023 | F4: =SUMIF($B$11:$B$1003,E4,$F$11:$F$1003) -> 58568025289
E5: 2024 | F5: =SUMIF($B$11:$B$1003,E5,$F$11:$F$1003) -> 2816980160
E6: 2025 | F6: =SUMIF($B$11:$B$1003,E6,$F$11:$F$1003) -> 1842503798
E7: 2026 | F7: =SUMIF($B$11:$B$1003,E7,$F$11:$F$1003) -> 1087426293
B10: Năm | C10: Nhóm tài sản | D10: Mã tài sản | E10: Diễn giải tài sản 1 | F10: Nguyên giá đầu kỳ (VNĐ)
A11: File Thạnh Phát | B11: 2021 | C11: Z21110P | D11: 101000000 | E11: Nhà xưởng số 03 | F11: 23688321578
A12: File Thạnh Phát | B12: 2021 | C12: Z21110P | D12: 101000001 | E12: Hạng mục làm đường nhà máy | F12: 3206333890
A13: File Thạnh Phát | B13: 2021 | C13: Z21110P | D13: 101000002 | E13: Nhà kho lều bạt | F13: 445541459
A14: File Thạnh Phát | B14: 2021 | C14: Z21110A | D14: 103000000 | E14: Nhà để xe CNV | F14: 36001880
A15: File Thạnh Phát | B15: 2021 | C15: Z21110A | D15: 103000001 | E15: Thiết kế nội thất văn phòng xưởng 03 | F15: 2813240158
A16: File Thạnh Phát | B16: 2021 | C16: Z21110A | D16: 103000002 | E16: Văn phòng xưởng 03 | F16: 13526642799
A17: File Thạnh Phát | B17: 2021 | C17: Z21120P | D17: 104000068 | E17: Hệ thống xử lý nước thải ChengWoen | F17: 46492741763
A18: File Thạnh Phát | B18: 2021 | C18: Z211201P | D18: 104600020 | E18: Đường ống nén khí xưởng 03 | F18: 758031567
A19: File Thạnh Phát | B19: 2021 | C19: Z211201P | D19: 104600021 | E19: Hệ thống cách nhiệt bể nước ngầm, Hệ thống PCCC | F19: 3682105850
A20: File Thạnh Phát | B20: 2021 | C20: Z211201P | D20: 104600022 | E20: Hệ thống Điện, cấp thoát Nước xưởng 03 | F20: 1729306981
A21: File Thạnh Phát | B21: 2021 | C21: Z211201P | D21: 104600026 | E21: Hệ thống điện xưởng 03 | F21: 1931331475
A22: File Thạnh Phát | B22: 2021 | C22: Z21120A | D22: 106000003 | E22: Hệ thống máy lạnh âm trần DAIKIN (1.5HP-3.5HP) | F22: 402450000
... A41: File Thạnh Phát | B41: 2022 | C41: Z21150A | D41: 113000000 | E41: Hạng mục trồng cây | F41: 121788182
A42: File Capex TT 2022 | B42: 2022 | D42: 113000001 | E42: Thi công hồ cá | F42: 322740000
A43: File Capex TT 2022 | B43: 2022 | D43: 115000004 | E43: Mái che xếp di động (Nam Trần) | F43: 60800000
A44: File Capex TT 2022 | B44: 2022 | D44: 159000058 | E44: Thi công đường bê tông nhựa | F44: 47250000
A45: File Thạnh Phát | B45: 2023 | C45: Z21110P | D45: 101000012 | E45: Nhà xưởng số F01 | F45: 23184211519
A46: File Thạnh Phát | B46: 2023 | C46: Z21110P | D46: 101000013 | E46: Nhà xưởng số F05 | F46: 14213865604
A47: File Thạnh Phát | B47: 2023 | C47: Z21110P | D47: 101000014 | E47: Sân chứa nguyên liệu, trạm cân | F47: 7312917741
A48: File Thạnh Phát | B48: 2023 | C48: Z21110P | D48: 101000015 | E48: Đường bê tông nhựa | F48: 1365430657
A49: File Thạnh Phát | B49: 2023 | C49: Z21110P | D49: 101000016 | E49: Hệ thống chiếu sáng F01-F05 | F49: 925192275
A50: File Thạnh Phát | B50: 2023 | C50: Z21110A | D50: 103000004 | E50: Văn phòng F02 | F50: 2569997827
A51: File Thạnh Phát | B51: 2023 | C51: Z211201P | D51: 104600062 | E51: Hệ thống PCCC xưởng F04 | F51: 941765419
A52: File Thạnh Phát | B52: 2023 | C52: Z211201P | D52: 104600063 | E52: Hệ thống PCCC xưởng F01 & F05 | F52: 2335337725
A53: File Thạnh Phát | B53: 2023 | C53: Z211201P | D53: 104600069 | E53: Máy tách nhãn chai Pet PVN-800 | F53: 773334901
A54: File Thạnh Phát | B54: 2023 | C54: Z21130P | D54: 107000032 | E54: Sàn nâng thủy lực | F54: 284144493
A55: File Thạnh Phát | B55: 2023 | C55: Z21150A | D55: 113000002 | E55: Trồng cây cảnh quan | F55: 151000000
A56: File Capex TT 2023 | B56: 2023 | C56: Z21110P | D56: 101000019 | E56: Hệ thống làm mát nhà xưởng | F56: 958076791
... A89: File Capex TT 2026 | B89: 2026 | C89: Z21110P | D89: 101000032 | E89: Mái che hồ nước sản xuất F3 | F89: 364888127

Sheet Thạnh Phát sở hữu
E2: 1 | R2: =COLUMNS(E2:R2) -> 14
R3: =SUBTOTAL(9,R6:R48) -> 221664376315
A4: Phân loại | B4: Phân nhóm SP | C4: Năm | D4: Nhóm tài sản | E4: Mã tài sản | F4: Diễn giải tài sản 1 | G4: Ngày ghi nhận TS | H4: Ngày bắt đầu KH | I4: T/G Khấu hao | J4: Cost center | L4: Work center | M4: Nhóm TK | N4: Tài khoản KH | O4: Tài khoản KH KTQT xác định | P4: Nguyên giá đầu kỳ (ngoại tệ) | Q4: Loại ngoại tê | R4: Nguyên giá đầu kỳ (VNĐ) | S4: Gía trị khấu hao 1 tháng | T4: 1 | U4: =+T4+1 -> 2 | V4: =+U4+1 -> 3 | W4: =+V4+1 -> 4 | X4: =+W4+1 -> 5 | Y4: =+X4+1 -> 6 | Z4: =+Y4+1 -> 7 | AA4: =+Z4+1 -> 8 | AB4: =+AA4+1 -> 9 | ... AE4: =+AD4+1 -> 12 | AF4: Số tiền khấu hao năm 2020 | AG4: Giá trị còn lại năm 2020 | AH4: 1 | AI4: 2 | AJ4: 3 | AK4: 4 | AL4: 5 | AM4: 6 | AN4: 7 | AO4: 8 | AP4: 9 | AQ4: 10 | AR4: 11 | AS4: 12 | AT4: Số tiền khấu hao năm 2021 | AU4: Giá trị còn lại năm 2021 | AV4: 1 | AW4: 2 | AX4: 3 | AY4: 4 | AZ4: 5 | BA4: 6 | BB4: 7 | BC4: 8 | BD4: 9 | BE4: 10 | BF4: 11 | BG4: 12 | BH4: Số tiền khấu hao năm 2022 | BI4: Giá trị còn lại năm 2022 | BJ4: 1 | BK4: 2 | BL4: 3 | BM4: 4 | BN4: 5 | BO4: 6 | BP4: 7 | BQ4: 8 | BR4: 9 | BS4: 10 | BT4: 11 | BU4: 12 | BV4: Số tiền khấu hao năm 2023 | BW4: Giá trị còn lại năm 2023 | BX4: 1 | BY4: 2 | BZ4: 3 | CA4: 4 | CB4: 5 | CC4: 6 | CD4: 7 | CE4: 8 | CF4: 9 | CG4: 10 | CH4: 11 | CI4: 12 | CJ4: Số tiền khấu hao năm 2024 | CK4: Giá trị còn lại năm 2024 | CM4: 2020 | CN4: 2021 | CO4: 2022 | CP4: 2023
E5: 1.2 | F5: THẠNH PHÁT SỞ HỮU | S5: =SUM(S6:S48) -> 1.239798e+09 | T5: =SUM(T6:T48) -> 1.239798e+09 | U5: =SUM(U6:U48) -> 1.239798e+09 | V5: =SUM(V6:V48) -> 1.239798e+09 | W5: =SUM(W6:W48) -> 1.239798e+09 | X5: =SUM(X6:X48) -> 1.239798e+09 | Y5: =SUM(Y6:Y48) -> 1.239798e+09 | Z5: =SUM(Z6:Z48) -> 1.239798e+09 | ... CK5: =SUM(CK6:CK48) -> 1.7245556e+11
A6: 6274.4 | B6: Chung | C6: =YEAR(H6) -> 2021 | D6: Z21110P | E6: 101000000 | F6: Nhà xưởng số 03 | G6: 44288 | H6: 44287 | I6: 300 | J6: 1001602000 | K6: Xưởng sản xuất PET | M6: =+LEFT(N6,4) -> 6274 | N6: 6274001901 | R6: 23688321578 | S6: 78961072 | T6: =$S6 -> 78961072 | U6: =$S6 -> 78961072 | V6: =$S6 -> 78961072 | W6: =$S6 -> 78961072 | X6: =$S6 -> 78961072 | Y6: =$S6 -> 78961072 | Z6: =$S6 -> 78961072 | AA6: =$S6 -> 78961072 | ... AE6: =$S6 -> 78961072 | AF6: =+SUM(T6:AE6) -> 9.4753286e+08 | AG6: 0 | AH6: =$S6 -> 78961072 | AI6: =$S6 -> 78961072 | AJ6: =$S6 -> 78961072 | AK6: =$S6 -> 78961072 | AL6: =$S6 -> 78961072 | AM6: =$S6 -> 78961072 | AN6: =$S6 -> 78961072 | AO6: =$S6 -> 78961072 | ... AS6: =$S6 -> 78961072 | AT6: =+SUM(AH6:AS6) -> 9.4753286e+08 | AU6: =+R6-AT6 -> 2.2740789e+10 | AV6: =+IF(YEAR($H6)<$AV$5,$S6,IF(AND(YEAR($H6)=$AV$5,MONTH($H6)<=AV$6),$S6,0)) -> 78961072 | AW6: =+IF(YEAR($H6)<$AV$5,$S6,IF(AND(YEAR($H6)=$AV$5,MONTH($H6)<=AW$6),$S6,0)) -> 78961072 | AX6: =+IF(YEAR($H6)<$AV$5,$S6,IF(AND(YEAR($H6)=$AV$5,MONTH($H6)<=AX$6),$S6,0)) -> 78961072 | AY6: =+IF(YEAR($H6)<$AV$5,$S6,IF(AND(YEAR($H6)=$AV$5,MONTH($H6)<=AY$6),$S6,0)) -> 78961072 | AZ6: =+IF(YEAR($H6)<$AV$5,$S6,IF(AND(YEAR($H6)=$AV$5,MONTH($H6)<=AZ$6),$S6,0)) -> 78961072 | BA6: =+IF(YEAR($H6)<$AV$5,$S6,IF(AND(YEAR($H6)=$AV$5,MONTH($H6)<=BA$6),$S6,0)) -> 78961072 | BB6: =+IF(YEAR($H6)<$AV$5,$S6,IF(AND(YEAR($H6)=$AV$5,MONTH($H6)<=BB$6),$S6,0)) -> 78961072 | BC6: =+IF(YEAR($H6)<$AV$5,$S6,IF(AND(YEAR($H6)=$AV$5,MONTH($H6)<=BC$6),$S6,0)) -> 78961072 | ... BG6: =+IF(YEAR($H6)<$AV$5,$S6,IF(AND(YEAR($H6)=$AV$5,MONTH($H6)<=BG$6),$S6,0)) -> 78961072 | BH6: =+SUM(AV6:BG6) -> 9.4753286e+08 | BI6: =+AU6-BH6 -> 2.1793256e+10 | BJ6: =+IF(YEAR($H6)<$BJ$5,$S6,IF(AND(YEAR($H6)=$BJ$5,MONTH($H6)<=BJ$6),$S6,0)) -> 78961072 | BK6: =+IF(YEAR($H6)<$BJ$5,$S6,IF(AND(YEAR($H6)=$BJ$5,MONTH($H6)<=BK$6),$S6,0)) -> 78961072 | BL6: =+IF(YEAR($H6)<$BJ$5,$S6,IF(AND(YEAR($H6)=$BJ$5,MONTH($H6)<=BL$6),$S6,0)) -> 78961072 | BM6: =+IF(YEAR($H6)<$BJ$5,$S6,IF(AND(YEAR($H6)=$BJ$5,MONTH($H6)<=BM$6),$S6,0)) -> 78961072 | BN6: =+IF(YEAR($H6)<$BJ$5,$S6,IF(AND(YEAR($H6)=$BJ$5,MONTH($H6)<=BN$6),$S6,0)) -> 78961072 | BO6: =+IF(YEAR($H6)<$BJ$5,$S6,IF(AND(YEAR($H6)=$BJ$5,MONTH($H6)<=BO$6),$S6,0)) -> 78961072 | BP6: =+IF(YEAR($H6)<$BJ$5,$S6,IF(AND(YEAR($H6)=$BJ$5,MONTH($H6)<=BP$6),$S6,0)) -> 78961072 | BQ6: =+IF(YEAR($H6)<$BJ$5,$S6,IF(AND(YEAR($H6)=$BJ$5,MONTH($H6)<=BQ$6),$S6,0)) -> 78961072 | ... BU6: =+IF(YEAR($H6)<$BJ$5,$S6,IF(AND(YEAR($H6)=$BJ$5,MONTH($H6)<=BU$6),$S6,0)) -> 78961072 | BV6: =+SUM(BJ6:BU6) -> 9.4753286e+08 | BW6: =+BI6-BV6 -> 2.0845723e+10 | BX6: =+$S6 -> 78961072 | BY6: =+$S6 -> 78961072 | BZ6: =+$S6 -> 78961072 | CA6: =+$S6 -> 78961072 | CB6: =+$S6 -> 78961072 | CC6: =+$S6 -> 78961072 | CD6: =+$S6 -> 78961072 | CE6: =+$S6 -> 78961072 | ... CI6: =+$S6 -> 78961072 | CJ6: =+SUM(BX6:CI6) -> 9.4753286e+08 | CK6: =+BW6-CJ6 -> 1.989819e+10 | CM6: =VLOOKUP($E6,'Capex TT 2020'!$D$5:$F$35,3,0) -> #N/A | CN6: =IFERROR(VLOOKUP($E6,'Capex TT 2021'!$D$5:$F$35,3,0),0) -> 23455092161 | CO6: =VLOOKUP($E6,'Capex TT 2022'!$D$5:$F$35,3,0) -> #N/A | CP6: =VLOOKUP($E6,'Capex TT 2023'!$D$5:$F$35,3,0) -> #N/A
A7: 6274.4 | B7: Chung | C7: =YEAR(H7) -> 2021 | D7: Z21110P | E7: 101000001 | F7: Hạng mục làm đường nhà máy | G7: 44439 | H7: 44438 | I7: 240 | J7: 1001602000 | K7: Xưởng sản xuất PET | M7: =+LEFT(N7,4) -> 6274 | N7: 6274001901 | R7: 3206333890 | S7: 13359725 | T7: =$S7 -> 13359725 | U7: =$S7 -> 13359725 | V7: =$S7 -> 13359725 | W7: =$S7 -> 13359725 | X7: =$S7 -> 13359725 | Y7: =$S7 -> 13359725 | Z7: =$S7 -> 13359725 | AA7: =$S7 -> 13359725 | ... AE7: =$S7 -> 13359725 | AF7: =+SUM(T7:AE7) -> 1.6031669e+08 | AG7: 0 | AH7: =$S7 -> 13359725 | AI7: =$S7 -> 13359725 | AJ7: =$S7 -> 13359725 | AK7: =$S7 -> 13359725 | AL7: =$S7 -> 13359725 | AM7: =$S7 -> 13359725 | AN7: =$S7 -> 13359725 | AO7: =$S7 -> 13359725 | ... AS7: =$S7 -> 13359725 | AT7: =+SUM(AH7:AS7) -> 1.6031669e+08 | AU7: =+R7-AT7 -> 3.0460172e+09 | AV7: =+IF(YEAR($H7)<$AV$5,$S7,IF(AND(YEAR($H7)=$AV$5,MONTH($H7)<=AV$6),$S7,0)) -> 13359725 | AW7: =+IF(YEAR($H7)<$AV$5,$S7,IF(AND(YEAR($H7)=$AV$5,MONTH($H7)<=AW$6),$S7,0)) -> 13359725 | AX7: =+IF(YEAR($H7)<$AV$5,$S7,IF(AND(YEAR($H7)=$AV$5,MONTH($H7)<=AX$6),$S7,0)) -> 13359725 | AY7: =+IF(YEAR($H7)<$AV$5,$S7,IF(AND(YEAR($H7)=$AV$5,MONTH($H7)<=AY$6),$S7,0)) -> 13359725 | AZ7: =+IF(YEAR($H7)<$AV$5,$S7,IF(AND(YEAR($H7)=$AV$5,MONTH($H7)<=AZ$6),$S7,0)) -> 13359725 | BA7: =+IF(YEAR($H7)<$AV$5,$S7,IF(AND(YEAR($H7)=$AV$5,MONTH($H7)<=BA$6),$S7,0)) -> 13359725 | BB7: =+IF(YEAR($H7)<$AV$5,$S7,IF(AND(YEAR($H7)=$AV$5,MONTH($H7)<=BB$6),$S7,0)) -> 13359725 | BC7: =+IF(YEAR($H7)<$AV$5,$S7,IF(AND(YEAR($H7)=$AV$5,MONTH($H7)<=BC$6),$S7,0)) -> 13359725 | ... BG7: =+IF(YEAR($H7)<$AV$5,$S7,IF(AND(YEAR($H7)=$AV$5,MONTH($H7)<=BG$6),$S7,0)) -> 13359725 | BH7: =+SUM(AV7:BG7) -> 1.6031669e+08 | BI7: =+AU7-BH7 -> 2885700501 | BJ7: =+IF(YEAR($H7)<$BJ$5,$S7,IF(AND(YEAR($H7)=$BJ$5,MONTH($H7)<=BJ$6),$S7,0)) -> 13359725 | BK7: =+IF(YEAR($H7)<$BJ$5,$S7,IF(AND(YEAR($H7)=$BJ$5,MONTH($H7)<=BK$6),$S7,0)) -> 13359725 | BL7: =+IF(YEAR($H7)<$BJ$5,$S7,IF(AND(YEAR($H7)=$BJ$5,MONTH($H7)<=BL$6),$S7,0)) -> 13359725 | BM7: =+IF(YEAR($H7)<$BJ$5,$S7,IF(AND(YEAR($H7)=$BJ$5,MONTH($H7)<=BM$6),$S7,0)) -> 13359725 | BN7: =+IF(YEAR($H7)<$BJ$5,$S7,IF(AND(YEAR($H7)=$BJ$5,MONTH($H7)<=BN$6),$S7,0)) -> 13359725 | BO7: =+IF(YEAR($H7)<$BJ$5,$S7,IF(AND(YEAR($H7)=$BJ$5,MONTH($H7)<=BO$6),$S7,0)) -> 13359725 | BP7: =+IF(YEAR($H7)<$BJ$5,$S7,IF(AND(YEAR($H7)=$BJ$5,MONTH($H7)<=BP$6),$S7,0)) -> 13359725 | BQ7: =+IF(YEAR($H7)<$BJ$5,$S7,IF(AND(YEAR($H7)=$BJ$5,MONTH($H7)<=BQ$6),$S7,0)) -> 13359725 | ... BU7: =+IF(YEAR($H7)<$BJ$5,$S7,IF(AND(YEAR($H7)=$BJ$5,MONTH($H7)<=BU$6),$S7,0)) -> 13359725 | BV7: =+SUM(BJ7:BU7) -> 1.6031669e+08 | BW7: =+BI7-BV7 -> 2.7253838e+09 | BX7: =+$S7 -> 13359725 | BY7: =+$S7 -> 13359725 | BZ7: =+$S7 -> 13359725 | CA7: =+$S7 -> 13359725 | CB7: =+$S7 -> 13359725 | CC7: =+$S7 -> 13359725 | CD7: =+$S7 -> 13359725 | CE7: =+$S7 -> 13359725 | ... CI7: =+$S7 -> 13359725 | CJ7: =+SUM(BX7:CI7) -> 1.6031669e+08 | CK7: =+BW7-CJ7 -> 2565067112 | CM7: =VLOOKUP($E7,'Capex TT 2020'!$D$5:$F$35,3,0) -> #N/A | CN7: =IFERROR(VLOOKUP($E7,'Capex TT 2021'!$D$5:$F$35,3,0),0) -> 3206333890 | CO7: =VLOOKUP($E7,'Capex TT 2022'!$D$5:$F$35,3,0) -> #N/A | CP7: =VLOOKUP($E7,'Capex TT 2023'!$D$5:$F$35,3,0) -> #N/A
A8: 6274.4 | B8: Chung | C8: =YEAR(H8) -> 2021 | D8: Z21110P | E8: 101000002 | F8: Nhà kho lều bạt | G8: 44439 | H8: 44438 | I8: 60 | J8: 1001602000 | K8: Xưởng sản xuất PET | M8: =+LEFT(N8,4) -> 6274 | N8: 6274001901 | R8: 445541459 | S8: 7425691 | T8: =$S8 -> 7425691 | U8: =$S8 -> 7425691 | V8: =$S8 -> 7425691 | W8: =$S8 -> 7425691 | X8: =$S8 -> 7425691 | Y8: =$S8 -> 7425691 | Z8: =$S8 -> 7425691 | AA8: =$S8 -> 7425691 | ... AE8: =$S8 -> 7425691 | AF8: =+SUM(T8:AE8) -> 89108292 | AG8: 0 | AH8: =$S8 -> 7425691 | AI8: =$S8 -> 7425691 | AJ8: =$S8 -> 7425691 | AK8: =$S8 -> 7425691 | AL8: =$S8 -> 7425691 | AM8: =$S8 -> 7425691 | AN8: =$S8 -> 7425691 | AO8: =$S8 -> 7425691 | ... AS8: =$S8 -> 7425691 | AT8: =+SUM(AH8:AS8) -> 89108292 | AU8: =+R8-AT8 -> 3.5643317e+08 | AV8: =+IF(YEAR($H8)<$AV$5,$S8,IF(AND(YEAR($H8)=$AV$5,MONTH($H8)<=AV$6),$S8,0)) -> 7425691 | AW8: =+IF(YEAR($H8)<$AV$5,$S8,IF(AND(YEAR($H8)=$AV$5,MONTH($H8)<=AW$6),$S8,0)) -> 7425691 | AX8: =+IF(YEAR($H8)<$AV$5,$S8,IF(AND(YEAR($H8)=$AV$5,MONTH($H8)<=AX$6),$S8,0)) -> 7425691 | AY8: =+IF(YEAR($H8)<$AV$5,$S8,IF(AND(YEAR($H8)=$AV$5,MONTH($H8)<=AY$6),$S8,0)) -> 7425691 | AZ8: =+IF(YEAR($H8)<$AV$5,$S8,IF(AND(YEAR($H8)=$AV$5,MONTH($H8)<=AZ$6),$S8,0)) -> 7425691 | BA8: =+IF(YEAR($H8)<$AV$5,$S8,IF(AND(YEAR($H8)=$AV$5,MONTH($H8)<=BA$6),$S8,0)) -> 7425691 | BB8: =+IF(YEAR($H8)<$AV$5,$S8,IF(AND(YEAR($H8)=$AV$5,MONTH($H8)<=BB$6),$S8,0)) -> 7425691 | BC8: =+IF(YEAR($H8)<$AV$5,$S8,IF(AND(YEAR($H8)=$AV$5,MONTH($H8)<=BC$6),$S8,0)) -> 7425691 | ... BG8: =+IF(YEAR($H8)<$AV$5,$S8,IF(AND(YEAR($H8)=$AV$5,MONTH($H8)<=BG$6),$S8,0)) -> 7425691 | BH8: =+SUM(AV8:BG8) -> 89108292 | BI8: =+AU8-BH8 -> 2.6732488e+08 | BJ8: =+IF(YEAR($H8)<$BJ$5,$S8,IF(AND(YEAR($H8)=$BJ$5,MONTH($H8)<=BJ$6),$S8,0)) -> 7425691 | BK8: =+IF(YEAR($H8)<$BJ$5,$S8,IF(AND(YEAR($H8)=$BJ$5,MONTH($H8)<=BK$6),$S8,0)) -> 7425691 | BL8: =+IF(YEAR($H8)<$BJ$5,$S8,IF(AND(YEAR($H8)=$BJ$5,MONTH($H8)<=BL$6),$S8,0)) -> 7425691 | BM8: =+IF(YEAR($H8)<$BJ$5,$S8,IF(AND(YEAR($H8)=$BJ$5,MONTH($H8)<=BM$6),$S8,0)) -> 7425691 | BN8: =+IF(YEAR($H8)<$BJ$5,$S8,IF(AND(YEAR($H8)=$BJ$5,MONTH($H8)<=BN$6),$S8,0)) -> 7425691 | BO8: =+IF(YEAR($H8)<$BJ$5,$S8,IF(AND(YEAR($H8)=$BJ$5,MONTH($H8)<=BO$6),$S8,0)) -> 7425691 | BP8: =+IF(YEAR($H8)<$BJ$5,$S8,IF(AND(YEAR($H8)=$BJ$5,MONTH($H8)<=BP$6),$S8,0)) -> 7425691 | BQ8: =+IF(YEAR($H8)<$BJ$5,$S8,IF(AND(YEAR($H8)=$BJ$5,MONTH($H8)<=BQ$6),$S8,0)) -> 7425691 | ... BU8: =+IF(YEAR($H8)<$BJ$5,$S8,IF(AND(YEAR($H8)=$BJ$5,MONTH($H8)<=BU$6),$S8,0)) -> 7425691 | BV8: =+SUM(BJ8:BU8) -> 89108292 | BW8: =+BI8-BV8 -> 1.7821658e+08 | BX8: =+$S8 -> 7425691 | BY8: =+$S8 -> 7425691 | BZ8: =+$S8 -> 7425691 | CA8: =+$S8 -> 7425691 | CB8: =+$S8 -> 7425691 | CC8: =+$S8 -> 7425691 | CD8: =+$S8 -> 7425691 | CE8: =+$S8 -> 7425691 | ... CI8: =+$S8 -> 7425691 | CJ8: =+SUM(BX8:CI8) -> 89108292 | CK8: =+BW8-CJ8 -> 89108292 | CM8: =VLOOKUP($E8,'Capex TT 2020'!$D$5:$F$35,3,0) -> #N/A | CN8: =IFERROR(VLOOKUP($E8,'Capex TT 2021'!$D$5:$F$35,3,0),0) -> 445541459 | CO8: =VLOOKUP($E8,'Capex TT 2022'!$D$5:$F$35,3,0) -> #N/A | CP8: =VLOOKUP($E8,'Capex TT 2023'!$D$5:$F$35,3,0) -> #N/A
A9: 6274.4 | B9: Chung | C9: =YEAR(H9) -> 2022 | D9: Z21110P | E9: 101000003 | F9: Văn phòng bộ phận kỹ thuật | G9: 44775 | H9: 44757 | I9: 60 | J9: 1001601300 | K9: Kỹ thuật | M9: =+LEFT(N9,4) -> 6274 | N9: 6274001901 | R9: 201303632 | S9: 3355060.5 | T9: =$S9 -> 3355060.5 | U9: =$S9 -> 3355060.5 | V9: =$S9 -> 3355060.5 | W9: =$S9 -> 3355060.5 | X9: =$S9 -> 3355060.5 | Y9: =$S9 -> 3355060.5 | Z9: =$S9 -> 3355060.5 | AA9: =$S9 -> 3355060.5 | ... AE9: =$S9 -> 3355060.5 | AF9: =+SUM(T9:AE9) -> 40260726 | AG9: 0 | AH9: =$S9 -> 3355060.5 | AI9: =$S9 -> 3355060.5 | AJ9: =$S9 -> 3355060.5 | AK9: =$S9 -> 3355060.5 | AL9: =$S9 -> 3355060.5 | AM9: =$S9 -> 3355060.5 | AN9: =$S9 -> 3355060.5 | AO9: =$S9 -> 3355060.5 | ... AS9: =$S9 -> 3355060.5 | AT9: =+SUM(AH9:AS9) -> 40260726 | AU9: 0 | AV9: =+IF(YEAR($H9)<$AV$5,$S9,IF(AND(YEAR($H9)=$AV$5,MONTH($H9)<=AV$6),$S9,0)) -> 3355060.5 | AW9: =+IF(YEAR($H9)<$AV$5,$S9,IF(AND(YEAR($H9)=$AV$5,MONTH($H9)<=AW$6),$S9,0)) -> 3355060.5 | AX9: =+IF(YEAR($H9)<$AV$5,$S9,IF(AND(YEAR($H9)=$AV$5,MONTH($H9)<=AX$6),$S9,0)) -> 3355060.5 | AY9: =+IF(YEAR($H9)<$AV$5,$S9,IF(AND(YEAR($H9)=$AV$5,MONTH($H9)<=AY$6),$S9,0)) -> 3355060.5 | AZ9: =+IF(YEAR($H9)<$AV$5,$S9,IF(AND(YEAR($H9)=$AV$5,MONTH($H9)<=AZ$6),$S9,0)) -> 3355060.5 | BA9: =+IF(YEAR($H9)<$AV$5,$S9,IF(AND(YEAR($H9)=$AV$5,MONTH($H9)<=BA$6),$S9,0)) -> 3355060.5 | BB9: =+IF(YEAR($H9)<$AV$5,$S9,IF(AND(YEAR($H9)=$AV$5,MONTH($H9)<=BB$6),$S9,0)) -> 3355060.5 | BC9: =+IF(YEAR($H9)<$AV$5,$S9,IF(AND(YEAR($H9)=$AV$5,MONTH($H9)<=BC$6),$S9,0)) -> 3355060.5 | ... BG9: =+IF(YEAR($H9)<$AV$5,$S9,IF(AND(YEAR($H9)=$AV$5,MONTH($H9)<=BG$6),$S9,0)) -> 3355060.5 | BH9: =+SUM(AV9:BG9) -> 40260726 | BI9: =+R9-BH9 -> 1.6104291e+08 | BJ9: =+IF(YEAR($H9)<$BJ$5,$S9,IF(AND(YEAR($H9)=$BJ$5,MONTH($H9)<=BJ$6),$S9,0)) -> 3355060.5 | BK9: =+IF(YEAR($H9)<$BJ$5,$S9,IF(AND(YEAR($H9)=$BJ$5,MONTH($H9)<=BK$6),$S9,0)) -> 3355060.5 | BL9: =+IF(YEAR($H9)<$BJ$5,$S9,IF(AND(YEAR($H9)=$BJ$5,MONTH($H9)<=BL$6),$S9,0)) -> 3355060.5 | BM9: =+IF(YEAR($H9)<$BJ$5,$S9,IF(AND(YEAR($H9)=$BJ$5,MONTH($H9)<=BM$6),$S9,0)) -> 3355060.5 | BN9: =+IF(YEAR($H9)<$BJ$5,$S9,IF(AND(YEAR($H9)=$BJ$5,MONTH($H9)<=BN$6),$S9,0)) -> 3355060.5 | BO9: =+IF(YEAR($H9)<$BJ$5,$S9,IF(AND(YEAR($H9)=$BJ$5,MONTH($H9)<=BO$6),$S9,0)) -> 3355060.5 | BP9: =+IF(YEAR($H9)<$BJ$5,$S9,IF(AND(YEAR($H9)=$BJ$5,MONTH($H9)<=BP$6),$S9,0)) -> 3355060.5 | BQ9: =+IF(YEAR($H9)<$BJ$5,$S9,IF(AND(YEAR($H9)=$BJ$5,MONTH($H9)<=BQ$6),$S9,0)) -> 3355060.5 | ... BU9: =+IF(YEAR($H9)<$BJ$5,$S9,IF(AND(YEAR($H9)=$BJ$5,MONTH($H9)<=BU$6),$S9,0)) -> 3355060.5 | BV9: =+SUM(BJ9:BU9) -> 40260726 | BW9: =+BI9-BV9 -> 1.2078218e+08 | BX9: =+$S9 -> 3355060.5 | BY9: =+$S9 -> 3355060.5 | BZ9: =+$S9 -> 3355060.5 | CA9: =+$S9 -> 3355060.5 | CB9: =+$S9 -> 3355060.5 | CC9: =+$S9 -> 3355060.5 | CD9: =+$S9 -> 3355060.5 | CE9: =+$S9 -> 3355060.5 | ... CI9: =+$S9 -> 3355060.5 | CJ9: =+SUM(BX9:CI9) -> 40260726 | CK9: =+BW9-CJ9 -> 80521453 | CM9: =VLOOKUP($E9,'Capex TT 2020'!$D$5:$F$35,3,0) -> #N/A | CN9: =IFERROR(VLOOKUP($E9,'Capex TT 2021'!$D$5:$F$35,3,0),0) -> 0 | CO9: =VLOOKUP($E9,'Capex TT 2022'!$D$5:$F$35,3,0) -> #N/A | CP9: =VLOOKUP($E9,'Capex TT 2023'!$D$5:$F$35,3,0) -> #N/A
A10: 6274.4 | B10: Chung | C10: =YEAR(H10) -> 2022 | D10: Z21110P | E10: 101000004 | F10: Xây dựng phòng Quản lý chất lượng | G10: 44775 | H10: 44757 | I10: 60 | J10: 1001601400 | K10: Kiểm soát chất lượng | M10: =+LEFT(N10,4) -> 6274 | N10: 6274001901 | R10: 269569137 | S10: 4492819 | T10: =$S10 -> 4492819 | U10: =$S10 -> 4492819 | V10: =$S10 -> 4492819 | W10: =$S10 -> 4492819 | X10: =$S10 -> 4492819 | Y10: =$S10 -> 4492819 | Z10: =$S10 -> 4492819 | AA10: =$S10 -> 4492819 | ... AE10: =$S10 -> 4492819 | AF10: =+SUM(T10:AE10) -> 53913827 | AG10: 0 | AH10: =$S10 -> 4492819 | AI10: =$S10 -> 4492819 | AJ10: =$S10 -> 4492819 | AK10: =$S10 -> 4492819 | AL10: =$S10 -> 4492819 | AM10: =$S10 -> 4492819 | AN10: =$S10 -> 4492819 | AO10: =$S10 -> 4492819 | ... AS10: =$S10 -> 4492819 | AT10: =+SUM(AH10:AS10) -> 53913827 | AU10: 0 | AV10: =+IF(YEAR($H10)<$AV$5,$S10,IF(AND(YEAR($H10)=$AV$5,MONTH($H10)<=AV$6),$S10,0)) -> 4492819 | AW10: =+IF(YEAR($H10)<$AV$5,$S10,IF(AND(YEAR($H10)=$AV$5,MONTH($H10)<=AW$6),$S10,0)) -> 4492819 | AX10: =+IF(YEAR($H10)<$AV$5,$S10,IF(AND(YEAR($H10)=$AV$5,MONTH($H10)<=AX$6),$S10,0)) -> 4492819 | AY10: =+IF(YEAR($H10)<$AV$5,$S10,IF(AND(YEAR($H10)=$AV$5,MONTH($H10)<=AY$6),$S10,0)) -> 4492819 | AZ10: =+IF(YEAR($H10)<$AV$5,$S10,IF(AND(YEAR($H10)=$AV$5,MONTH($H10)<=AZ$6),$S10,0)) -> 4492819 | BA10: =+IF(YEAR($H10)<$AV$5,$S10,IF(AND(YEAR($H10)=$AV$5,MONTH($H10)<=BA$6),$S10,0)) -> 4492819 | BB10: =+IF(YEAR($H10)<$AV$5,$S10,IF(AND(YEAR($H10)=$AV$5,MONTH($H10)<=BB$6),$S10,0)) -> 4492819 | BC10: =+IF(YEAR($H10)<$AV$5,$S10,IF(AND(YEAR($H10)=$AV$5,MONTH($H10)<=BC$6),$S10,0)) -> 4492819 | ... BG10: =+IF(YEAR($H10)<$AV$5,$S10,IF(AND(YEAR($H10)=$AV$5,MONTH($H10)<=BG$6),$S10,0)) -> 4492819 | BH10: =+SUM(AV10:BG10) -> 53913827 | BI10: =+R10-BH10 -> 2.1565531e+08 | BJ10: =+IF(YEAR($H10)<$BJ$5,$S10,IF(AND(YEAR($H10)=$BJ$5,MONTH($H10)<=BJ$6),$S10,0)) -> 4492819 | BK10: =+IF(YEAR($H10)<$BJ$5,$S10,IF(AND(YEAR($H10)=$BJ$5,MONTH($H10)<=BK$6),$S10,0)) -> 4492819 | BL10: =+IF(YEAR($H10)<$BJ$5,$S10,IF(AND(YEAR($H10)=$BJ$5,MONTH($H10)<=BL$6),$S10,0)) -> 4492819 | BM10: =+IF(YEAR($H10)<$BJ$5,$S10,IF(AND(YEAR($H10)=$BJ$5,MONTH($H10)<=BM$6),$S10,0)) -> 4492819 | BN10: =+IF(YEAR($H10)<$BJ$5,$S10,IF(AND(YEAR($H10)=$BJ$5,MONTH($H10)<=BN$6),$S10,0)) -> 4492819 | BO10: =+IF(YEAR($H10)<$BJ$5,$S10,IF(AND(YEAR($H10)=$BJ$5,MONTH($H10)<=BO$6),$S10,0)) -> 4492819 | BP10: =+IF(YEAR($H10)<$BJ$5,$S10,IF(AND(YEAR($H10)=$BJ$5,MONTH($H10)<=BP$6),$S10,0)) -> 4492819 | BQ10: =+IF(YEAR($H10)<$BJ$5,$S10,IF(AND(YEAR($H10)=$BJ$5,MONTH($H10)<=BQ$6),$S10,0)) -> 4492819 | ... BU10: =+IF(YEAR($H10)<$BJ$5,$S10,IF(AND(YEAR($H10)=$BJ$5,MONTH($H10)<=BU$6),$S10,0)) -> 4492819 | BV10: =+SUM(BJ10:BU10) -> 53913827 | BW10: =+BI10-BV10 -> 1.6174148e+08 | BX10: =+$S10 -> 4492819 | BY10: =+$S10 -> 4492819 | BZ10: =+$S10 -> 4492819 | CA10: =+$S10 -> 4492819 | CB10: =+$S10 -> 4492819 | CC10: =+$S10 -> 4492819 | CD10: =+$S10 -> 4492819 | CE10: =+$S10 -> 4492819 | ... CI10: =+$S10 -> 4492819 | CJ10: =+SUM(BX10:CI10) -> 53913827 | CK10: =+BW10-CJ10 -> 1.0782765e+08 | CM10: =VLOOKUP($E10,'Capex TT 2020'!$D$5:$F$35,3,0) -> #N/A | CN10: =IFERROR(VLOOKUP($E10,'Capex TT 2021'!$D$5:$F$35,3,0),0) -> 0 | CO10: =VLOOKUP($E10,'Capex TT 2022'!$D$5:$F$35,3,0) -> #N/A | CP10: =VLOOKUP($E10,'Capex TT 2023'!$D$5:$F$35,3,0) -> #N/A
A11: 6274.4 | B11: Chung | C11: =YEAR(H11) -> 2022 | D11: Z21110P | E11: 101000005 | F11: Nhà xưởng số F02 | G11: 44804 | H11: 44788 | I11: 300 | J11: 1001604000 | K11: Khối SX - Xưởng 2 | M11: =+LEFT(N11,4) -> 6274 | N11: 6274001901 | R11: 24510513422 | S11: 81701711 | T11: =$S11 -> 81701711 | U11: =$S11 -> 81701711 | V11: =$S11 -> 81701711 | W11: =$S11 -> 81701711 | X11: =$S11 -> 81701711 | Y11: =$S11 -> 81701711 | Z11: =$S11 -> 81701711 | AA11: =$S11 -> 81701711 | ... AE11: =$S11 -> 81701711 | AF11: =+SUM(T11:AE11) -> 9.8042054e+08 | AG11: 0 | AH11: =$S11 -> 81701711 | AI11: =$S11 -> 81701711 | AJ11: =$S11 -> 81701711 | AK11: =$S11 -> 81701711 | AL11: =$S11 -> 81701711 | AM11: =$S11 -> 81701711 | AN11: =$S11 -> 81701711 | AO11: =$S11 -> 81701711 | ... AS11: =$S11 -> 81701711 | AT11: =+SUM(AH11:AS11) -> 9.8042054e+08 | AU11: 0 | AV11: =+IF(YEAR($H11)<$AV$5,$S11,IF(AND(YEAR($H11)=$AV$5,MONTH($H11)<=AV$6),$S11,0)) -> 81701711 | AW11: =+IF(YEAR($H11)<$AV$5,$S11,IF(AND(YEAR($H11)=$AV$5,MONTH($H11)<=AW$6),$S11,0)) -> 81701711 | AX11: =+IF(YEAR($H11)<$AV$5,$S11,IF(AND(YEAR($H11)=$AV$5,MONTH($H11)<=AX$6),$S11,0)) -> 81701711 | AY11: =+IF(YEAR($H11)<$AV$5,$S11,IF(AND(YEAR($H11)=$AV$5,MONTH($H11)<=AY$6),$S11,0)) -> 81701711 | AZ11: =+IF(YEAR($H11)<$AV$5,$S11,IF(AND(YEAR($H11)=$AV$5,MONTH($H11)<=AZ$6),$S11,0)) -> 81701711 | BA11: =+IF(YEAR($H11)<$AV$5,$S11,IF(AND(YEAR($H11)=$AV$5,MONTH($H11)<=BA$6),$S11,0)) -> 81701711 | BB11: =+IF(YEAR($H11)<$AV$5,$S11,IF(AND(YEAR($H11)=$AV$5,MONTH($H11)<=BB$6),$S11,0)) -> 81701711 | BC11: =+IF(YEAR($H11)<$AV$5,$S11,IF(AND(YEAR($H11)=$AV$5,MONTH($H11)<=BC$6),$S11,0)) -> 81701711 | ... BG11: =+IF(YEAR($H11)<$AV$5,$S11,IF(AND(YEAR($H11)=$AV$5,MONTH($H11)<=BG$6),$S11,0)) -> 81701711 | BH11: =+SUM(AV11:BG11) -> 9.8042054e+08 | BI11: =+R11-BH11 -> 2.3530093e+10 | BJ11: =+IF(YEAR($H11)<$BJ$5,$S11,IF(AND(YEAR($H11)=$BJ$5,MONTH($H11)<=BJ$6),$S11,0)) -> 81701711 | BK11: =+IF(YEAR($H11)<$BJ$5,$S11,IF(AND(YEAR($H11)=$BJ$5,MONTH($H11)<=BK$6),$S11,0)) -> 81701711 | BL11: =+IF(YEAR($H11)<$BJ$5,$S11,IF(AND(YEAR($H11)=$BJ$5,MONTH($H11)<=BL$6),$S11,0)) -> 81701711 | BM11: =+IF(YEAR($H11)<$BJ$5,$S11,IF(AND(YEAR($H11)=$BJ$5,MONTH($H11)<=BM$6),$S11,0)) -> 81701711 | BN11: =+IF(YEAR($H11)<$BJ$5,$S11,IF(AND(YEAR($H11)=$BJ$5,MONTH($H11)<=BN$6),$S11,0)) -> 81701711 | BO11: =+IF(YEAR($H11)<$BJ$5,$S11,IF(AND(YEAR($H11)=$BJ$5,MONTH($H11)<=BO$6),$S11,0)) -> 81701711 | BP11: =+IF(YEAR($H11)<$BJ$5,$S11,IF(AND(YEAR($H11)=$BJ$5,MONTH($H11)<=BP$6),$S11,0)) -> 81701711 | BQ11: =+IF(YEAR($H11)<$BJ$5,$S11,IF(AND(YEAR($H11)=$BJ$5,MONTH($H11)<=BQ$6),$S11,0)) -> 81701711 | ... BU11: =+IF(YEAR($H11)<$BJ$5,$S11,IF(AND(YEAR($H11)=$BJ$5,MONTH($H11)<=BU$6),$S11,0)) -> 81701711 | BV11: =+SUM(BJ11:BU11) -> 9.8042054e+08 | BW11: =+BI11-BV11 -> 2.2549672e+10 | BX11: =+$S11 -> 81701711 | BY11: =+$S11 -> 81701711 | BZ11: =+$S11 -> 81701711 | CA11: =+$S11 -> 81701711 | CB11: =+$S11 -> 81701711 | CC11: =+$S11 -> 81701711 | CD11: =+$S11 -> 81701711 | CE11: =+$S11 -> 81701711 | ... CI11: =+$S11 -> 81701711 | CJ11: =+SUM(BX11:CI11) -> 9.8042054e+08 | CK11: =+BW11-CJ11 -> 2.1569252e+10 | CM11: =VLOOKUP($E11,'Capex TT 2020'!$D$5:$F$35,3,0) -> #N/A | CN11: =IFERROR(VLOOKUP($E11,'Capex TT 2021'!$D$5:$F$35,3,0),0) -> 0 | CO11: =VLOOKUP($E11,'Capex TT 2022'!$D$5:$F$35,3,0) -> #N/A | CP11: =VLOOKUP($E11,'Capex TT 2023'!$D$5:$F$35,3,0) -> #N/A
A12: 6274.4 | B12: Chung | C12: =YEAR(H12) -> 2022 | D12: Z21110P | E12: 101000006 | F12: Nhà chứa hóa chất XLNT | G12: 44804 | H12: 44788 | I12: 60 | J12: 1001602000 | K12: Xưởng sản xuất PET | M12: =+LEFT(N12,4) -> 6274 | N12: 6274001901 | R12: 210559021 | S12: 3509317 | T12: =$S12 -> 3509317 | U12: =$S12 -> 3509317 | V12: =$S12 -> 3509317 | W12: =$S12 -> 3509317 | X12: =$S12 -> 3509317 | Y12: =$S12 -> 3509317 | Z12: =$S12 -> 3509317 | AA12: =$S12 -> 3509317 | ... AE12: =$S12 -> 3509317 | AF12: =+SUM(T12:AE12) -> 42111804 | AG12: 0 | AH12: =$S12 -> 3509317 | AI12: =$S12 -> 3509317 | AJ12: =$S12 -> 3509317 | AK12: =$S12 -> 3509317 | AL12: =$S12 -> 3509317 | AM12: =$S12 -> 3509317 | AN12: =$S12 -> 3509317 | AO12: =$S12 -> 3509317 | ... AS12: =$S12 -> 3509317 | AT12: =+SUM(AH12:AS12) -> 42111804 | AU12: 0 | AV12: =+IF(YEAR($H12)<$AV$5,$S12,IF(AND(YEAR($H12)=$AV$5,MONTH($H12)<=AV$6),$S12,0)) -> 3509317 | AW12: =+IF(YEAR($H12)<$AV$5,$S12,IF(AND(YEAR($H12)=$AV$5,MONTH($H12)<=AW$6),$S12,0)) -> 3509317 | AX12: =+IF(YEAR($H12)<$AV$5,$S12,IF(AND(YEAR($H12)=$AV$5,MONTH($H12)<=AX$6),$S12,0)) -> 3509317 | AY12: =+IF(YEAR($H12)<$AV$5,$S12,IF(AND(YEAR($H12)=$AV$5,MONTH($H12)<=AY$6),$S12,0)) -> 3509317 | AZ12: =+IF(YEAR($H12)<$AV$5,$S12,IF(AND(YEAR($H12)=$AV$5,MONTH($H12)<=AZ$6),$S12,0)) -> 3509317 | BA12: =+IF(YEAR($H12)<$AV$5,$S12,IF(AND(YEAR($H12)=$AV$5,MONTH($H12)<=BA$6),$S12,0)) -> 3509317 | BB12: =+IF(YEAR($H12)<$AV$5,$S12,IF(AND(YEAR($H12)=$AV$5,MONTH($H12)<=BB$6),$S12,0)) -> 3509317 | BC12: =+IF(YEAR($H12)<$AV$5,$S12,IF(AND(YEAR($H12)=$AV$5,MONTH($H12)<=BC$6),$S12,0)) -> 3509317 | ... BG12: =+IF(YEAR($H12)<$AV$5,$S12,IF(AND(YEAR($H12)=$AV$5,MONTH($H12)<=BG$6),$S12,0)) -> 3509317 | BH12: =+SUM(AV12:BG12) -> 42111804 | BI12: =+R12-BH12 -> 1.6844722e+08 | BJ12: =+IF(YEAR($H12)<$BJ$5,$S12,IF(AND(YEAR($H12)=$BJ$5,MONTH($H12)<=BJ$6),$S12,0)) -> 3509317 | BK12: =+IF(YEAR($H12)<$BJ$5,$S12,IF(AND(YEAR($H12)=$BJ$5,MONTH($H12)<=BK$6),$S12,0)) -> 3509317 | BL12: =+IF(YEAR($H12)<$BJ$5,$S12,IF(AND(YEAR($H12)=$BJ$5,MONTH($H12)<=BL$6),$S12,0)) -> 3509317 | BM12: =+IF(YEAR($H12)<$BJ$5,$S12,IF(AND(YEAR($H12)=$BJ$5,MONTH($H12)<=BM$6),$S12,0)) -> 3509317 | BN12: =+IF(YEAR($H12)<$BJ$5,$S12,IF(AND(YEAR($H12)=$BJ$5,MONTH($H12)<=BN$6),$S12,0)) -> 3509317 | BO12: =+IF(YEAR($H12)<$BJ$5,$S12,IF(AND(YEAR($H12)=$BJ$5,MONTH($H12)<=BO$6),$S12,0)) -> 3509317 | BP12: =+IF(YEAR($H12)<$BJ$5,$S12,IF(AND(YEAR($H12)=$BJ$5,MONTH($H12)<=BP$6),$S12,0)) -> 3509317 | BQ12: =+IF(YEAR($H12)<$BJ$5,$S12,IF(AND(YEAR($H12)=$BJ$5,MONTH($H12)<=BQ$6),$S12,0)) -> 3509317 | ... BU12: =+IF(YEAR($H12)<$BJ$5,$S12,IF(AND(YEAR($H12)=$BJ$5,MONTH($H12)<=BU$6),$S12,0)) -> 3509317 | BV12: =+SUM(BJ12:BU12) -> 42111804 | BW12: =+BI12-BV12 -> 1.2633541e+08 | BX12: =+$S12 -> 3509317 | BY12: =+$S12 -> 3509317 | BZ12: =+$S12 -> 3509317 | CA12: =+$S12 -> 3509317 | CB12: =+$S12 -> 3509317 | CC12: =+$S12 -> 3509317 | CD12: =+$S12 -> 3509317 | CE12: =+$S12 -> 3509317 | ... CI12: =+$S12 -> 3509317 | CJ12: =+SUM(BX12:CI12) -> 42111804 | CK12: =+BW12-CJ12 -> 84223608 | CM12: =VLOOKUP($E12,'Capex TT 2020'!$D$5:$F$35,3,0) -> #N/A | CN12: =IFERROR(VLOOKUP($E12,'Capex TT 2021'!$D$5:$F$35,3,0),0) -> 0 | CO12: =VLOOKUP($E12,'Capex TT 2022'!$D$5:$F$35,3,0) -> #N/A | CP12: =VLOOKUP($E12,'Capex TT 2023'!$D$5:$F$35,3,0) -> #N/A
A13: 6274.4 | B13: Chung | C13: =YEAR(H13) -> 2022 | D13: Z21110P | E13: 101000007 | F13: Hạ tầng kỹ thuật xưởng F02 | G13: 44820 | H13: 44819 | I13: 72 | J13: 1001604000 | K13: Khối SX - Xưởng 2 | M13: =+LEFT(N13,4) -> 6274 | N13: 6274001901 | R13: 1701337836 | S13: 23629692 | T13: =$S13 -> 23629692 | U13: =$S13 -> 23629692 | V13: =$S13 -> 23629692 | W13: =$S13 -> 23629692 | X13: =$S13 -> 23629692 | Y13: =$S13 -> 23629692 | Z13: =$S13 -> 23629692 | AA13: =$S13 -> 23629692 | ... AE13: =$S13 -> 23629692 | AF13: =+SUM(T13:AE13) -> 2.8355631e+08 | AG13: 0 | AH13: =$S13 -> 23629692 | AI13: =$S13 -> 23629692 | AJ13: =$S13 -> 23629692 | AK13: =$S13 -> 23629692 | AL13: =$S13 -> 23629692 | AM13: =$S13 -> 23629692 | AN13: =$S13 -> 23629692 | AO13: =$S13 -> 23629692 | ... AS13: =$S13 -> 23629692 | AT13: =+SUM(AH13:AS13) -> 2.8355631e+08 | AU13: 0 | AV13: =+IF(YEAR($H13)<$AV$5,$S13,IF(AND(YEAR($H13)=$AV$5,MONTH($H13)<=AV$6),$S13,0)) -> 23629692 | AW13: =+IF(YEAR($H13)<$AV$5,$S13,IF(AND(YEAR($H13)=$AV$5,MONTH($H13)<=AW$6),$S13,0)) -> 23629692 | AX13: =+IF(YEAR($H13)<$AV$5,$S13,IF(AND(YEAR($H13)=$AV$5,MONTH($H13)<=AX$6),$S13,0)) -> 23629692 | AY13: =+IF(YEAR($H13)<$AV$5,$S13,IF(AND(YEAR($H13)=$AV$5,MONTH($H13)<=AY$6),$S13,0)) -> 23629692 | AZ13: =+IF(YEAR($H13)<$AV$5,$S13,IF(AND(YEAR($H13)=$AV$5,MONTH($H13)<=AZ$6),$S13,0)) -> 23629692 | BA13: =+IF(YEAR($H13)<$AV$5,$S13,IF(AND(YEAR($H13)=$AV$5,MONTH($H13)<=BA$6),$S13,0)) -> 23629692 | BB13: =+IF(YEAR($H13)<$AV$5,$S13,IF(AND(YEAR($H13)=$AV$5,MONTH($H13)<=BB$6),$S13,0)) -> 23629692 | BC13: =+IF(YEAR($H13)<$AV$5,$S13,IF(AND(YEAR($H13)=$AV$5,MONTH($H13)<=BC$6),$S13,0)) -> 23629692 | ... BG13: =+IF(YEAR($H13)<$AV$5,$S13,IF(AND(YEAR($H13)=$AV$5,MONTH($H13)<=BG$6),$S13,0)) -> 23629692 | BH13: =+SUM(AV13:BG13) -> 2.8355631e+08 | BI13: =+R13-BH13 -> 1417781530 | BJ13: =+IF(YEAR($H13)<$BJ$5,$S13,IF(AND(YEAR($H13)=$BJ$5,MONTH($H13)<=BJ$6),$S13,0)) -> 23629692 | BK13: =+IF(YEAR($H13)<$BJ$5,$S13,IF(AND(YEAR($H13)=$BJ$5,MONTH($H13)<=BK$6),$S13,0)) -> 23629692 | BL13: =+IF(YEAR($H13)<$BJ$5,$S13,IF(AND(YEAR($H13)=$BJ$5,MONTH($H13)<=BL$6),$S13,0)) -> 23629692 | BM13: =+IF(YEAR($H13)<$BJ$5,$S13,IF(AND(YEAR($H13)=$BJ$5,MONTH($H13)<=BM$6),$S13,0)) -> 23629692 | BN13: =+IF(YEAR($H13)<$BJ$5,$S13,IF(AND(YEAR($H13)=$BJ$5,MONTH($H13)<=BN$6),$S13,0)) -> 23629692 | BO13: =+IF(YEAR($H13)<$BJ$5,$S13,IF(AND(YEAR($H13)=$BJ$5,MONTH($H13)<=BO$6),$S13,0)) -> 23629692 | BP13: =+IF(YEAR($H13)<$BJ$5,$S13,IF(AND(YEAR($H13)=$BJ$5,MONTH($H13)<=BP$6),$S13,0)) -> 23629692 | BQ13: =+IF(YEAR($H13)<$BJ$5,$S13,IF(AND(YEAR($H13)=$BJ$5,MONTH($H13)<=BQ$6),$S13,0)) -> 23629692 | ... BU13: =+IF(YEAR($H13)<$BJ$5,$S13,IF(AND(YEAR($H13)=$BJ$5,MONTH($H13)<=BU$6),$S13,0)) -> 23629692 | BV13: =+SUM(BJ13:BU13) -> 2.8355631e+08 | BW13: =+BI13-BV13 -> 1134225224 | BX13: =+$S13 -> 23629692 | BY13: =+$S13 -> 23629692 | BZ13: =+$S13 -> 23629692 | CA13: =+$S13 -> 23629692 | CB13: =+$S13 -> 23629692 | CC13: =+$S13 -> 23629692 | CD13: =+$S13 -> 23629692 | CE13: =+$S13 -> 23629692 | ... CI13: =+$S13 -> 23629692 | CJ13: =+SUM(BX13:CI13) -> 2.8355631e+08 | CK13: =+BW13-CJ13 -> 850668918 | CM13: =VLOOKUP($E13,'Capex TT 2020'!$D$5:$F$35,3,0) -> #N/A | CN13: =IFERROR(VLOOKUP($E13,'Capex TT 2021'!$D$5:$F$35,3,0),0) -> 0 | CO13: =VLOOKUP($E13,'Capex TT 2022'!$D$5:$F$35,3,0) -> #N/A | CP13: =VLOOKUP($E13,'Capex TT 2023'!$D$5:$F$35,3,0) -> #N/A
A14: 6274.4 | B14: Chung | C14: =YEAR(H14) -> 2022 | D14: Z21110P | E14: 101000008 | F14: Nhà chứa vật tư | G14: 44833 | H14: 44835 | I14: 60 | J14: 1001602000 | K14: Xưởng sản xuất PET | M14: =+LEFT(N14,4) -> 6274 | N14: 6274001901 | R14: 111000050 | S14: 1850000.8 | T14: =$S14 -> 1850000.8 | U14: =$S14 -> 1850000.8 | V14: =$S14 -> 1850000.8 | W14: =$S14 -> 1850000.8 | X14: =$S14 -> 1850000.8 | Y14: =$S14 -> 1850000.8 | Z14: =$S14 -> 1850000.8 | AA14: =$S14 -> 1850000.8 | ... AE14: =$S14 -> 1850000.8 | AF14: =+SUM(T14:AE14) -> 22200010 | AG14: 0 | AH14: =$S14 -> 1850000.8 | AI14: =$S14 -> 1850000.8 | AJ14: =$S14 -> 1850000.8 | AK14: =$S14 -> 1850000.8 | AL14: =$S14 -> 1850000.8 | AM14: =$S14 -> 1850000.8 | AN14: =$S14 -> 1850000.8 | AO14: =$S14 -> 1850000.8 | ... AS14: =$S14 -> 1850000.8 | AT14: =+SUM(AH14:AS14) -> 22200010 | AU14: 0 | AV14: =+IF(YEAR($H14)<$AV$5,$S14,IF(AND(YEAR($H14)=$AV$5,MONTH($H14)<=AV$6),$S14,0)) -> 1850000.8 | AW14: =+IF(YEAR($H14)<$AV$5,$S14,IF(AND(YEAR($H14)=$AV$5,MONTH($H14)<=AW$6),$S14,0)) -> 1850000.8 | AX14: =+IF(YEAR($H14)<$AV$5,$S14,IF(AND(YEAR($H14)=$AV$5,MONTH($H14)<=AX$6),$S14,0)) -> 1850000.8 | AY14: =+IF(YEAR($H14)<$AV$5,$S14,IF(AND(YEAR($H14)=$AV$5,MONTH($H14)<=AY$6),$S14,0)) -> 1850000.8 | AZ14: =+IF(YEAR($H14)<$AV$5,$S14,IF(AND(YEAR($H14)=$AV$5,MONTH($H14)<=AZ$6),$S14,0)) -> 1850000.8 | BA14: =+IF(YEAR($H14)<$AV$5,$S14,IF(AND(YEAR($H14)=$AV$5,MONTH($H14)<=BA$6),$S14,0)) -> 1850000.8 | BB14: =+IF(YEAR($H14)<$AV$5,$S14,IF(AND(YEAR($H14)=$AV$5,MONTH($H14)<=BB$6),$S14,0)) -> 1850000.8 | BC14: =+IF(YEAR($H14)<$AV$5,$S14,IF(AND(YEAR($H14)=$AV$5,MONTH($H14)<=BC$6),$S14,0)) -> 1850000.8 | ... BG14: =+IF(YEAR($H14)<$AV$5,$S14,IF(AND(YEAR($H14)=$AV$5,MONTH($H14)<=BG$6),$S14,0)) -> 1850000.8 | BH14: =+SUM(AV14:BG14) -> 22200010 | BI14: =+R14-BH14 -> 88800040 | BJ14: =+IF(YEAR($H14)<$BJ$5,$S14,IF(AND(YEAR($H14)=$BJ$5,MONTH($H14)<=BJ$6),$S14,0)) -> 1850000.8 | BK14: =+IF(YEAR($H14)<$BJ$5,$S14,IF(AND(YEAR($H14)=$BJ$5,MONTH($H14)<=BK$6),$S14,0)) -> 1850000.8 | BL14: =+IF(YEAR($H14)<$BJ$5,$S14,IF(AND(YEAR($H14)=$BJ$5,MONTH($H14)<=BL$6),$S14,0)) -> 1850000.8 | BM14: =+IF(YEAR($H14)<$BJ$5,$S14,IF(AND(YEAR($H14)=$BJ$5,MONTH($H14)<=BM$6),$S14,0)) -> 1850000.8 | BN14: =+IF(YEAR($H14)<$BJ$5,$S14,IF(AND(YEAR($H14)=$BJ$5,MONTH($H14)<=BN$6),$S14,0)) -> 1850000.8 | BO14: =+IF(YEAR($H14)<$BJ$5,$S14,IF(AND(YEAR($H14)=$BJ$5,MONTH($H14)<=BO$6),$S14,0)) -> 1850000.8 | BP14: =+IF(YEAR($H14)<$BJ$5,$S14,IF(AND(YEAR($H14)=$BJ$5,MONTH($H14)<=BP$6),$S14,0)) -> 1850000.8 | BQ14: =+IF(YEAR($H14)<$BJ$5,$S14,IF(AND(YEAR($H14)=$BJ$5,MONTH($H14)<=BQ$6),$S14,0)) -> 1850000.8 | ... BU14: =+IF(YEAR($H14)<$BJ$5,$S14,IF(AND(YEAR($H14)=$BJ$5,MONTH($H14)<=BU$6),$S14,0)) -> 1850000.8 | BV14: =+SUM(BJ14:BU14) -> 22200010 | BW14: =+BI14-BV14 -> 66600030 | BX14: =+$S14 -> 1850000.8 | BY14: =+$S14 -> 1850000.8 | BZ14: =+$S14 -> 1850000.8 | CA14: =+$S14 -> 1850000.8 | CB14: =+$S14 -> 1850000.8 | CC14: =+$S14 -> 1850000.8 | CD14: =+$S14 -> 1850000.8 | CE14: =+$S14 -> 1850000.8 | ... CI14: =+$S14 -> 1850000.8 | CJ14: =+SUM(BX14:CI14) -> 22200010 | CK14: =+BW14-CJ14 -> 44400020 | CM14: =VLOOKUP($E14,'Capex TT 2020'!$D$5:$F$35,3,0) -> #N/A | CN14: =IFERROR(VLOOKUP($E14,'Capex TT 2021'!$D$5:$F$35,3,0),0) -> 0 | CO14: =VLOOKUP($E14,'Capex TT 2022'!$D$5:$F$35,3,0) -> #N/A | CP14: =VLOOKUP($E14,'Capex TT 2023'!$D$5:$F$35,3,0) -> #N/A
A15: 6274.4 | B15: Chung | C15: =YEAR(H15) -> 2022 | D15: Z21110P | E15: 101000009 | F15: San lắp cát nền chứa nguyên liệu | G15: 44833 | H15: 44835 | I15: 96 | J15: 1001602000 | K15: Xưởng sản xuất PET | M15: =+LEFT(N15,4) -> 6274 | N15: 6274001901 | R15: 3739738080 | S15: 38955605 | T15: =$S15 -> 38955605 | U15: =$S15 -> 38955605 | V15: =$S15 -> 38955605 | W15: =$S15 -> 38955605 | X15: =$S15 -> 38955605 | Y15: =$S15 -> 38955605 | Z15: =$S15 -> 38955605 | AA15: =$S15 -> 38955605 | ... AE15: =$S15 -> 38955605 | AF15: =+SUM(T15:AE15) -> 467467260 | AG15: 0 | AH15: =$S15 -> 38955605 | AI15: =$S15 -> 38955605 | AJ15: =$S15 -> 38955605 | AK15: =$S15 -> 38955605 | AL15: =$S15 -> 38955605 | AM15: =$S15 -> 38955605 | AN15: =$S15 -> 38955605 | AO15: =$S15 -> 38955605 | ... AS15: =$S15 -> 38955605 | AT15: =+SUM(AH15:AS15) -> 467467260 | AU15: 0 | AV15: =+IF(YEAR($H15)<$AV$5,$S15,IF(AND(YEAR($H15)=$AV$5,MONTH($H15)<=AV$6),$S15,0)) -> 38955605 | AW15: =+IF(YEAR($H15)<$AV$5,$S15,IF(AND(YEAR($H15)=$AV$5,MONTH($H15)<=AW$6),$S15,0)) -> 38955605 | AX15: =+IF(YEAR($H15)<$AV$5,$S15,IF(AND(YEAR($H15)=$AV$5,MONTH($H15)<=AX$6),$S15,0)) -> 38955605 | AY15: =+IF(YEAR($H15)<$AV$5,$S15,IF(AND(YEAR($H15)=$AV$5,MONTH($H15)<=AY$6),$S15,0)) -> 38955605 | AZ15: =+IF(YEAR($H15)<$AV$5,$S15,IF(AND(YEAR($H15)=$AV$5,MONTH($H15)<=AZ$6),$S15,0)) -> 38955605 | BA15: =+IF(YEAR($H15)<$AV$5,$S15,IF(AND(YEAR($H15)=$AV$5,MONTH($H15)<=BA$6),$S15,0)) -> 38955605 | BB15: =+IF(YEAR($H15)<$AV$5,$S15,IF(AND(YEAR($H15)=$AV$5,MONTH($H15)<=BB$6),$S15,0)) -> 38955605 | BC15: =+IF(YEAR($H15)<$AV$5,$S15,IF(AND(YEAR($H15)=$AV$5,MONTH($H15)<=BC$6),$S15,0)) -> 38955605 | ... BG15: =+IF(YEAR($H15)<$AV$5,$S15,IF(AND(YEAR($H15)=$AV$5,MONTH($H15)<=BG$6),$S15,0)) -> 38955605 | BH15: =+SUM(AV15:BG15) -> 467467260 | BI15: =+R15-BH15 -> 3272270820 | BJ15: =+IF(YEAR($H15)<$BJ$5,$S15,IF(AND(YEAR($H15)=$BJ$5,MONTH($H15)<=BJ$6),$S15,0)) -> 38955605 | BK15: =+IF(YEAR($H15)<$BJ$5,$S15,IF(AND(YEAR($H15)=$BJ$5,MONTH($H15)<=BK$6),$S15,0)) -> 38955605 | BL15: =+IF(YEAR($H15)<$BJ$5,$S15,IF(AND(YEAR($H15)=$BJ$5,MONTH($H15)<=BL$6),$S15,0)) -> 38955605 | BM15: =+IF(YEAR($H15)<$BJ$5,$S15,IF(AND(YEAR($H15)=$BJ$5,MONTH($H15)<=BM$6),$S15,0)) -> 38955605 | BN15: =+IF(YEAR($H15)<$BJ$5,$S15,IF(AND(YEAR($H15)=$BJ$5,MONTH($H15)<=BN$6),$S15,0)) -> 38955605 | BO15: =+IF(YEAR($H15)<$BJ$5,$S15,IF(AND(YEAR($H15)=$BJ$5,MONTH($H15)<=BO$6),$S15,0)) -> 38955605 | BP15: =+IF(YEAR($H15)<$BJ$5,$S15,IF(AND(YEAR($H15)=$BJ$5,MONTH($H15)<=BP$6),$S15,0)) -> 38955605 | BQ15: =+IF(YEAR($H15)<$BJ$5,$S15,IF(AND(YEAR($H15)=$BJ$5,MONTH($H15)<=BQ$6),$S15,0)) -> 38955605 | ... BU15: =+IF(YEAR($H15)<$BJ$5,$S15,IF(AND(YEAR($H15)=$BJ$5,MONTH($H15)<=BU$6),$S15,0)) -> 38955605 | BV15: =+SUM(BJ15:BU15) -> 467467260 | BW15: =+BI15-BV15 -> 2804803560 | BX15: =+$S15 -> 38955605 | BY15: =+$S15 -> 38955605 | BZ15: =+$S15 -> 38955605 | CA15: =+$S15 -> 38955605 | CB15: =+$S15 -> 38955605 | CC15: =+$S15 -> 38955605 | CD15: =+$S15 -> 38955605 | CE15: =+$S15 -> 38955605 | ... CI15: =+$S15 -> 38955605 | CJ15: =+SUM(BX15:CI15) -> 467467260 | CK15: =+BW15-CJ15 -> 2337336300 | CM15: =VLOOKUP($E15,'Capex TT 2020'!$D$5:$F$35,3,0) -> #N/A | CN15: =IFERROR(VLOOKUP($E15,'Capex TT 2021'!$D$5:$F$35,3,0),0) -> 0 | CO15: =VLOOKUP($E15,'Capex TT 2022'!$D$5:$F$35,3,0) -> #N/A | CP15: =VLOOKUP($E15,'Capex TT 2023'!$D$5:$F$35,3,0) -> #N/A
A16: 6274.4 | B16: Chung | C16: =YEAR(H16) -> 2022 | D16: Z21110P | E16: 101000010 | F16: Kho bao bì xưởng F04 | G16: 44866 | H16: 44866 | I16: 36 | J16: 1001602000 | K16: Xưởng sản xuất PET | M16: =+LEFT(N16,4) -> 6274 | N16: 6274001901 | R16: 83293056 | S16: 2313696 | T16: =$S16 -> 2313696 | U16: =$S16 -> 2313696 | V16: =$S16 -> 2313696 | W16: =$S16 -> 2313696 | X16: =$S16 -> 2313696 | Y16: =$S16 -> 2313696 | Z16: =$S16 -> 2313696 | AA16: =$S16 -> 2313696 | ... AE16: =$S16 -> 2313696 | AF16: =+SUM(T16:AE16) -> 27764352 | AG16: 0 | AH16: =$S16 -> 2313696 | AI16: =$S16 -> 2313696 | AJ16: =$S16 -> 2313696 | AK16: =$S16 -> 2313696 | AL16: =$S16 -> 2313696 | AM16: =$S16 -> 2313696 | AN16: =$S16 -> 2313696 | AO16: =$S16 -> 2313696 | ... AS16: =$S16 -> 2313696 | AT16: =+SUM(AH16:AS16) -> 27764352 | AU16: 0 | AV16: =+IF(YEAR($H16)<$AV$5,$S16,IF(AND(YEAR($H16)=$AV$5,MONTH($H16)<=AV$6),$S16,0)) -> 2313696 | AW16: =+IF(YEAR($H16)<$AV$5,$S16,IF(AND(YEAR($H16)=$AV$5,MONTH($H16)<=AW$6),$S16,0)) -> 2313696 | AX16: =+IF(YEAR($H16)<$AV$5,$S16,IF(AND(YEAR($H16)=$AV$5,MONTH($H16)<=AX$6),$S16,0)) -> 2313696 | AY16: =+IF(YEAR($H16)<$AV$5,$S16,IF(AND(YEAR($H16)=$AV$5,MONTH($H16)<=AY$6),$S16,0)) -> 2313696 | AZ16: =+IF(YEAR($H16)<$AV$5,$S16,IF(AND(YEAR($H16)=$AV$5,MONTH($H16)<=AZ$6),$S16,0)) -> 2313696 | BA16: =+IF(YEAR($H16)<$AV$5,$S16,IF(AND(YEAR($H16)=$AV$5,MONTH($H16)<=BA$6),$S16,0)) -> 2313696 | BB16: =+IF(YEAR($H16)<$AV$5,$S16,IF(AND(YEAR($H16)=$AV$5,MONTH($H16)<=BB$6),$S16,0)) -> 2313696 | BC16: =+IF(YEAR($H16)<$AV$5,$S16,IF(AND(YEAR($H16)=$AV$5,MONTH($H16)<=BC$6),$S16,0)) -> 2313696 | ... BG16: =+IF(YEAR($H16)<$AV$5,$S16,IF(AND(YEAR($H16)=$AV$5,MONTH($H16)<=BG$6),$S16,0)) -> 2313696 | BH16: =+SUM(AV16:BG16) -> 27764352 | BI16: =+R16-BH16 -> 55528704 | BJ16: =+IF(YEAR($H16)<$BJ$5,$S16,IF(AND(YEAR($H16)=$BJ$5,MONTH($H16)<=BJ$6),$S16,0)) -> 2313696 | BK16: =+IF(YEAR($H16)<$BJ$5,$S16,IF(AND(YEAR($H16)=$BJ$5,MONTH($H16)<=BK$6),$S16,0)) -> 2313696 | BL16: =+IF(YEAR($H16)<$BJ$5,$S16,IF(AND(YEAR($H16)=$BJ$5,MONTH($H16)<=BL$6),$S16,0)) -> 2313696 | BM16: =+IF(YEAR($H16)<$BJ$5,$S16,IF(AND(YEAR($H16)=$BJ$5,MONTH($H16)<=BM$6),$S16,0)) -> 2313696 | BN16: =+IF(YEAR($H16)<$BJ$5,$S16,IF(AND(YEAR($H16)=$BJ$5,MONTH($H16)<=BN$6),$S16,0)) -> 2313696 | BO16: =+IF(YEAR($H16)<$BJ$5,$S16,IF(AND(YEAR($H16)=$BJ$5,MONTH($H16)<=BO$6),$S16,0)) -> 2313696 | BP16: =+IF(YEAR($H16)<$BJ$5,$S16,IF(AND(YEAR($H16)=$BJ$5,MONTH($H16)<=BP$6),$S16,0)) -> 2313696 | BQ16: =+IF(YEAR($H16)<$BJ$5,$S16,IF(AND(YEAR($H16)=$BJ$5,MONTH($H16)<=BQ$6),$S16,0)) -> 2313696 | ... BU16: =+IF(YEAR($H16)<$BJ$5,$S16,IF(AND(YEAR($H16)=$BJ$5,MONTH($H16)<=BU$6),$S16,0)) -> 2313696 | BV16: =+SUM(BJ16:BU16) -> 27764352 | BW16: =+BI16-BV16 -> 27764352 | BX16: =+$S16 -> 2313696 | BY16: =+$S16 -> 2313696 | BZ16: =+$S16 -> 2313696 | CA16: =+$S16 -> 2313696 | CB16: =+$S16 -> 2313696 | CC16: =+$S16 -> 2313696 | CD16: =+$S16 -> 2313696 | CE16: =+$S16 -> 2313696 | ... CI16: =+$S16 -> 2313696 | CJ16: =+SUM(BX16:CI16) -> 27764352 | CK16: =+BW16-CJ16 -> 0 | CM16: =VLOOKUP($E16,'Capex TT 2020'!$D$5:$F$35,3,0) -> #N/A | CN16: =IFERROR(VLOOKUP($E16,'Capex TT 2021'!$D$5:$F$35,3,0),0) -> 0 | CO16: =VLOOKUP($E16,'Capex TT 2022'!$D$5:$F$35,3,0) -> #N/A | CP16: =VLOOKUP($E16,'Capex TT 2023'!$D$5:$F$35,3,0) -> #N/A
A17: 6274.4 | B17: Chung | C17: =YEAR(H17) -> 2022 | D17: Z21110P | E17: 101000011 | F17: Nhà xưởng số F04 | G17: 44867 | H17: 44866 | I17: 300 | J17: 1001605000 | K17: Khối SX - Xưởng 4 | M17: =+LEFT(N17,4) -> 6274 | N17: 6274001901 | R17: 10605884537 | S17: 35352948 | T17: =$S17 -> 35352948 | U17: =$S17 -> 35352948 | V17: =$S17 -> 35352948 | W17: =$S17 -> 35352948 | X17: =$S17 -> 35352948 | Y17: =$S17 -> 35352948 | Z17: =$S17 -> 35352948 | AA17: =$S17 -> 35352948 | ... AE17: =$S17 -> 35352948 | AF17: =+SUM(T17:AE17) -> 4.2423538e+08 | AG17: 0 | AH17: =$S17 -> 35352948 | AI17: =$S17 -> 35352948 | AJ17: =$S17 -> 35352948 | AK17: =$S17 -> 35352948 | AL17: =$S17 -> 35352948 | AM17: =$S17 -> 35352948 | AN17: =$S17 -> 35352948 | AO17: =$S17 -> 35352948 | ... AS17: =$S17 -> 35352948 | AT17: =+SUM(AH17:AS17) -> 4.2423538e+08 | AU17: 0 | AV17: =+IF(YEAR($H17)<$AV$5,$S17,IF(AND(YEAR($H17)=$AV$5,MONTH($H17)<=AV$6),$S17,0)) -> 35352948 | AW17: =+IF(YEAR($H17)<$AV$5,$S17,IF(AND(YEAR($H17)=$AV$5,MONTH($H17)<=AW$6),$S17,0)) -> 35352948 | AX17: =+IF(YEAR($H17)<$AV$5,$S17,IF(AND(YEAR($H17)=$AV$5,MONTH($H17)<=AX$6),$S17,0)) -> 35352948 | AY17: =+IF(YEAR($H17)<$AV$5,$S17,IF(AND(YEAR($H17)=$AV$5,MONTH($H17)<=AY$6),$S17,0)) -> 35352948 | AZ17: =+IF(YEAR($H17)<$AV$5,$S17,IF(AND(YEAR($H17)=$AV$5,MONTH($H17)<=AZ$6),$S17,0)) -> 35352948 | BA17: =+IF(YEAR($H17)<$AV$5,$S17,IF(AND(YEAR($H17)=$AV$5,MONTH($H17)<=BA$6),$S17,0)) -> 35352948 | BB17: =+IF(YEAR($H17)<$AV$5,$S17,IF(AND(YEAR($H17)=$AV$5,MONTH($H17)<=BB$6),$S17,0)) -> 35352948 | BC17: =+IF(YEAR($H17)<$AV$5,$S17,IF(AND(YEAR($H17)=$AV$5,MONTH($H17)<=BC$6),$S17,0)) -> 35352948 | ... BG17: =+IF(YEAR($H17)<$AV$5,$S17,IF(AND(YEAR($H17)=$AV$5,MONTH($H17)<=BG$6),$S17,0)) -> 35352948 | BH17: =+SUM(AV17:BG17) -> 4.2423538e+08 | BI17: =+R17-BH17 -> 1.0181649e+10 | BJ17: =+IF(YEAR($H17)<$BJ$5,$S17,IF(AND(YEAR($H17)=$BJ$5,MONTH($H17)<=BJ$6),$S17,0)) -> 35352948 | BK17: =+IF(YEAR($H17)<$BJ$5,$S17,IF(AND(YEAR($H17)=$BJ$5,MONTH($H17)<=BK$6),$S17,0)) -> 35352948 | BL17: =+IF(YEAR($H17)<$BJ$5,$S17,IF(AND(YEAR($H17)=$BJ$5,MONTH($H17)<=BL$6),$S17,0)) -> 35352948 | BM17: =+IF(YEAR($H17)<$BJ$5,$S17,IF(AND(YEAR($H17)=$BJ$5,MONTH($H17)<=BM$6),$S17,0)) -> 35352948 | BN17: =+IF(YEAR($H17)<$BJ$5,$S17,IF(AND(YEAR($H17)=$BJ$5,MONTH($H17)<=BN$6),$S17,0)) -> 35352948 | BO17: =+IF(YEAR($H17)<$BJ$5,$S17,IF(AND(YEAR($H17)=$BJ$5,MONTH($H17)<=BO$6),$S17,0)) -> 35352948 | BP17: =+IF(YEAR($H17)<$BJ$5,$S17,IF(AND(YEAR($H17)=$BJ$5,MONTH($H17)<=BP$6),$S17,0)) -> 35352948 | BQ17: =+IF(YEAR($H17)<$BJ$5,$S17,IF(AND(YEAR($H17)=$BJ$5,MONTH($H17)<=BQ$6),$S17,0)) -> 35352948 | ... BU17: =+IF(YEAR($H17)<$BJ$5,$S17,IF(AND(YEAR($H17)=$BJ$5,MONTH($H17)<=BU$6),$S17,0)) -> 35352948 | BV17: =+SUM(BJ17:BU17) -> 4.2423538e+08 | BW17: =+BI17-BV17 -> 9.7574138e+09 | BX17: =+$S17 -> 35352948 | BY17: =+$S17 -> 35352948 | BZ17: =+$S17 -> 35352948 | CA17: =+$S17 -> 35352948 | CB17: =+$S17 -> 35352948 | CC17: =+$S17 -> 35352948 | CD17: =+$S17 -> 35352948 | CE17: =+$S17 -> 35352948 | ... CI17: =+$S17 -> 35352948 | CJ17: =+SUM(BX17:CI17) -> 4.2423538e+08 | CK17: =+BW17-CJ17 -> 9.3331784e+09 | CM17: =VLOOKUP($E17,'Capex TT 2020'!$D$5:$F$35,3,0) -> #N/A | CN17: =IFERROR(VLOOKUP($E17,'Capex TT 2021'!$D$5:$F$35,3,0),0) -> 0 | CO17: =VLOOKUP($E17,'Capex TT 2022'!$D$5:$F$35,3,0) -> #N/A | CP17: =VLOOKUP($E17,'Capex TT 2023'!$D$5:$F$35,3,0) -> #N/A
A18: 6274.4 | B18: Chung | C18: =YEAR(H18) -> 2023 | D18: Z21110P | E18: 101000012 | F18: Nhà xưởng số F01 | G18: 44914 | H18: 44927 | I18: 300 | J18: 1001603000 | K18: Khối SX - Xưởng 1 | M18: =+LEFT(N18,4) -> 6274 | N18: 6274001901 | R18: 23184211519 | S18: 77280705 | T18: =$S18 -> 77280705 | U18: =$S18 -> 77280705 | V18: =$S18 -> 77280705 | W18: =$S18 -> 77280705 | X18: =$S18 -> 77280705 | Y18: =$S18 -> 77280705 | Z18: =$S18 -> 77280705 | AA18: =$S18 -> 77280705 | ... AE18: =$S18 -> 77280705 | AF18: =+SUM(T18:AE18) -> 9.2736846e+08 | AG18: 0 | AH18: =$S18 -> 77280705 | AI18: =$S18 -> 77280705 | AJ18: =$S18 -> 77280705 | AK18: =$S18 -> 77280705 | AL18: =$S18 -> 77280705 | AM18: =$S18 -> 77280705 | AN18: =$S18 -> 77280705 | AO18: =$S18 -> 77280705 | ... AS18: =$S18 -> 77280705 | AT18: =+SUM(AH18:AS18) -> 9.2736846e+08 | AU18: 0 | AV18: =+IF(YEAR($H18)<$AV$5,$S18,IF(AND(YEAR($H18)=$AV$5,MONTH($H18)<=AV$6),$S18,0)) -> 77280705 | AW18: =+IF(YEAR($H18)<$AV$5,$S18,IF(AND(YEAR($H18)=$AV$5,MONTH($H18)<=AW$6),$S18,0)) -> 77280705 | AX18: =+IF(YEAR($H18)<$AV$5,$S18,IF(AND(YEAR($H18)=$AV$5,MONTH($H18)<=AX$6),$S18,0)) -> 77280705 | AY18: =+IF(YEAR($H18)<$AV$5,$S18,IF(AND(YEAR($H18)=$AV$5,MONTH($H18)<=AY$6),$S18,0)) -> 77280705 | AZ18: =+IF(YEAR($H18)<$AV$5,$S18,IF(AND(YEAR($H18)=$AV$5,MONTH($H18)<=AZ$6),$S18,0)) -> 77280705 | BA18: =+IF(YEAR($H18)<$AV$5,$S18,IF(AND(YEAR($H18)=$AV$5,MONTH($H18)<=BA$6),$S18,0)) -> 77280705 | BB18: =+IF(YEAR($H18)<$AV$5,$S18,IF(AND(YEAR($H18)=$AV$5,MONTH($H18)<=BB$6),$S18,0)) -> 77280705 | BC18: =+IF(YEAR($H18)<$AV$5,$S18,IF(AND(YEAR($H18)=$AV$5,MONTH($H18)<=BC$6),$S18,0)) -> 77280705 | ... BG18: =+IF(YEAR($H18)<$AV$5,$S18,IF(AND(YEAR($H18)=$AV$5,MONTH($H18)<=BG$6),$S18,0)) -> 77280705 | BH18: =+SUM(AV18:BG18) -> 9.2736846e+08 | BI18: 0 | BJ18: =+IF(YEAR($H18)<$BJ$5,$S18,IF(AND(YEAR($H18)=$BJ$5,MONTH($H18)<=BJ$6),$S18,0)) -> 77280705 | BK18: =+IF(YEAR($H18)<$BJ$5,$S18,IF(AND(YEAR($H18)=$BJ$5,MONTH($H18)<=BK$6),$S18,0)) -> 77280705 | BL18: =+IF(YEAR($H18)<$BJ$5,$S18,IF(AND(YEAR($H18)=$BJ$5,MONTH($H18)<=BL$6),$S18,0)) -> 77280705 | BM18: =+IF(YEAR($H18)<$BJ$5,$S18,IF(AND(YEAR($H18)=$BJ$5,MONTH($H18)<=BM$6),$S18,0)) -> 77280705 | BN18: =+IF(YEAR($H18)<$BJ$5,$S18,IF(AND(YEAR($H18)=$BJ$5,MONTH($H18)<=BN$6),$S18,0)) -> 77280705 | BO18: =+IF(YEAR($H18)<$BJ$5,$S18,IF(AND(YEAR($H18)=$BJ$5,MONTH($H18)<=BO$6),$S18,0)) -> 77280705 | BP18: =+IF(YEAR($H18)<$BJ$5,$S18,IF(AND(YEAR($H18)=$BJ$5,MONTH($H18)<=BP$6),$S18,0)) -> 77280705 | BQ18: =+IF(YEAR($H18)<$BJ$5,$S18,IF(AND(YEAR($H18)=$BJ$5,MONTH($H18)<=BQ$6),$S18,0)) -> 77280705 | ... BU18: =+IF(YEAR($H18)<$BJ$5,$S18,IF(AND(YEAR($H18)=$BJ$5,MONTH($H18)<=BU$6),$S18,0)) -> 77280705 | BV18: =+SUM(BJ18:BU18) -> 9.2736846e+08 | BW18: =+R18-BV18 -> 2.2256843e+10 | BX18: =+$S18 -> 77280705 | BY18: =+$S18 -> 77280705 | BZ18: =+$S18 -> 77280705 | CA18: =+$S18 -> 77280705 | CB18: =+$S18 -> 77280705 | CC18: =+$S18 -> 77280705 | CD18: =+$S18 -> 77280705 | CE18: =+$S18 -> 77280705 | ... CI18: =+$S18 -> 77280705 | CJ18: =+SUM(BX18:CI18) -> 9.2736846e+08 | CK18: =+BW18-CJ18 -> 2.1329475e+10 | CM18: =VLOOKUP($E18,'Capex TT 2020'!$D$5:$F$35,3,0) -> #N/A | CN18: =IFERROR(VLOOKUP($E18,'Capex TT 2021'!$D$5:$F$35,3,0),0) -> 0 | CO18: =VLOOKUP($E18,'Capex TT 2022'!$D$5:$F$35,3,0) -> #N/A | CP18: =VLOOKUP($E18,'Capex TT 2023'!$D$5:$F$35,3,0) -> #N/A
A19: 6274.4 | B19: Chung | C19: =YEAR(H19) -> 2023 | D19: Z21110P | E19: 101000013 | F19: Nhà xưởng số F05 | G19: 44914 | H19: 44927 | I19: 300 | J19: 1001606000 | K19: Xưởng sản xuất HDPE | M19: =+LEFT(N19,4) -> 6274 | N19: 6274001901 | R19: 14213865604 | S19: 47379552 | T19: =$S19 -> 47379552 | U19: =$S19 -> 47379552 | V19: =$S19 -> 47379552 | W19: =$S19 -> 47379552 | X19: =$S19 -> 47379552 | Y19: =$S19 -> 47379552 | Z19: =$S19 -> 47379552 | AA19: =$S19 -> 47379552 | ... AE19: =$S19 -> 47379552 | AF19: =+SUM(T19:AE19) -> 5.6855462e+08 | AG19: 0 | AH19: =$S19 -> 47379552 | AI19: =$S19 -> 47379552 | AJ19: =$S19 -> 47379552 | AK19: =$S19 -> 47379552 | AL19: =$S19 -> 47379552 | AM19: =$S19 -> 47379552 | AN19: =$S19 -> 47379552 | AO19: =$S19 -> 47379552 | ... AS19: =$S19 -> 47379552 | AT19: =+SUM(AH19:AS19) -> 5.6855462e+08 | AU19: 0 | AV19: =+IF(YEAR($H19)<$AV$5,$S19,IF(AND(YEAR($H19)=$AV$5,MONTH($H19)<=AV$6),$S19,0)) -> 47379552 | AW19: =+IF(YEAR($H19)<$AV$5,$S19,IF(AND(YEAR($H19)=$AV$5,MONTH($H19)<=AW$6),$S19,0)) -> 47379552 | AX19: =+IF(YEAR($H19)<$AV$5,$S19,IF(AND(YEAR($H19)=$AV$5,MONTH($H19)<=AX$6),$S19,0)) -> 47379552 | AY19: =+IF(YEAR($H19)<$AV$5,$S19,IF(AND(YEAR($H19)=$AV$5,MONTH($H19)<=AY$6),$S19,0)) -> 47379552 | AZ19: =+IF(YEAR($H19)<$AV$5,$S19,IF(AND(YEAR($H19)=$AV$5,MONTH($H19)<=AZ$6),$S19,0)) -> 47379552 | BA19: =+IF(YEAR($H19)<$AV$5,$S19,IF(AND(YEAR($H19)=$AV$5,MONTH($H19)<=BA$6),$S19,0)) -> 47379552 | BB19: =+IF(YEAR($H19)<$AV$5,$S19,IF(AND(YEAR($H19)=$AV$5,MONTH($H19)<=BB$6),$S19,0)) -> 47379552 | BC19: =+IF(YEAR($H19)<$AV$5,$S19,IF(AND(YEAR($H19)=$AV$5,MONTH($H19)<=BC$6),$S19,0)) -> 47379552 | ... BG19: =+IF(YEAR($H19)<$AV$5,$S19,IF(AND(YEAR($H19)=$AV$5,MONTH($H19)<=BG$6),$S19,0)) -> 47379552 | BH19: =+SUM(AV19:BG19) -> 5.6855462e+08 | BI19: 0 | BJ19: =+IF(YEAR($H19)<$BJ$5,$S19,IF(AND(YEAR($H19)=$BJ$5,MONTH($H19)<=BJ$6),$S19,0)) -> 47379552 | BK19: =+IF(YEAR($H19)<$BJ$5,$S19,IF(AND(YEAR($H19)=$BJ$5,MONTH($H19)<=BK$6),$S19,0)) -> 47379552 | BL19: =+IF(YEAR($H19)<$BJ$5,$S19,IF(AND(YEAR($H19)=$BJ$5,MONTH($H19)<=BL$6),$S19,0)) -> 47379552 | BM19: =+IF(YEAR($H19)<$BJ$5,$S19,IF(AND(YEAR($H19)=$BJ$5,MONTH($H19)<=BM$6),$S19,0)) -> 47379552 | BN19: =+IF(YEAR($H19)<$BJ$5,$S19,IF(AND(YEAR($H19)=$BJ$5,MONTH($H19)<=BN$6),$S19,0)) -> 47379552 | BO19: =+IF(YEAR($H19)<$BJ$5,$S19,IF(AND(YEAR($H19)=$BJ$5,MONTH($H19)<=BO$6),$S19,0)) -> 47379552 | BP19: =+IF(YEAR($H19)<$BJ$5,$S19,IF(AND(YEAR($H19)=$BJ$5,MONTH($H19)<=BP$6),$S19,0)) -> 47379552 | BQ19: =+IF(YEAR($H19)<$BJ$5,$S19,IF(AND(YEAR($H19)=$BJ$5,MONTH($H19)<=BQ$6),$S19,0)) -> 47379552 | ... BU19: =+IF(YEAR($H19)<$BJ$5,$S19,IF(AND(YEAR($H19)=$BJ$5,MONTH($H19)<=BU$6),$S19,0)) -> 47379552 | BV19: =+SUM(BJ19:BU19) -> 5.6855462e+08 | BW19: =+R19-BV19 -> 1.3645311e+10 | BX19: =+$S19 -> 47379552 | BY19: =+$S19 -> 47379552 | BZ19: =+$S19 -> 47379552 | CA19: =+$S19 -> 47379552 | CB19: =+$S19 -> 47379552 | CC19: =+$S19 -> 47379552 | CD19: =+$S19 -> 47379552 | CE19: =+$S19 -> 47379552 | ... CI19: =+$S19 -> 47379552 | CJ19: =+SUM(BX19:CI19) -> 5.6855462e+08 | CK19: =+BW19-CJ19 -> 1.3076756e+10 | CM19: =VLOOKUP($E19,'Capex TT 2020'!$D$5:$F$35,3,0) -> #N/A | CN19: =IFERROR(VLOOKUP($E19,'Capex TT 2021'!$D$5:$F$35,3,0),0) -> 0 | CO19: =VLOOKUP($E19,'Capex TT 2022'!$D$5:$F$35,3,0) -> #N/A | CP19: =VLOOKUP($E19,'Capex TT 2023'!$D$5:$F$35,3,0) -> #N/A
A20: 6274.4 | B20: Chung | C20: =YEAR(H20) -> 2023 | D20: Z21110P | E20: 101000014 | F20: Sân chứa nguyên liệu, trạm cân | G20: 44915 | H20: 44927 | I20: 96 | J20: 1001602000 | K20: Xưởng sản xuất PET | M20: =+LEFT(N20,4) -> 6274 | N20: 6274001901 | R20: 7312917741 | S20: 76176226 | T20: =$S20 -> 76176226 | U20: =$S20 -> 76176226 | V20: =$S20 -> 76176226 | W20: =$S20 -> 76176226 | X20: =$S20 -> 76176226 | Y20: =$S20 -> 76176226 | Z20: =$S20 -> 76176226 | AA20: =$S20 -> 76176226 | ... AE20: =$S20 -> 76176226 | AF20: =+SUM(T20:AE20) -> 9.1411472e+08 | AG20: 0 | AH20: =$S20 -> 76176226 | AI20: =$S20 -> 76176226 | AJ20: =$S20 -> 76176226 | AK20: =$S20 -> 76176226 | AL20: =$S20 -> 76176226 | AM20: =$S20 -> 76176226 | AN20: =$S20 -> 76176226 | AO20: =$S20 -> 76176226 | ... AS20: =$S20 -> 76176226 | AT20: =+SUM(AH20:AS20) -> 9.1411472e+08 | AU20: 0 | AV20: =+IF(YEAR($H20)<$AV$5,$S20,IF(AND(YEAR($H20)=$AV$5,MONTH($H20)<=AV$6),$S20,0)) -> 76176226 | AW20: =+IF(YEAR($H20)<$AV$5,$S20,IF(AND(YEAR($H20)=$AV$5,MONTH($H20)<=AW$6),$S20,0)) -> 76176226 | AX20: =+IF(YEAR($H20)<$AV$5,$S20,IF(AND(YEAR($H20)=$AV$5,MONTH($H20)<=AX$6),$S20,0)) -> 76176226 | AY20: =+IF(YEAR($H20)<$AV$5,$S20,IF(AND(YEAR($H20)=$AV$5,MONTH($H20)<=AY$6),$S20,0)) -> 76176226 | AZ20: =+IF(YEAR($H20)<$AV$5,$S20,IF(AND(YEAR($H20)=$AV$5,MONTH($H20)<=AZ$6),$S20,0)) -> 76176226 | BA20: =+IF(YEAR($H20)<$AV$5,$S20,IF(AND(YEAR($H20)=$AV$5,MONTH($H20)<=BA$6),$S20,0)) -> 76176226 | BB20: =+IF(YEAR($H20)<$AV$5,$S20,IF(AND(YEAR($H20)=$AV$5,MONTH($H20)<=BB$6),$S20,0)) -> 76176226 | BC20: =+IF(YEAR($H20)<$AV$5,$S20,IF(AND(YEAR($H20)=$AV$5,MONTH($H20)<=BC$6),$S20,0)) -> 76176226 | ... BG20: =+IF(YEAR($H20)<$AV$5,$S20,IF(AND(YEAR($H20)=$AV$5,MONTH($H20)<=BG$6),$S20,0)) -> 76176226 | BH20: =+SUM(AV20:BG20) -> 9.1411472e+08 | BI20: 0 | BJ20: =+IF(YEAR($H20)<$BJ$5,$S20,IF(AND(YEAR($H20)=$BJ$5,MONTH($H20)<=BJ$6),$S20,0)) -> 76176226 | BK20: =+IF(YEAR($H20)<$BJ$5,$S20,IF(AND(YEAR($H20)=$BJ$5,MONTH($H20)<=BK$6),$S20,0)) -> 76176226 | BL20: =+IF(YEAR($H20)<$BJ$5,$S20,IF(AND(YEAR($H20)=$BJ$5,MONTH($H20)<=BL$6),$S20,0)) -> 76176226 | BM20: =+IF(YEAR($H20)<$BJ$5,$S20,IF(AND(YEAR($H20)=$BJ$5,MONTH($H20)<=BM$6),$S20,0)) -> 76176226 | BN20: =+IF(YEAR($H20)<$BJ$5,$S20,IF(AND(YEAR($H20)=$BJ$5,MONTH($H20)<=BN$6),$S20,0)) -> 76176226 | BO20: =+IF(YEAR($H20)<$BJ$5,$S20,IF(AND(YEAR($H20)=$BJ$5,MONTH($H20)<=BO$6),$S20,0)) -> 76176226 | BP20: =+IF(YEAR($H20)<$BJ$5,$S20,IF(AND(YEAR($H20)=$BJ$5,MONTH($H20)<=BP$6),$S20,0)) -> 76176226 | BQ20: =+IF(YEAR($H20)<$BJ$5,$S20,IF(AND(YEAR($H20)=$BJ$5,MONTH($H20)<=BQ$6),$S20,0)) -> 76176226 | ... BU20: =+IF(YEAR($H20)<$BJ$5,$S20,IF(AND(YEAR($H20)=$BJ$5,MONTH($H20)<=BU$6),$S20,0)) -> 76176226 | BV20: =+SUM(BJ20:BU20) -> 9.1411472e+08 | BW20: =+R20-BV20 -> 6.398803e+09 | BX20: =+$S20 -> 76176226 | BY20: =+$S20 -> 76176226 | BZ20: =+$S20 -> 76176226 | CA20: =+$S20 -> 76176226 | CB20: =+$S20 -> 76176226 | CC20: =+$S20 -> 76176226 | CD20: =+$S20 -> 76176226 | CE20: =+$S20 -> 76176226 | ... CI20: =+$S20 -> 76176226 | CJ20: =+SUM(BX20:CI20) -> 9.1411472e+08 | CK20: =+BW20-CJ20 -> 5.4846883e+09 | CM20: =VLOOKUP($E20,'Capex TT 2020'!$D$5:$F$35,3,0) -> #N/A | CN20: =IFERROR(VLOOKUP($E20,'Capex TT 2021'!$D$5:$F$35,3,0),0) -> 0 | CO20: =VLOOKUP($E20,'Capex TT 2022'!$D$5:$F$35,3,0) -> #N/A | CP20: =VLOOKUP($E20,'Capex TT 2023'!$D$5:$F$35,3,0) -> #N/A
A21: 6274.4 | B21: Chung | C21: =YEAR(H21) -> 2023 | D21: Z21110P | E21: 101000015 | F21: Đường bê tông nhựa | G21: 44915 | H21: 44927 | I21: 72 | J21: 1001602000 | K21: Xưởng sản xuất PET | M21: =+LEFT(N21,4) -> 6274 | N21: 6274001901 | R21: 1365430657 | S21: 18964315 | T21: =$S21 -> 18964315 | U21: =$S21 -> 18964315 | V21: =$S21 -> 18964315 | W21: =$S21 -> 18964315 | X21: =$S21 -> 18964315 | Y21: =$S21 -> 18964315 | Z21: =$S21 -> 18964315 | AA21: =$S21 -> 18964315 | ... AE21: =$S21 -> 18964315 | AF21: =+SUM(T21:AE21) -> 2.2757178e+08 | AG21: 0 | AH21: =$S21 -> 18964315 | AI21: =$S21 -> 18964315 | AJ21: =$S21 -> 18964315 | AK21: =$S21 -> 18964315 | AL21: =$S21 -> 18964315 | AM21: =$S21 -> 18964315 | AN21: =$S21 -> 18964315 | AO21: =$S21 -> 18964315 | ... AS21: =$S21 -> 18964315 | AT21: =+SUM(AH21:AS21) -> 2.2757178e+08 | AU21: 0 | AV21: =+IF(YEAR($H21)<$AV$5,$S21,IF(AND(YEAR($H21)=$AV$5,MONTH($H21)<=AV$6),$S21,0)) -> 18964315 | AW21: =+IF(YEAR($H21)<$AV$5,$S21,IF(AND(YEAR($H21)=$AV$5,MONTH($H21)<=AW$6),$S21,0)) -> 18964315 | AX21: =+IF(YEAR($H21)<$AV$5,$S21,IF(AND(YEAR($H21)=$AV$5,MONTH($H21)<=AX$6),$S21,0)) -> 18964315 | AY21: =+IF(YEAR($H21)<$AV$5,$S21,IF(AND(YEAR($H21)=$AV$5,MONTH($H21)<=AY$6),$S21,0)) -> 18964315 | AZ21: =+IF(YEAR($H21)<$AV$5,$S21,IF(AND(YEAR($H21)=$AV$5,MONTH($H21)<=AZ$6),$S21,0)) -> 18964315 | BA21: =+IF(YEAR($H21)<$AV$5,$S21,IF(AND(YEAR($H21)=$AV$5,MONTH($H21)<=BA$6),$S21,0)) -> 18964315 | BB21: =+IF(YEAR($H21)<$AV$5,$S21,IF(AND(YEAR($H21)=$AV$5,MONTH($H21)<=BB$6),$S21,0)) -> 18964315 | BC21: =+IF(YEAR($H21)<$AV$5,$S21,IF(AND(YEAR($H21)=$AV$5,MONTH($H21)<=BC$6),$S21,0)) -> 18964315 | ... BG21: =+IF(YEAR($H21)<$AV$5,$S21,IF(AND(YEAR($H21)=$AV$5,MONTH($H21)<=BG$6),$S21,0)) -> 18964315 | BH21: =+SUM(AV21:BG21) -> 2.2757178e+08 | BI21: 0 | BJ21: =+IF(YEAR($H21)<$BJ$5,$S21,IF(AND(YEAR($H21)=$BJ$5,MONTH($H21)<=BJ$6),$S21,0)) -> 18964315 | BK21: =+IF(YEAR($H21)<$BJ$5,$S21,IF(AND(YEAR($H21)=$BJ$5,MONTH($H21)<=BK$6),$S21,0)) -> 18964315 | BL21: =+IF(YEAR($H21)<$BJ$5,$S21,IF(AND(YEAR($H21)=$BJ$5,MONTH($H21)<=BL$6),$S21,0)) -> 18964315 | BM21: =+IF(YEAR($H21)<$BJ$5,$S21,IF(AND(YEAR($H21)=$BJ$5,MONTH($H21)<=BM$6),$S21,0)) -> 18964315 | BN21: =+IF(YEAR($H21)<$BJ$5,$S21,IF(AND(YEAR($H21)=$BJ$5,MONTH($H21)<=BN$6),$S21,0)) -> 18964315 | BO21: =+IF(YEAR($H21)<$BJ$5,$S21,IF(AND(YEAR($H21)=$BJ$5,MONTH($H21)<=BO$6),$S21,0)) -> 18964315 | BP21: =+IF(YEAR($H21)<$BJ$5,$S21,IF(AND(YEAR($H21)=$BJ$5,MONTH($H21)<=BP$6),$S21,0)) -> 18964315 | BQ21: =+IF(YEAR($H21)<$BJ$5,$S21,IF(AND(YEAR($H21)=$BJ$5,MONTH($H21)<=BQ$6),$S21,0)) -> 18964315 | ... BU21: =+IF(YEAR($H21)<$BJ$5,$S21,IF(AND(YEAR($H21)=$BJ$5,MONTH($H21)<=BU$6),$S21,0)) -> 18964315 | BV21: =+SUM(BJ21:BU21) -> 2.2757178e+08 | BW21: =+R21-BV21 -> 1.1378589e+09 | BX21: =+$S21 -> 18964315 | BY21: =+$S21 -> 18964315 | BZ21: =+$S21 -> 18964315 | CA21: =+$S21 -> 18964315 | CB21: =+$S21 -> 18964315 | CC21: =+$S21 -> 18964315 | CD21: =+$S21 -> 18964315 | CE21: =+$S21 -> 18964315 | ... CI21: =+$S21 -> 18964315 | CJ21: =+SUM(BX21:CI21) -> 2.2757178e+08 | CK21: =+BW21-CJ21 -> 9.102871e+08 | CM21: =VLOOKUP($E21,'Capex TT 2020'!$D$5:$F$35,3,0) -> #N/A | CN21: =IFERROR(VLOOKUP($E21,'Capex TT 2021'!$D$5:$F$35,3,0),0) -> 0 | CO21: =VLOOKUP($E21,'Capex TT 2022'!$D$5:$F$35,3,0) -> #N/A | CP21: =VLOOKUP($E21,'Capex TT 2023'!$D$5:$F$35,3,0) -> #N/A
A22: 6274.4 | B22: Chung | C22: =YEAR(H22) -> 2023 | D22: Z21110P | E22: 101000016 | F22: Hệ thống chiếu sáng F01-F05 | G22: 44915 | H22: 44927 | I22: 60 | J22: 1001602000 | K22: Xưởng sản xuất PET | M22: =+LEFT(N22,4) -> 6274 | N22: 6274001901 | R22: 925192275 | S22: 15419871 | T22: =$S22 -> 15419871 | U22: =$S22 -> 15419871 | V22: =$S22 -> 15419871 | W22: =$S22 -> 15419871 | X22: =$S22 -> 15419871 | Y22: =$S22 -> 15419871 | Z22: =$S22 -> 15419871 | AA22: =$S22 -> 15419871 | ... AE22: =$S22 -> 15419871 | AF22: =+SUM(T22:AE22) -> 185038455 | AG22: 0 | AH22: =$S22 -> 15419871 | AI22: =$S22 -> 15419871 | AJ22: =$S22 -> 15419871 | AK22: =$S22 -> 15419871 | AL22: =$S22 -> 15419871 | AM22: =$S22 -> 15419871 | AN22: =$S22 -> 15419871 | AO22: =$S22 -> 15419871 | ... AS22: =$S22 -> 15419871 | AT22: =+SUM(AH22:AS22) -> 185038455 | AU22: 0 | AV22: =+IF(YEAR($H22)<$AV$5,$S22,IF(AND(YEAR($H22)=$AV$5,MONTH($H22)<=AV$6),$S22,0)) -> 15419871 | AW22: =+IF(YEAR($H22)<$AV$5,$S22,IF(AND(YEAR($H22)=$AV$5,MONTH($H22)<=AW$6),$S22,0)) -> 15419871 | AX22: =+IF(YEAR($H22)<$AV$5,$S22,IF(AND(YEAR($H22)=$AV$5,MONTH($H22)<=AX$6),$S22,0)) -> 15419871 | AY22: =+IF(YEAR($H22)<$AV$5,$S22,IF(AND(YEAR($H22)=$AV$5,MONTH($H22)<=AY$6),$S22,0)) -> 15419871 | AZ22: =+IF(YEAR($H22)<$AV$5,$S22,IF(AND(YEAR($H22)=$AV$5,MONTH($H22)<=AZ$6),$S22,0)) -> 15419871 | BA22: =+IF(YEAR($H22)<$AV$5,$S22,IF(AND(YEAR($H22)=$AV$5,MONTH($H22)<=BA$6),$S22,0)) -> 15419871 | BB22: =+IF(YEAR($H22)<$AV$5,$S22,IF(AND(YEAR($H22)=$AV$5,MONTH($H22)<=BB$6),$S22,0)) -> 15419871 | BC22: =+IF(YEAR($H22)<$AV$5,$S22,IF(AND(YEAR($H22)=$AV$5,MONTH($H22)<=BC$6),$S22,0)) -> 15419871 | ... BG22: =+IF(YEAR($H22)<$AV$5,$S22,IF(AND(YEAR($H22)=$AV$5,MONTH($H22)<=BG$6),$S22,0)) -> 15419871 | BH22: =+SUM(AV22:BG22) -> 185038455 | BI22: 0 | BJ22: =+IF(YEAR($H22)<$BJ$5,$S22,IF(AND(YEAR($H22)=$BJ$5,MONTH($H22)<=BJ$6),$S22,0)) -> 15419871 | BK22: =+IF(YEAR($H22)<$BJ$5,$S22,IF(AND(YEAR($H22)=$BJ$5,MONTH($H22)<=BK$6),$S22,0)) -> 15419871 | BL22: =+IF(YEAR($H22)<$BJ$5,$S22,IF(AND(YEAR($H22)=$BJ$5,MONTH($H22)<=BL$6),$S22,0)) -> 15419871 | BM22: =+IF(YEAR($H22)<$BJ$5,$S22,IF(AND(YEAR($H22)=$BJ$5,MONTH($H22)<=BM$6),$S22,0)) -> 15419871 | BN22: =+IF(YEAR($H22)<$BJ$5,$S22,IF(AND(YEAR($H22)=$BJ$5,MONTH($H22)<=BN$6),$S22,0)) -> 15419871 | BO22: =+IF(YEAR($H22)<$BJ$5,$S22,IF(AND(YEAR($H22)=$BJ$5,MONTH($H22)<=BO$6),$S22,0)) -> 15419871 | BP22: =+IF(YEAR($H22)<$BJ$5,$S22,IF(AND(YEAR($H22)=$BJ$5,MONTH($H22)<=BP$6),$S22,0)) -> 15419871 | BQ22: =+IF(YEAR($H22)<$BJ$5,$S22,IF(AND(YEAR($H22)=$BJ$5,MONTH($H22)<=BQ$6),$S22,0)) -> 15419871 | ... BU22: =+IF(YEAR($H22)<$BJ$5,$S22,IF(AND(YEAR($H22)=$BJ$5,MONTH($H22)<=BU$6),$S22,0)) -> 15419871 | BV22: =+SUM(BJ22:BU22) -> 185038455 | BW22: =+R22-BV22 -> 740153820 | BX22: =+$S22 -> 15419871 | BY22: =+$S22 -> 15419871 | BZ22: =+$S22 -> 15419871 | CA22: =+$S22 -> 15419871 | CB22: =+$S22 -> 15419871 | CC22: =+$S22 -> 15419871 | CD22: =+$S22 -> 15419871 | CE22: =+$S22 -> 15419871 | ... CI22: =+$S22 -> 15419871 | CJ22: =+SUM(BX22:CI22) -> 185038455 | CK22: =+BW22-CJ22 -> 555115365 | CM22: =VLOOKUP($E22,'Capex TT 2020'!$D$5:$F$35,3,0) -> #N/A | CN22: =IFERROR(VLOOKUP($E22,'Capex TT 2021'!$D$5:$F$35,3,0),0) -> 0 | CO22: =VLOOKUP($E22,'Capex TT 2022'!$D$5:$F$35,3,0) -> #N/A | CP22: =VLOOKUP($E22,'Capex TT 2023'!$D$5:$F$35,3,0) -> #N/A
A23: 6274.4 | B23: Chung | C23: =YEAR(H23) -> 2021 | D23: Z21110A | E23: 103000000 | F23: Nhà để xe CNV | G23: 44439 | H23: 44438 | I23: 60 | J23: 1001202000 | K23: Hành chánh nhân sự | M23: =+LEFT(N23,4) -> 6424 | N23: 6424001901 | R23: 36001880 | S23: 600031.33 | T23: =$S23 -> 600031.33 | U23: =$S23 -> 600031.33 | V23: =$S23 -> 600031.33 | W23: =$S23 -> 600031.33 | X23: =$S23 -> 600031.33 | Y23: =$S23 -> 600031.33 | Z23: =$S23 -> 600031.33 | AA23: =$S23 -> 600031.33 | ... AE23: =$S23 -> 600031.33 | AF23: =+SUM(T23:AE23) -> 7200376 | AG23: 0 | AH23: =$S23 -> 600031.33 | AI23: =$S23 -> 600031.33 | AJ23: =$S23 -> 600031.33 | AK23: =$S23 -> 600031.33 | AL23: =$S23 -> 600031.33 | AM23: =$S23 -> 600031.33 | AN23: =$S23 -> 600031.33 | AO23: =$S23 -> 600031.33 | ... AS23: =$S23 -> 600031.33 | AT23: =+SUM(AH23:AS23) -> 7200376 | AU23: =+R23-AT23 -> 28801504 | AV23: =+IF(YEAR($H23)<$AV$5,$S23,IF(AND(YEAR($H23)=$AV$5,MONTH($H23)<=AV$6),$S23,0)) -> 600031.33 | AW23: =+IF(YEAR($H23)<$AV$5,$S23,IF(AND(YEAR($H23)=$AV$5,MONTH($H23)<=AW$6),$S23,0)) -> 600031.33 | AX23: =+IF(YEAR($H23)<$AV$5,$S23,IF(AND(YEAR($H23)=$AV$5,MONTH($H23)<=AX$6),$S23,0)) -> 600031.33 | AY23: =+IF(YEAR($H23)<$AV$5,$S23,IF(AND(YEAR($H23)=$AV$5,MONTH($H23)<=AY$6),$S23,0)) -> 600031.33 | AZ23: =+IF(YEAR($H23)<$AV$5,$S23,IF(AND(YEAR($H23)=$AV$5,MONTH($H23)<=AZ$6),$S23,0)) -> 600031.33 | BA23: =+IF(YEAR($H23)<$AV$5,$S23,IF(AND(YEAR($H23)=$AV$5,MONTH($H23)<=BA$6),$S23,0)) -> 600031.33 | BB23: =+IF(YEAR($H23)<$AV$5,$S23,IF(AND(YEAR($H23)=$AV$5,MONTH($H23)<=BB$6),$S23,0)) -> 600031.33 | BC23: =+IF(YEAR($H23)<$AV$5,$S23,IF(AND(YEAR($H23)=$AV$5,MONTH($H23)<=BC$6),$S23,0)) -> 600031.33 | ... BG23: =+IF(YEAR($H23)<$AV$5,$S23,IF(AND(YEAR($H23)=$AV$5,MONTH($H23)<=BG$6),$S23,0)) -> 600031.33 | BH23: =+SUM(AV23:BG23) -> 7200376 | BI23: =+AU23-BH23 -> 21601128 | BJ23: =+IF(YEAR($H23)<$BJ$5,$S23,IF(AND(YEAR($H23)=$BJ$5,MONTH($H23)<=BJ$6),$S23,0)) -> 600031.33 | BK23: =+IF(YEAR($H23)<$BJ$5,$S23,IF(AND(YEAR($H23)=$BJ$5,MONTH($H23)<=BK$6),$S23,0)) -> 600031.33 | BL23: =+IF(YEAR($H23)<$BJ$5,$S23,IF(AND(YEAR($H23)=$BJ$5,MONTH($H23)<=BL$6),$S23,0)) -> 600031.33 | BM23: =+IF(YEAR($H23)<$BJ$5,$S23,IF(AND(YEAR($H23)=$BJ$5,MONTH($H23)<=BM$6),$S23,0)) -> 600031.33 | BN23: =+IF(YEAR($H23)<$BJ$5,$S23,IF(AND(YEAR($H23)=$BJ$5,MONTH($H23)<=BN$6),$S23,0)) -> 600031.33 | BO23: =+IF(YEAR($H23)<$BJ$5,$S23,IF(AND(YEAR($H23)=$BJ$5,MONTH($H23)<=BO$6),$S23,0)) -> 600031.33 | BP23: =+IF(YEAR($H23)<$BJ$5,$S23,IF(AND(YEAR($H23)=$BJ$5,MONTH($H23)<=BP$6),$S23,0)) -> 600031.33 | BQ23: =+IF(YEAR($H23)<$BJ$5,$S23,IF(AND(YEAR($H23)=$BJ$5,MONTH($H23)<=BQ$6),$S23,0)) -> 600031.33 | ... BU23: =+IF(YEAR($H23)<$BJ$5,$S23,IF(AND(YEAR($H23)=$BJ$5,MONTH($H23)<=BU$6),$S23,0)) -> 600031.33 | BV23: =+SUM(BJ23:BU23) -> 7200376 | BW23: =+BI23-BV23 -> 14400752 | BX23: =+$S23 -> 600031.33 | BY23: =+$S23 -> 600031.33 | BZ23: =+$S23 -> 600031.33 | CA23: =+$S23 -> 600031.33 | CB23: =+$S23 -> 600031.33 | CC23: =+$S23 -> 600031.33 | CD23: =+$S23 -> 600031.33 | CE23: =+$S23 -> 600031.33 | ... CI23: =+$S23 -> 600031.33 | CJ23: =+SUM(BX23:CI23) -> 7200376 | CK23: =+BW23-CJ23 -> 7200376 | CM23: =VLOOKUP($E23,'Capex TT 2020'!$D$5:$F$35,3,0) -> #N/A | CN23: =IFERROR(VLOOKUP($E23,'Capex TT 2021'!$D$5:$F$35,3,0),0) -> 36001880 | CO23: =VLOOKUP($E23,'Capex TT 2022'!$D$5:$F$35,3,0) -> #N/A | CP23: =VLOOKUP($E23,'Capex TT 2023'!$D$5:$F$35,3,0) -> #N/A
A24: 6274.4 | B24: Chung | C24: =YEAR(H24) -> 2021 | D24: Z21110A | E24: 103000001 | F24: Thiết kế nội thất văn phòng xưởng 03 | G24: 44439 | H24: 44438 | I24: 120 | J24: 1001202000 | K24: Hành chánh nhân sự | M24: =+LEFT(N24,4) -> 6424 | N24: 6424001901 | R24: 2813240158 | S24: 23443668 | T24: =$S24 -> 23443668 | U24: =$S24 -> 23443668 | V24: =$S24 -> 23443668 | W24: =$S24 -> 23443668 | X24: =$S24 -> 23443668 | Y24: =$S24 -> 23443668 | Z24: =$S24 -> 23443668 | AA24: =$S24 -> 23443668 | ... AE24: =$S24 -> 23443668 | AF24: =+SUM(T24:AE24) -> 2.8132402e+08 | AG24: 0 | AH24: =$S24 -> 23443668 | AI24: =$S24 -> 23443668 | AJ24: =$S24 -> 23443668 | AK24: =$S24 -> 23443668 | AL24: =$S24 -> 23443668 | AM24: =$S24 -> 23443668 | AN24: =$S24 -> 23443668 | AO24: =$S24 -> 23443668 | ... AS24: =$S24 -> 23443668 | AT24: =+SUM(AH24:AS24) -> 2.8132402e+08 | AU24: =+R24-AT24 -> 2.5319161e+09 | AV24: =+IF(YEAR($H24)<$AV$5,$S24,IF(AND(YEAR($H24)=$AV$5,MONTH($H24)<=AV$6),$S24,0)) -> 23443668 | AW24: =+IF(YEAR($H24)<$AV$5,$S24,IF(AND(YEAR($H24)=$AV$5,MONTH($H24)<=AW$6),$S24,0)) -> 23443668 | AX24: =+IF(YEAR($H24)<$AV$5,$S24,IF(AND(YEAR($H24)=$AV$5,MONTH($H24)<=AX$6),$S24,0)) -> 23443668 | AY24: =+IF(YEAR($H24)<$AV$5,$S24,IF(AND(YEAR($H24)=$AV$5,MONTH($H24)<=AY$6),$S24,0)) -> 23443668 | AZ24: =+IF(YEAR($H24)<$AV$5,$S24,IF(AND(YEAR($H24)=$AV$5,MONTH($H24)<=AZ$6),$S24,0)) -> 23443668 | BA24: =+IF(YEAR($H24)<$AV$5,$S24,IF(AND(YEAR($H24)=$AV$5,MONTH($H24)<=BA$6),$S24,0)) -> 23443668 | BB24: =+IF(YEAR($H24)<$AV$5,$S24,IF(AND(YEAR($H24)=$AV$5,MONTH($H24)<=BB$6),$S24,0)) -> 23443668 | BC24: =+IF(YEAR($H24)<$AV$5,$S24,IF(AND(YEAR($H24)=$AV$5,MONTH($H24)<=BC$6),$S24,0)) -> 23443668 | ... BG24: =+IF(YEAR($H24)<$AV$5,$S24,IF(AND(YEAR($H24)=$AV$5,MONTH($H24)<=BG$6),$S24,0)) -> 23443668 | BH24: =+SUM(AV24:BG24) -> 2.8132402e+08 | BI24: =+AU24-BH24 -> 2.2505921e+09 | BJ24: =+IF(YEAR($H24)<$BJ$5,$S24,IF(AND(YEAR($H24)=$BJ$5,MONTH($H24)<=BJ$6),$S24,0)) -> 23443668 | BK24: =+IF(YEAR($H24)<$BJ$5,$S24,IF(AND(YEAR($H24)=$BJ$5,MONTH($H24)<=BK$6),$S24,0)) -> 23443668 | BL24: =+IF(YEAR($H24)<$BJ$5,$S24,IF(AND(YEAR($H24)=$BJ$5,MONTH($H24)<=BL$6),$S24,0)) -> 23443668 | BM24: =+IF(YEAR($H24)<$BJ$5,$S24,IF(AND(YEAR($H24)=$BJ$5,MONTH($H24)<=BM$6),$S24,0)) -> 23443668 | BN24: =+IF(YEAR($H24)<$BJ$5,$S24,IF(AND(YEAR($H24)=$BJ$5,MONTH($H24)<=BN$6),$S24,0)) -> 23443668 | BO24: =+IF(YEAR($H24)<$BJ$5,$S24,IF(AND(YEAR($H24)=$BJ$5,MONTH($H24)<=BO$6),$S24,0)) -> 23443668 | BP24: =+IF(YEAR($H24)<$BJ$5,$S24,IF(AND(YEAR($H24)=$BJ$5,MONTH($H24)<=BP$6),$S24,0)) -> 23443668 | BQ24: =+IF(YEAR($H24)<$BJ$5,$S24,IF(AND(YEAR($H24)=$BJ$5,MONTH($H24)<=BQ$6),$S24,0)) -> 23443668 | ... BU24: =+IF(YEAR($H24)<$BJ$5,$S24,IF(AND(YEAR($H24)=$BJ$5,MONTH($H24)<=BU$6),$S24,0)) -> 23443668 | BV24: =+SUM(BJ24:BU24) -> 2.8132402e+08 | BW24: =+BI24-BV24 -> 1.9692681e+09 | BX24: =+$S24 -> 23443668 | BY24: =+$S24 -> 23443668 | BZ24: =+$S24 -> 23443668 | CA24: =+$S24 -> 23443668 | CB24: =+$S24 -> 23443668 | CC24: =+$S24 -> 23443668 | CD24: =+$S24 -> 23443668 | CE24: =+$S24 -> 23443668 | ... CI24: =+$S24 -> 23443668 | CJ24: =+SUM(BX24:CI24) -> 2.8132402e+08 | CK24: =+BW24-CJ24 -> 1.6879441e+09 | CM24: =VLOOKUP($E24,'Capex TT 2020'!$D$5:$F$35,3,0) -> #N/A | CN24: =IFERROR(VLOOKUP($E24,'Capex TT 2021'!$D$5:$F$35,3,0),0) -> 2813240158 | CO24: =VLOOKUP($E24,'Capex TT 2022'!$D$5:$F$35,3,0) -> #N/A | CP24: =VLOOKUP($E24,'Capex TT 2023'!$D$5:$F$35,3,0) -> #N/A
A25: 6274.4 | B25: Chung | C25: =YEAR(H25) -> 2021 | D25: Z21110A | E25: 103000002 | F25: Văn phòng xưởng 03 | G25: 44439 | H25: 44438 | I25: 240 | J25: 1001202000 | K25: Hành chánh nhân sự | M25: =+LEFT(N25,4) -> 6424 | N25: 6424001901 | R25: 13526642799 | S25: 56361012 | T25: =$S25 -> 56361012 | U25: =$S25 -> 56361012 | V25: =$S25 -> 56361012 | W25: =$S25 -> 56361012 | X25: =$S25 -> 56361012 | Y25: =$S25 -> 56361012 | Z25: =$S25 -> 56361012 | AA25: =$S25 -> 56361012 | ... AE25: =$S25 -> 56361012 | AF25: =+SUM(T25:AE25) -> 6.7633214e+08 | AG25: 0 | AH25: =$S25 -> 56361012 | AI25: =$S25 -> 56361012 | AJ25: =$S25 -> 56361012 | AK25: =$S25 -> 56361012 | AL25: =$S25 -> 56361012 | AM25: =$S25 -> 56361012 | AN25: =$S25 -> 56361012 | AO25: =$S25 -> 56361012 | ... AS25: =$S25 -> 56361012 | AT25: =+SUM(AH25:AS25) -> 6.7633214e+08 | AU25: =+R25-AT25 -> 1.2850311e+10 | AV25: =+IF(YEAR($H25)<$AV$5,$S25,IF(AND(YEAR($H25)=$AV$5,MONTH($H25)<=AV$6),$S25,0)) -> 56361012 | AW25: =+IF(YEAR($H25)<$AV$5,$S25,IF(AND(YEAR($H25)=$AV$5,MONTH($H25)<=AW$6),$S25,0)) -> 56361012 | AX25: =+IF(YEAR($H25)<$AV$5,$S25,IF(AND(YEAR($H25)=$AV$5,MONTH($H25)<=AX$6),$S25,0)) -> 56361012 | AY25: =+IF(YEAR($H25)<$AV$5,$S25,IF(AND(YEAR($H25)=$AV$5,MONTH($H25)<=AY$6),$S25,0)) -> 56361012 | AZ25: =+IF(YEAR($H25)<$AV$5,$S25,IF(AND(YEAR($H25)=$AV$5,MONTH($H25)<=AZ$6),$S25,0)) -> 56361012 | BA25: =+IF(YEAR($H25)<$AV$5,$S25,IF(AND(YEAR($H25)=$AV$5,MONTH($H25)<=BA$6),$S25,0)) -> 56361012 | BB25: =+IF(YEAR($H25)<$AV$5,$S25,IF(AND(YEAR($H25)=$AV$5,MONTH($H25)<=BB$6),$S25,0)) -> 56361012 | BC25: =+IF(YEAR($H25)<$AV$5,$S25,IF(AND(YEAR($H25)=$AV$5,MONTH($H25)<=BC$6),$S25,0)) -> 56361012 | ... BG25: =+IF(YEAR($H25)<$AV$5,$S25,IF(AND(YEAR($H25)=$AV$5,MONTH($H25)<=BG$6),$S25,0)) -> 56361012 | BH25: =+SUM(AV25:BG25) -> 6.7633214e+08 | BI25: =+AU25-BH25 -> 1.2173979e+10 | BJ25: =+IF(YEAR($H25)<$BJ$5,$S25,IF(AND(YEAR($H25)=$BJ$5,MONTH($H25)<=BJ$6),$S25,0)) -> 56361012 | BK25: =+IF(YEAR($H25)<$BJ$5,$S25,IF(AND(YEAR($H25)=$BJ$5,MONTH($H25)<=BK$6),$S25,0)) -> 56361012 | BL25: =+IF(YEAR($H25)<$BJ$5,$S25,IF(AND(YEAR($H25)=$BJ$5,MONTH($H25)<=BL$6),$S25,0)) -> 56361012 | BM25: =+IF(YEAR($H25)<$BJ$5,$S25,IF(AND(YEAR($H25)=$BJ$5,MONTH($H25)<=BM$6),$S25,0)) -> 56361012 | BN25: =+IF(YEAR($H25)<$BJ$5,$S25,IF(AND(YEAR($H25)=$BJ$5,MONTH($H25)<=BN$6),$S25,0)) -> 56361012 | BO25: =+IF(YEAR($H25)<$BJ$5,$S25,IF(AND(YEAR($H25)=$BJ$5,MONTH($H25)<=BO$6),$S25,0)) -> 56361012 | BP25: =+IF(YEAR($H25)<$BJ$5,$S25,IF(AND(YEAR($H25)=$BJ$5,MONTH($H25)<=BP$6),$S25,0)) -> 56361012 | BQ25: =+IF(YEAR($H25)<$BJ$5,$S25,IF(AND(YEAR($H25)=$BJ$5,MONTH($H25)<=BQ$6),$S25,0)) -> 56361012 | ... BU25: =+IF(YEAR($H25)<$BJ$5,$S25,IF(AND(YEAR($H25)=$BJ$5,MONTH($H25)<=BU$6),$S25,0)) -> 56361012 | BV25: =+SUM(BJ25:BU25) -> 6.7633214e+08 | BW25: =+BI25-BV25 -> 1.1497646e+10 | BX25: =+$S25 -> 56361012 | BY25: =+$S25 -> 56361012 | BZ25: =+$S25 -> 56361012 | CA25: =+$S25 -> 56361012 | CB25: =+$S25 -> 56361012 | CC25: =+$S25 -> 56361012 | CD25: =+$S25 -> 56361012 | CE25: =+$S25 -> 56361012 | ... CI25: =+$S25 -> 56361012 | CJ25: =+SUM(BX25:CI25) -> 6.7633214e+08 | CK25: =+BW25-CJ25 -> 1.0821314e+10 | CM25: =VLOOKUP($E25,'Capex TT 2020'!$D$5:$F$35,3,0) -> #N/A | CN25: =IFERROR(VLOOKUP($E25,'Capex TT 2021'!$D$5:$F$35,3,0),0) -> 13526642799 | CO25: =VLOOKUP($E25,'Capex TT 2022'!$D$5:$F$35,3,0) -> #N/A | CP25: =VLOOKUP($E25,'Capex TT 2023'!$D$5:$F$35,3,0) -> #N/A
A26: 6274.4 | B26: Chung | C26: =YEAR(H26) -> 2022 | D26: Z21110A | E26: 103000003 | F26: Nhà xe công nhân | G26: 44866 | H26: 44866 | I26: 36 | J26: 1001202000 | K26: Hành chánh nhân sự | M26: =+LEFT(N26,4) -> 6424 | N26: 6424001901 | R26: 110029564 | S26: 3056376.8 | T26: =$S26 -> 3056376.8 | U26: =$S26 -> 3056376.8 | V26: =$S26 -> 3056376.8 | W26: =$S26 -> 3056376.8 | X26: =$S26 -> 3056376.8 | Y26: =$S26 -> 3056376.8 | Z26: =$S26 -> 3056376.8 | AA26: =$S26 -> 3056376.8 | ... AE26: =$S26 -> 3056376.8 | AF26: =+SUM(T26:AE26) -> 36676521 | AG26: 0 | AH26: =$S26 -> 3056376.8 | AI26: =$S26 -> 3056376.8 | AJ26: =$S26 -> 3056376.8 | AK26: =$S26 -> 3056376.8 | AL26: =$S26 -> 3056376.8 | AM26: =$S26 -> 3056376.8 | AN26: =$S26 -> 3056376.8 | AO26: =$S26 -> 3056376.8 | ... AS26: =$S26 -> 3056376.8 | AT26: =+SUM(AH26:AS26) -> 36676521 | AU26: 0 | AV26: =+IF(YEAR($H26)<$AV$5,$S26,IF(AND(YEAR($H26)=$AV$5,MONTH($H26)<=AV$6),$S26,0)) -> 3056376.8 | AW26: =+IF(YEAR($H26)<$AV$5,$S26,IF(AND(YEAR($H26)=$AV$5,MONTH($H26)<=AW$6),$S26,0)) -> 3056376.8 | AX26: =+IF(YEAR($H26)<$AV$5,$S26,IF(AND(YEAR($H26)=$AV$5,MONTH($H26)<=AX$6),$S26,0)) -> 3056376.8 | AY26: =+IF(YEAR($H26)<$AV$5,$S26,IF(AND(YEAR($H26)=$AV$5,MONTH($H26)<=AY$6),$S26,0)) -> 3056376.8 | AZ26: =+IF(YEAR($H26)<$AV$5,$S26,IF(AND(YEAR($H26)=$AV$5,MONTH($H26)<=AZ$6),$S26,0)) -> 3056376.8 | BA26: =+IF(YEAR($H26)<$AV$5,$S26,IF(AND(YEAR($H26)=$AV$5,MONTH($H26)<=BA$6),$S26,0)) -> 3056376.8 | BB26: =+IF(YEAR($H26)<$AV$5,$S26,IF(AND(YEAR($H26)=$AV$5,MONTH($H26)<=BB$6),$S26,0)) -> 3056376.8 | BC26: =+IF(YEAR($H26)<$AV$5,$S26,IF(AND(YEAR($H26)=$AV$5,MONTH($H26)<=BC$6),$S26,0)) -> 3056376.8 | ... BG26: =+IF(YEAR($H26)<$AV$5,$S26,IF(AND(YEAR($H26)=$AV$5,MONTH($H26)<=BG$6),$S26,0)) -> 3056376.8 | BH26: =+SUM(AV26:BG26) -> 36676521 | BI26: =+R26-BH26 -> 73353043 | BJ26: =+IF(YEAR($H26)<$BJ$5,$S26,IF(AND(YEAR($H26)=$BJ$5,MONTH($H26)<=BJ$6),$S26,0)) -> 3056376.8 | BK26: =+IF(YEAR($H26)<$BJ$5,$S26,IF(AND(YEAR($H26)=$BJ$5,MONTH($H26)<=BK$6),$S26,0)) -> 3056376.8 | BL26: =+IF(YEAR($H26)<$BJ$5,$S26,IF(AND(YEAR($H26)=$BJ$5,MONTH($H26)<=BL$6),$S26,0)) -> 3056376.8 | BM26: =+IF(YEAR($H26)<$BJ$5,$S26,IF(AND(YEAR($H26)=$BJ$5,MONTH($H26)<=BM$6),$S26,0)) -> 3056376.8 | BN26: =+IF(YEAR($H26)<$BJ$5,$S26,IF(AND(YEAR($H26)=$BJ$5,MONTH($H26)<=BN$6),$S26,0)) -> 3056376.8 | BO26: =+IF(YEAR($H26)<$BJ$5,$S26,IF(AND(YEAR($H26)=$BJ$5,MONTH($H26)<=BO$6),$S26,0)) -> 3056376.8 | BP26: =+IF(YEAR($H26)<$BJ$5,$S26,IF(AND(YEAR($H26)=$BJ$5,MONTH($H26)<=BP$6),$S26,0)) -> 3056376.8 | BQ26: =+IF(YEAR($H26)<$BJ$5,$S26,IF(AND(YEAR($H26)=$BJ$5,MONTH($H26)<=BQ$6),$S26,0)) -> 3056376.8 | ... BU26: =+IF(YEAR($H26)<$BJ$5,$S26,IF(AND(YEAR($H26)=$BJ$5,MONTH($H26)<=BU$6),$S26,0)) -> 3056376.8 | BV26: =+SUM(BJ26:BU26) -> 36676521 | BW26: =+BI26-BV26 -> 36676521 | BX26: =+$S26 -> 3056376.8 | BY26: =+$S26 -> 3056376.8 | BZ26: =+$S26 -> 3056376.8 | CA26: =+$S26 -> 3056376.8 | CB26: =+$S26 -> 3056376.8 | CC26: =+$S26 -> 3056376.8 | CD26: =+$S26 -> 3056376.8 | CE26: =+$S26 -> 3056376.8 | ... CI26: =+$S26 -> 3056376.8 | CJ26: =+SUM(BX26:CI26) -> 36676521 | CK26: =+BW26-CJ26 -> 0 | CM26: =VLOOKUP($E26,'Capex TT 2020'!$D$5:$F$35,3,0) -> #N/A | CN26: =IFERROR(VLOOKUP($E26,'Capex TT 2021'!$D$5:$F$35,3,0),0) -> 0 | CO26: =VLOOKUP($E26,'Capex TT 2022'!$D$5:$F$35,3,0) -> #N/A | CP26: =VLOOKUP($E26,'Capex TT 2023'!$D$5:$F$35,3,0) -> #N/A
A27: 6274.4 | B27: Chung | C27: =YEAR(H27) -> 2023 | D27: Z21110A | E27: 103000004 | F27: Văn phòng F02 | G27: 44916 | H27: 44927 | I27: 240 | J27: 1001202000 | K27: Hành chánh nhân sự | M27: =+LEFT(N27,4) -> 6424 | N27: 6424001901 | R27: 2569997827 | S27: 10708324 | T27: =$S27 -> 10708324 | U27: =$S27 -> 10708324 | V27: =$S27 -> 10708324 | W27: =$S27 -> 10708324 | X27: =$S27 -> 10708324 | Y27: =$S27 -> 10708324 | Z27: =$S27 -> 10708324 | AA27: =$S27 -> 10708324 | ... AE27: =$S27 -> 10708324 | AF27: =+SUM(T27:AE27) -> 1.2849989e+08 | AG27: 0 | AH27: =$S27 -> 10708324 | AI27: =$S27 -> 10708324 | AJ27: =$S27 -> 10708324 | AK27: =$S27 -> 10708324 | AL27: =$S27 -> 10708324 | AM27: =$S27 -> 10708324 | AN27: =$S27 -> 10708324 | AO27: =$S27 -> 10708324 | ... AS27: =$S27 -> 10708324 | AT27: =+SUM(AH27:AS27) -> 1.2849989e+08 | AU27: 0 | AV27: =+IF(YEAR($H27)<$AV$5,$S27,IF(AND(YEAR($H27)=$AV$5,MONTH($H27)<=AV$6),$S27,0)) -> 10708324 | AW27: =+IF(YEAR($H27)<$AV$5,$S27,IF(AND(YEAR($H27)=$AV$5,MONTH($H27)<=AW$6),$S27,0)) -> 10708324 | AX27: =+IF(YEAR($H27)<$AV$5,$S27,IF(AND(YEAR($H27)=$AV$5,MONTH($H27)<=AX$6),$S27,0)) -> 10708324 | AY27: =+IF(YEAR($H27)<$AV$5,$S27,IF(AND(YEAR($H27)=$AV$5,MONTH($H27)<=AY$6),$S27,0)) -> 10708324 | AZ27: =+IF(YEAR($H27)<$AV$5,$S27,IF(AND(YEAR($H27)=$AV$5,MONTH($H27)<=AZ$6),$S27,0)) -> 10708324 | BA27: =+IF(YEAR($H27)<$AV$5,$S27,IF(AND(YEAR($H27)=$AV$5,MONTH($H27)<=BA$6),$S27,0)) -> 10708324 | BB27: =+IF(YEAR($H27)<$AV$5,$S27,IF(AND(YEAR($H27)=$AV$5,MONTH($H27)<=BB$6),$S27,0)) -> 10708324 | BC27: =+IF(YEAR($H27)<$AV$5,$S27,IF(AND(YEAR($H27)=$AV$5,MONTH($H27)<=BC$6),$S27,0)) -> 10708324 | ... BG27: =+IF(YEAR($H27)<$AV$5,$S27,IF(AND(YEAR($H27)=$AV$5,MONTH($H27)<=BG$6),$S27,0)) -> 10708324 | BH27: =+SUM(AV27:BG27) -> 1.2849989e+08 | BI27: 0 | BJ27: =+IF(YEAR($H27)<$BJ$5,$S27,IF(AND(YEAR($H27)=$BJ$5,MONTH($H27)<=BJ$6),$S27,0)) -> 10708324 | BK27: =+IF(YEAR($H27)<$BJ$5,$S27,IF(AND(YEAR($H27)=$BJ$5,MONTH($H27)<=BK$6),$S27,0)) -> 10708324 | BL27: =+IF(YEAR($H27)<$BJ$5,$S27,IF(AND(YEAR($H27)=$BJ$5,MONTH($H27)<=BL$6),$S27,0)) -> 10708324 | BM27: =+IF(YEAR($H27)<$BJ$5,$S27,IF(AND(YEAR($H27)=$BJ$5,MONTH($H27)<=BM$6),$S27,0)) -> 10708324 | BN27: =+IF(YEAR($H27)<$BJ$5,$S27,IF(AND(YEAR($H27)=$BJ$5,MONTH($H27)<=BN$6),$S27,0)) -> 10708324 | BO27: =+IF(YEAR($H27)<$BJ$5,$S27,IF(AND(YEAR($H27)=$BJ$5,MONTH($H27)<=BO$6),$S27,0)) -> 10708324 | BP27: =+IF(YEAR($H27)<$BJ$5,$S27,IF(AND(YEAR($H27)=$BJ$5,MONTH($H27)<=BP$6),$S27,0)) -> 10708324 | BQ27: =+IF(YEAR($H27)<$BJ$5,$S27,IF(AND(YEAR($H27)=$BJ$5,MONTH($H27)<=BQ$6),$S27,0)) -> 10708324 | ... BU27: =+IF(YEAR($H27)<$BJ$5,$S27,IF(AND(YEAR($H27)=$BJ$5,MONTH($H27)<=BU$6),$S27,0)) -> 10708324 | BV27: =+SUM(BJ27:BU27) -> 1.2849989e+08 | BW27: =+R27-BV27 -> 2.4414979e+09 | BX27: =+$S27 -> 10708324 | BY27: =+$S27 -> 10708324 | BZ27: =+$S27 -> 10708324 | CA27: =+$S27 -> 10708324 | CB27: =+$S27 -> 10708324 | CC27: =+$S27 -> 10708324 | CD27: =+$S27 -> 10708324 | CE27: =+$S27 -> 10708324 | ... CI27: =+$S27 -> 10708324 | CJ27: =+SUM(BX27:CI27) -> 1.2849989e+08 | CK27: =+BW27-CJ27 -> 2.312998e+09 | CM27: =VLOOKUP($E27,'Capex TT 2020'!$D$5:$F$35,3,0) -> #N/A | CN27: =IFERROR(VLOOKUP($E27,'Capex TT 2021'!$D$5:$F$35,3,0),0) -> 0 | CO27: =VLOOKUP($E27,'Capex TT 2022'!$D$5:$F$35,3,0) -> #N/A | CP27: =VLOOKUP($E27,'Capex TT 2023'!$D$5:$F$35,3,0) -> #N/A
A28: 6274.4 | B28: Chung | C28: =YEAR(H28) -> 2021 | D28: Z21120P | E28: 104000068 | F28: Hệ thống xử lý nước thải ChengWoen | G28: 44417 | H28: 44417 | I28: 120 | J28: 1001602101 | K28: Chuyền rửa vảy PET-W | M28: =+LEFT(N28,4) -> 6274 | N28: 6274001903 | R28: 46492741763 | S28: 3.8743951e+08 | T28: =$S28 -> 3.8743951e+08 | U28: =$S28 -> 3.8743951e+08 | V28: =$S28 -> 3.8743951e+08 | W28: =$S28 -> 3.8743951e+08 | X28: =$S28 -> 3.8743951e+08 | Y28: =$S28 -> 3.8743951e+08 | Z28: =$S28 -> 3.8743951e+08 | AA28: =$S28 -> 3.8743951e+08 | ... AE28: =$S28 -> 3.8743951e+08 | AF28: =+SUM(T28:AE28) -> 4.6492742e+09 | AG28: 0 | AH28: =$S28 -> 3.8743951e+08 | AI28: =$S28 -> 3.8743951e+08 | AJ28: =$S28 -> 3.8743951e+08 | AK28: =$S28 -> 3.8743951e+08 | AL28: =$S28 -> 3.8743951e+08 | AM28: =$S28 -> 3.8743951e+08 | AN28: =$S28 -> 3.8743951e+08 | AO28: =$S28 -> 3.8743951e+08 | ... AS28: =$S28 -> 3.8743951e+08 | AT28: =+SUM(AH28:AS28) -> 4.6492742e+09 | AU28: =+R28-AT28 -> 4.1843468e+10 | AV28: =+IF(YEAR($H28)<$AV$5,$S28,IF(AND(YEAR($H28)=$AV$5,MONTH($H28)<=AV$6),$S28,0)) -> 3.8743951e+08 | AW28: =+IF(YEAR($H28)<$AV$5,$S28,IF(AND(YEAR($H28)=$AV$5,MONTH($H28)<=AW$6),$S28,0)) -> 3.8743951e+08 | AX28: =+IF(YEAR($H28)<$AV$5,$S28,IF(AND(YEAR($H28)=$AV$5,MONTH($H28)<=AX$6),$S28,0)) -> 3.8743951e+08 | AY28: =+IF(YEAR($H28)<$AV$5,$S28,IF(AND(YEAR($H28)=$AV$5,MONTH($H28)<=AY$6),$S28,0)) -> 3.8743951e+08 | AZ28: =+IF(YEAR($H28)<$AV$5,$S28,IF(AND(YEAR($H28)=$AV$5,MONTH($H28)<=AZ$6),$S28,0)) -> 3.8743951e+08 | BA28: =+IF(YEAR($H28)<$AV$5,$S28,IF(AND(YEAR($H28)=$AV$5,MONTH($H28)<=BA$6),$S28,0)) -> 3.8743951e+08 | BB28: =+IF(YEAR($H28)<$AV$5,$S28,IF(AND(YEAR($H28)=$AV$5,MONTH($H28)<=BB$6),$S28,0)) -> 3.8743951e+08 | BC28: =+IF(YEAR($H28)<$AV$5,$S28,IF(AND(YEAR($H28)=$AV$5,MONTH($H28)<=BC$6),$S28,0)) -> 3.8743951e+08 | ... BG28: =+IF(YEAR($H28)<$AV$5,$S28,IF(AND(YEAR($H28)=$AV$5,MONTH($H28)<=BG$6),$S28,0)) -> 3.8743951e+08 | BH28: =+SUM(AV28:BG28) -> 4.6492742e+09 | BI28: =+AU28-BH28 -> 3.7194193e+10 | BJ28: =+IF(YEAR($H28)<$BJ$5,$S28,IF(AND(YEAR($H28)=$BJ$5,MONTH($H28)<=BJ$6),$S28,0)) -> 3.8743951e+08 | BK28: =+IF(YEAR($H28)<$BJ$5,$S28,IF(AND(YEAR($H28)=$BJ$5,MONTH($H28)<=BK$6),$S28,0)) -> 3.8743951e+08 | BL28: =+IF(YEAR($H28)<$BJ$5,$S28,IF(AND(YEAR($H28)=$BJ$5,MONTH($H28)<=BL$6),$S28,0)) -> 3.8743951e+08 | BM28: =+IF(YEAR($H28)<$BJ$5,$S28,IF(AND(YEAR($H28)=$BJ$5,MONTH($H28)<=BM$6),$S28,0)) -> 3.8743951e+08 | BN28: =+IF(YEAR($H28)<$BJ$5,$S28,IF(AND(YEAR($H28)=$BJ$5,MONTH($H28)<=BN$6),$S28,0)) -> 3.8743951e+08 | BO28: =+IF(YEAR($H28)<$BJ$5,$S28,IF(AND(YEAR($H28)=$BJ$5,MONTH($H28)<=BO$6),$S28,0)) -> 3.8743951e+08 | BP28: =+IF(YEAR($H28)<$BJ$5,$S28,IF(AND(YEAR($H28)=$BJ$5,MONTH($H28)<=BP$6),$S28,0)) -> 3.8743951e+08 | BQ28: =+IF(YEAR($H28)<$BJ$5,$S28,IF(AND(YEAR($H28)=$BJ$5,MONTH($H28)<=BQ$6),$S28,0)) -> 3.8743951e+08 | ... BU28: =+IF(YEAR($H28)<$BJ$5,$S28,IF(AND(YEAR($H28)=$BJ$5,MONTH($H28)<=BU$6),$S28,0)) -> 3.8743951e+08 | BV28: =+SUM(BJ28:BU28) -> 4.6492742e+09 | BW28: =+BI28-BV28 -> 3.2544919e+10 | BX28: =+$S28 -> 3.8743951e+08 | BY28: =+$S28 -> 3.8743951e+08 | BZ28: =+$S28 -> 3.8743951e+08 | CA28: =+$S28 -> 3.8743951e+08 | CB28: =+$S28 -> 3.8743951e+08 | CC28: =+$S28 -> 3.8743951e+08 | CD28: =+$S28 -> 3.8743951e+08 | CE28: =+$S28 -> 3.8743951e+08 | ... CI28: =+$S28 -> 3.8743951e+08 | CJ28: =+SUM(BX28:CI28) -> 4.6492742e+09 | CK28: =+BW28-CJ28 -> 2.7895645e+10 | CM28: =VLOOKUP($E28,'Capex TT 2020'!$D$5:$F$35,3,0) -> #N/A | CN28: =IFERROR(VLOOKUP($E28,'Capex TT 2021'!$D$5:$F$35,3,0),0) -> 46273512763 | CO28: =VLOOKUP($E28,'Capex TT 2022'!$D$5:$F$35,3,0) -> #N/A | CP28: =VLOOKUP($E28,'Capex TT 2023'!$D$5:$F$35,3,0) -> #N/A
A29: 6274.4 | B29: Chung | C29: =YEAR(H29) -> 2021 | D29: Z211201P | E29: 104600020 | F29: Đường ống nén khí xưởng 03 | G29: 44439 | H29: 44438 | I29: 120 | J29: 1001602000 | K29: Xưởng sản xuất PET | M29: =+LEFT(N29,4) -> 6274 | N29: 6274001906 | R29: 758031567 | S29: 6316929.7 | T29: =$S29 -> 6316929.7 | U29: =$S29 -> 6316929.7 | V29: =$S29 -> 6316929.7 | W29: =$S29 -> 6316929.7 | X29: =$S29 -> 6316929.7 | Y29: =$S29 -> 6316929.7 | Z29: =$S29 -> 6316929.7 | AA29: =$S29 -> 6316929.7 | ... AE29: =$S29 -> 6316929.7 | AF29: =+SUM(T29:AE29) -> 75803157 | AG29: 0 | AH29: =$S29 -> 6316929.7 | AI29: =$S29 -> 6316929.7 | AJ29: =$S29 -> 6316929.7 | AK29: =$S29 -> 6316929.7 | AL29: =$S29 -> 6316929.7 | AM29: =$S29 -> 6316929.7 | AN29: =$S29 -> 6316929.7 | AO29: =$S29 -> 6316929.7 | ... AS29: =$S29 -> 6316929.7 | AT29: =+SUM(AH29:AS29) -> 75803157 | AU29: =+R29-AT29 -> 6.8222841e+08 | AV29: =+IF(YEAR($H29)<$AV$5,$S29,IF(AND(YEAR($H29)=$AV$5,MONTH($H29)<=AV$6),$S29,0)) -> 6316929.7 | AW29: =+IF(YEAR($H29)<$AV$5,$S29,IF(AND(YEAR($H29)=$AV$5,MONTH($H29)<=AW$6),$S29,0)) -> 6316929.7 | AX29: =+IF(YEAR($H29)<$AV$5,$S29,IF(AND(YEAR($H29)=$AV$5,MONTH($H29)<=AX$6),$S29,0)) -> 6316929.7 | AY29: =+IF(YEAR($H29)<$AV$5,$S29,IF(AND(YEAR($H29)=$AV$5,MONTH($H29)<=AY$6),$S29,0)) -> 6316929.7 | AZ29: =+IF(YEAR($H29)<$AV$5,$S29,IF(AND(YEAR($H29)=$AV$5,MONTH($H29)<=AZ$6),$S29,0)) -> 6316929.7 | BA29: =+IF(YEAR($H29)<$AV$5,$S29,IF(AND(YEAR($H29)=$AV$5,MONTH($H29)<=BA$6),$S29,0)) -> 6316929.7 | BB29: =+IF(YEAR($H29)<$AV$5,$S29,IF(AND(YEAR($H29)=$AV$5,MONTH($H29)<=BB$6),$S29,0)) -> 6316929.7 | BC29: =+IF(YEAR($H29)<$AV$5,$S29,IF(AND(YEAR($H29)=$AV$5,MONTH($H29)<=BC$6),$S29,0)) -> 6316929.7 | ... BG29: =+IF(YEAR($H29)<$AV$5,$S29,IF(AND(YEAR($H29)=$AV$5,MONTH($H29)<=BG$6),$S29,0)) -> 6316929.7 | BH29: =+SUM(AV29:BG29) -> 75803157 | BI29: =+AU29-BH29 -> 6.0642525e+08 | BJ29: =+IF(YEAR($H29)<$BJ$5,$S29,IF(AND(YEAR($H29)=$BJ$5,MONTH($H29)<=BJ$6),$S29,0)) -> 6316929.7 | BK29: =+IF(YEAR($H29)<$BJ$5,$S29,IF(AND(YEAR($H29)=$BJ$5,MONTH($H29)<=BK$6),$S29,0)) -> 6316929.7 | BL29: =+IF(YEAR($H29)<$BJ$5,$S29,IF(AND(YEAR($H29)=$BJ$5,MONTH($H29)<=BL$6),$S29,0)) -> 6316929.7 | BM29: =+IF(YEAR($H29)<$BJ$5,$S29,IF(AND(YEAR($H29)=$BJ$5,MONTH($H29)<=BM$6),$S29,0)) -> 6316929.7 | BN29: =+IF(YEAR($H29)<$BJ$5,$S29,IF(AND(YEAR($H29)=$BJ$5,MONTH($H29)<=BN$6),$S29,0)) -> 6316929.7 | BO29: =+IF(YEAR($H29)<$BJ$5,$S29,IF(AND(YEAR($H29)=$BJ$5,MONTH($H29)<=BO$6),$S29,0)) -> 6316929.7 | BP29: =+IF(YEAR($H29)<$BJ$5,$S29,IF(AND(YEAR($H29)=$BJ$5,MONTH($H29)<=BP$6),$S29,0)) -> 6316929.7 | BQ29: =+IF(YEAR($H29)<$BJ$5,$S29,IF(AND(YEAR($H29)=$BJ$5,MONTH($H29)<=BQ$6),$S29,0)) -> 6316929.7 | ... BU29: =+IF(YEAR($H29)<$BJ$5,$S29,IF(AND(YEAR($H29)=$BJ$5,MONTH($H29)<=BU$6),$S29,0)) -> 6316929.7 | BV29: =+SUM(BJ29:BU29) -> 75803157 | BW29: =+BI29-BV29 -> 5.306221e+08 | BX29: =+$S29 -> 6316929.7 | BY29: =+$S29 -> 6316929.7 | BZ29: =+$S29 -> 6316929.7 | CA29: =+$S29 -> 6316929.7 | CB29: =+$S29 -> 6316929.7 | CC29: =+$S29 -> 6316929.7 | CD29: =+$S29 -> 6316929.7 | CE29: =+$S29 -> 6316929.7 | ... CI29: =+$S29 -> 6316929.7 | CJ29: =+SUM(BX29:CI29) -> 75803157 | CK29: =+BW29-CJ29 -> 4.5481894e+08 | CM29: =VLOOKUP($E29,'Capex TT 2020'!$D$5:$F$35,3,0) -> #N/A | CN29: =IFERROR(VLOOKUP($E29,'Capex TT 2021'!$D$5:$F$35,3,0),0) -> 758031567 | CO29: =VLOOKUP($E29,'Capex TT 2022'!$D$5:$F$35,3,0) -> #N/A | CP29: =VLOOKUP($E29,'Capex TT 2023'!$D$5:$F$35,3,0) -> #N/A
A30: 6274.4 | B30: Chung | C30: =YEAR(H30) -> 2021 | D30: Z211201P | E30: 104600021 | F30: Hệ thống cách nhiệt bể nước ngầm, Hệ thống PCCC | G30: 44439 | H30: 44438 | I30: 120 | J30: 1001602000 | K30: Xưởng sản xuất PET | M30: =+LEFT(N30,4) -> 6274 | N30: 6274001906 | R30: 3682105850 | S30: 30684215 | T30: =$S30 -> 30684215 | U30: =$S30 -> 30684215 | V30: =$S30 -> 30684215 | W30: =$S30 -> 30684215 | X30: =$S30 -> 30684215 | Y30: =$S30 -> 30684215 | Z30: =$S30 -> 30684215 | AA30: =$S30 -> 30684215 | ... AE30: =$S30 -> 30684215 | AF30: =+SUM(T30:AE30) -> 3.6821059e+08 | AG30: 0 | AH30: =$S30 -> 30684215 | AI30: =$S30 -> 30684215 | AJ30: =$S30 -> 30684215 | AK30: =$S30 -> 30684215 | AL30: =$S30 -> 30684215 | AM30: =$S30 -> 30684215 | AN30: =$S30 -> 30684215 | AO30: =$S30 -> 30684215 | ... AS30: =$S30 -> 30684215 | AT30: =+SUM(AH30:AS30) -> 3.6821059e+08 | AU30: =+R30-AT30 -> 3313895265 | AV30: =+IF(YEAR($H30)<$AV$5,$S30,IF(AND(YEAR($H30)=$AV$5,MONTH($H30)<=AV$6),$S30,0)) -> 30684215 | AW30: =+IF(YEAR($H30)<$AV$5,$S30,IF(AND(YEAR($H30)=$AV$5,MONTH($H30)<=AW$6),$S30,0)) -> 30684215 | AX30: =+IF(YEAR($H30)<$AV$5,$S30,IF(AND(YEAR($H30)=$AV$5,MONTH($H30)<=AX$6),$S30,0)) -> 30684215 | AY30: =+IF(YEAR($H30)<$AV$5,$S30,IF(AND(YEAR($H30)=$AV$5,MONTH($H30)<=AY$6),$S30,0)) -> 30684215 | AZ30: =+IF(YEAR($H30)<$AV$5,$S30,IF(AND(YEAR($H30)=$AV$5,MONTH($H30)<=AZ$6),$S30,0)) -> 30684215 | BA30: =+IF(YEAR($H30)<$AV$5,$S30,IF(AND(YEAR($H30)=$AV$5,MONTH($H30)<=BA$6),$S30,0)) -> 30684215 | BB30: =+IF(YEAR($H30)<$AV$5,$S30,IF(AND(YEAR($H30)=$AV$5,MONTH($H30)<=BB$6),$S30,0)) -> 30684215 | BC30: =+IF(YEAR($H30)<$AV$5,$S30,IF(AND(YEAR($H30)=$AV$5,MONTH($H30)<=BC$6),$S30,0)) -> 30684215 | ... BG30: =+IF(YEAR($H30)<$AV$5,$S30,IF(AND(YEAR($H30)=$AV$5,MONTH($H30)<=BG$6),$S30,0)) -> 30684215 | BH30: =+SUM(AV30:BG30) -> 3.6821059e+08 | BI30: =+AU30-BH30 -> 2945684680 | BJ30: =+IF(YEAR($H30)<$BJ$5,$S30,IF(AND(YEAR($H30)=$BJ$5,MONTH($H30)<=BJ$6),$S30,0)) -> 30684215 | BK30: =+IF(YEAR($H30)<$BJ$5,$S30,IF(AND(YEAR($H30)=$BJ$5,MONTH($H30)<=BK$6),$S30,0)) -> 30684215 | BL30: =+IF(YEAR($H30)<$BJ$5,$S30,IF(AND(YEAR($H30)=$BJ$5,MONTH($H30)<=BL$6),$S30,0)) -> 30684215 | BM30: =+IF(YEAR($H30)<$BJ$5,$S30,IF(AND(YEAR($H30)=$BJ$5,MONTH($H30)<=BM$6),$S30,0)) -> 30684215 | BN30: =+IF(YEAR($H30)<$BJ$5,$S30,IF(AND(YEAR($H30)=$BJ$5,MONTH($H30)<=BN$6),$S30,0)) -> 30684215 | BO30: =+IF(YEAR($H30)<$BJ$5,$S30,IF(AND(YEAR($H30)=$BJ$5,MONTH($H30)<=BO$6),$S30,0)) -> 30684215 | BP30: =+IF(YEAR($H30)<$BJ$5,$S30,IF(AND(YEAR($H30)=$BJ$5,MONTH($H30)<=BP$6),$S30,0)) -> 30684215 | BQ30: =+IF(YEAR($H30)<$BJ$5,$S30,IF(AND(YEAR($H30)=$BJ$5,MONTH($H30)<=BQ$6),$S30,0)) -> 30684215 | ... BU30: =+IF(YEAR($H30)<$BJ$5,$S30,IF(AND(YEAR($H30)=$BJ$5,MONTH($H30)<=BU$6),$S30,0)) -> 30684215 | BV30: =+SUM(BJ30:BU30) -> 3.6821059e+08 | BW30: =+BI30-BV30 -> 2577474095 | BX30: =+$S30 -> 30684215 | BY30: =+$S30 -> 30684215 | BZ30: =+$S30 -> 30684215 | CA30: =+$S30 -> 30684215 | CB30: =+$S30 -> 30684215 | CC30: =+$S30 -> 30684215 | CD30: =+$S30 -> 30684215 | CE30: =+$S30 -> 30684215 | ... CI30: =+$S30 -> 30684215 | CJ30: =+SUM(BX30:CI30) -> 3.6821059e+08 | CK30: =+BW30-CJ30 -> 2209263510 | CM30: =VLOOKUP($E30,'Capex TT 2020'!$D$5:$F$35,3,0) -> #N/A | CN30: =IFERROR(VLOOKUP($E30,'Capex TT 2021'!$D$5:$F$35,3,0),0) -> 3682105850 | CO30: =VLOOKUP($E30,'Capex TT 2022'!$D$5:$F$35,3,0) -> #N/A | CP30: =VLOOKUP($E30,'Capex TT 2023'!$D$5:$F$35,3,0) -> #N/A
A31: 6274.4 | B31: Chung | C31: =YEAR(H31) -> 2021 | D31: Z211201P | E31: 104600022 | F31: Hệ thống Điện, cấp thoát Nước xưởng 03 | G31: 44439 | H31: 44438 | I31: 120 | J31: 1001602000 | K31: Xưởng sản xuất PET | M31: =+LEFT(N31,4) -> 6274 | N31: 6274001906 | R31: 1729306981 | S31: 14410892 | T31: =$S31 -> 14410892 | U31: =$S31 -> 14410892 | V31: =$S31 -> 14410892 | W31: =$S31 -> 14410892 | X31: =$S31 -> 14410892 | Y31: =$S31 -> 14410892 | Z31: =$S31 -> 14410892 | AA31: =$S31 -> 14410892 | ... AE31: =$S31 -> 14410892 | AF31: =+SUM(T31:AE31) -> 1.729307e+08 | AG31: 0 | AH31: =$S31 -> 14410892 | AI31: =$S31 -> 14410892 | AJ31: =$S31 -> 14410892 | AK31: =$S31 -> 14410892 | AL31: =$S31 -> 14410892 | AM31: =$S31 -> 14410892 | AN31: =$S31 -> 14410892 | AO31: =$S31 -> 14410892 | ... AS31: =$S31 -> 14410892 | AT31: =+SUM(AH31:AS31) -> 1.729307e+08 | AU31: =+R31-AT31 -> 1.5563763e+09 | AV31: =+IF(YEAR($H31)<$AV$5,$S31,IF(AND(YEAR($H31)=$AV$5,MONTH($H31)<=AV$6),$S31,0)) -> 14410892 | AW31: =+IF(YEAR($H31)<$AV$5,$S31,IF(AND(YEAR($H31)=$AV$5,MONTH($H31)<=AW$6),$S31,0)) -> 14410892 | AX31: =+IF(YEAR($H31)<$AV$5,$S31,IF(AND(YEAR($H31)=$AV$5,MONTH($H31)<=AX$6),$S31,0)) -> 14410892 | AY31: =+IF(YEAR($H31)<$AV$5,$S31,IF(AND(YEAR($H31)=$AV$5,MONTH($H31)<=AY$6),$S31,0)) -> 14410892 | AZ31: =+IF(YEAR($H31)<$AV$5,$S31,IF(AND(YEAR($H31)=$AV$5,MONTH($H31)<=AZ$6),$S31,0)) -> 14410892 | BA31: =+IF(YEAR($H31)<$AV$5,$S31,IF(AND(YEAR($H31)=$AV$5,MONTH($H31)<=BA$6),$S31,0)) -> 14410892 | BB31: =+IF(YEAR($H31)<$AV$5,$S31,IF(AND(YEAR($H31)=$AV$5,MONTH($H31)<=BB$6),$S31,0)) -> 14410892 | BC31: =+IF(YEAR($H31)<$AV$5,$S31,IF(AND(YEAR($H31)=$AV$5,MONTH($H31)<=BC$6),$S31,0)) -> 14410892 | ... BG31: =+IF(YEAR($H31)<$AV$5,$S31,IF(AND(YEAR($H31)=$AV$5,MONTH($H31)<=BG$6),$S31,0)) -> 14410892 | BH31: =+SUM(AV31:BG31) -> 1.729307e+08 | BI31: =+AU31-BH31 -> 1.3834456e+09 | BJ31: =+IF(YEAR($H31)<$BJ$5,$S31,IF(AND(YEAR($H31)=$BJ$5,MONTH($H31)<=BJ$6),$S31,0)) -> 14410892 | BK31: =+IF(YEAR($H31)<$BJ$5,$S31,IF(AND(YEAR($H31)=$BJ$5,MONTH($H31)<=BK$6),$S31,0)) -> 14410892 | BL31: =+IF(YEAR($H31)<$BJ$5,$S31,IF(AND(YEAR($H31)=$BJ$5,MONTH($H31)<=BL$6),$S31,0)) -> 14410892 | BM31: =+IF(YEAR($H31)<$BJ$5,$S31,IF(AND(YEAR($H31)=$BJ$5,MONTH($H31)<=BM$6),$S31,0)) -> 14410892 | BN31: =+IF(YEAR($H31)<$BJ$5,$S31,IF(AND(YEAR($H31)=$BJ$5,MONTH($H31)<=BN$6),$S31,0)) -> 14410892 | BO31: =+IF(YEAR($H31)<$BJ$5,$S31,IF(AND(YEAR($H31)=$BJ$5,MONTH($H31)<=BO$6),$S31,0)) -> 14410892 | BP31: =+IF(YEAR($H31)<$BJ$5,$S31,IF(AND(YEAR($H31)=$BJ$5,MONTH($H31)<=BP$6),$S31,0)) -> 14410892 | BQ31: =+IF(YEAR($H31)<$BJ$5,$S31,IF(AND(YEAR($H31)=$BJ$5,MONTH($H31)<=BQ$6),$S31,0)) -> 14410892 | ... BU31: =+IF(YEAR($H31)<$BJ$5,$S31,IF(AND(YEAR($H31)=$BJ$5,MONTH($H31)<=BU$6),$S31,0)) -> 14410892 | BV31: =+SUM(BJ31:BU31) -> 1.729307e+08 | BW31: =+BI31-BV31 -> 1.2105149e+09 | BX31: =+$S31 -> 14410892 | BY31: =+$S31 -> 14410892 | BZ31: =+$S31 -> 14410892 | CA31: =+$S31 -> 14410892 | CB31: =+$S31 -> 14410892 | CC31: =+$S31 -> 14410892 | CD31: =+$S31 -> 14410892 | CE31: =+$S31 -> 14410892 | ... CI31: =+$S31 -> 14410892 | CJ31: =+SUM(BX31:CI31) -> 1.729307e+08 | CK31: =+BW31-CJ31 -> 1.0375842e+09 | CM31: =VLOOKUP($E31,'Capex TT 2020'!$D$5:$F$35,3,0) -> #N/A | CN31: =IFERROR(VLOOKUP($E31,'Capex TT 2021'!$D$5:$F$35,3,0),0) -> 1729306981 | CO31: =VLOOKUP($E31,'Capex TT 2022'!$D$5:$F$35,3,0) -> #N/A | CP31: =VLOOKUP($E31,'Capex TT 2023'!$D$5:$F$35,3,0) -> #N/A
A32: 6274.4 | B32: Chung | C32: =YEAR(H32) -> 2021 | D32: Z211201P | E32: 104600026 | F32: Hệ thống điện xưởng 03 | G32: 44439 | H32: 44438 | I32: 120 | J32: 1001602000 | K32: Xưởng sản xuất PET | M32: =+LEFT(N32,4) -> 6274 | N32: 6274001906 | R32: 1931331475 | S32: 16094429 | T32: =$S32 -> 16094429 | U32: =$S32 -> 16094429 | V32: =$S32 -> 16094429 | W32: =$S32 -> 16094429 | X32: =$S32 -> 16094429 | Y32: =$S32 -> 16094429 | Z32: =$S32 -> 16094429 | AA32: =$S32 -> 16094429 | ... AE32: =$S32 -> 16094429 | AF32: =+SUM(T32:AE32) -> 1.9313315e+08 | AG32: 0 | AH32: =$S32 -> 16094429 | AI32: =$S32 -> 16094429 | AJ32: =$S32 -> 16094429 | AK32: =$S32 -> 16094429 | AL32: =$S32 -> 16094429 | AM32: =$S32 -> 16094429 | AN32: =$S32 -> 16094429 | AO32: =$S32 -> 16094429 | ... AS32: =$S32 -> 16094429 | AT32: =+SUM(AH32:AS32) -> 1.9313315e+08 | AU32: =+R32-AT32 -> 1.7381983e+09 | AV32: =+IF(YEAR($H32)<$AV$5,$S32,IF(AND(YEAR($H32)=$AV$5,MONTH($H32)<=AV$6),$S32,0)) -> 16094429 | AW32: =+IF(YEAR($H32)<$AV$5,$S32,IF(AND(YEAR($H32)=$AV$5,MONTH($H32)<=AW$6),$S32,0)) -> 16094429 | AX32: =+IF(YEAR($H32)<$AV$5,$S32,IF(AND(YEAR($H32)=$AV$5,MONTH($H32)<=AX$6),$S32,0)) -> 16094429 | AY32: =+IF(YEAR($H32)<$AV$5,$S32,IF(AND(YEAR($H32)=$AV$5,MONTH($H32)<=AY$6),$S32,0)) -> 16094429 | AZ32: =+IF(YEAR($H32)<$AV$5,$S32,IF(AND(YEAR($H32)=$AV$5,MONTH($H32)<=AZ$6),$S32,0)) -> 16094429 | BA32: =+IF(YEAR($H32)<$AV$5,$S32,IF(AND(YEAR($H32)=$AV$5,MONTH($H32)<=BA$6),$S32,0)) -> 16094429 | BB32: =+IF(YEAR($H32)<$AV$5,$S32,IF(AND(YEAR($H32)=$AV$5,MONTH($H32)<=BB$6),$S32,0)) -> 16094429 | BC32: =+IF(YEAR($H32)<$AV$5,$S32,IF(AND(YEAR($H32)=$AV$5,MONTH($H32)<=BC$6),$S32,0)) -> 16094429 | ... BG32: =+IF(YEAR($H32)<$AV$5,$S32,IF(AND(YEAR($H32)=$AV$5,MONTH($H32)<=BG$6),$S32,0)) -> 16094429 | BH32: =+SUM(AV32:BG32) -> 1.9313315e+08 | BI32: =+AU32-BH32 -> 1545065180 | BJ32: =+IF(YEAR($H32)<$BJ$5,$S32,IF(AND(YEAR($H32)=$BJ$5,MONTH($H32)<=BJ$6),$S32,0)) -> 16094429 | BK32: =+IF(YEAR($H32)<$BJ$5,$S32,IF(AND(YEAR($H32)=$BJ$5,MONTH($H32)<=BK$6),$S32,0)) -> 16094429 | BL32: =+IF(YEAR($H32)<$BJ$5,$S32,IF(AND(YEAR($H32)=$BJ$5,MONTH($H32)<=BL$6),$S32,0)) -> 16094429 | BM32: =+IF(YEAR($H32)<$BJ$5,$S32,IF(AND(YEAR($H32)=$BJ$5,MONTH($H32)<=BM$6),$S32,0)) -> 16094429 | BN32: =+IF(YEAR($H32)<$BJ$5,$S32,IF(AND(YEAR($H32)=$BJ$5,MONTH($H32)<=BN$6),$S32,0)) -> 16094429 | BO32: =+IF(YEAR($H32)<$BJ$5,$S32,IF(AND(YEAR($H32)=$BJ$5,MONTH($H32)<=BO$6),$S32,0)) -> 16094429 | BP32: =+IF(YEAR($H32)<$BJ$5,$S32,IF(AND(YEAR($H32)=$BJ$5,MONTH($H32)<=BP$6),$S32,0)) -> 16094429 | BQ32: =+IF(YEAR($H32)<$BJ$5,$S32,IF(AND(YEAR($H32)=$BJ$5,MONTH($H32)<=BQ$6),$S32,0)) -> 16094429 | ... BU32: =+IF(YEAR($H32)<$BJ$5,$S32,IF(AND(YEAR($H32)=$BJ$5,MONTH($H32)<=BU$6),$S32,0)) -> 16094429 | BV32: =+SUM(BJ32:BU32) -> 1.9313315e+08 | BW32: =+BI32-BV32 -> 1.351932e+09 | BX32: =+$S32 -> 16094429 | BY32: =+$S32 -> 16094429 | BZ32: =+$S32 -> 16094429 | CA32: =+$S32 -> 16094429 | CB32: =+$S32 -> 16094429 | CC32: =+$S32 -> 16094429 | CD32: =+$S32 -> 16094429 | CE32: =+$S32 -> 16094429 | ... CI32: =+$S32 -> 16094429 | CJ32: =+SUM(BX32:CI32) -> 1.9313315e+08 | CK32: =+BW32-CJ32 -> 1158798885 | CM32: =VLOOKUP($E32,'Capex TT 2020'!$D$5:$F$35,3,0) -> #N/A | CN32: =IFERROR(VLOOKUP($E32,'Capex TT 2021'!$D$5:$F$35,3,0),0) -> 1931331475 | CO32: =VLOOKUP($E32,'Capex TT 2022'!$D$5:$F$35,3,0) -> #N/A | CP32: =VLOOKUP($E32,'Capex TT 2023'!$D$5:$F$35,3,0) -> #N/A
A33: 6274.4 | B33: Chung | C33: =YEAR(H33) -> 2022 | D33: Z211201P | E33: 104600048 | F33: Hệ thống PCCC xưởng F02 | G33: 44804 | H33: 44788 | I33: 120 | J33: 1001604000 | K33: Khối SX - Xưởng 2 | M33: =+LEFT(N33,4) -> 6274 | N33: 6274001906 | R33: 1467082739 | S33: 12225689 | T33: =$S33 -> 12225689 | U33: =$S33 -> 12225689 | V33: =$S33 -> 12225689 | W33: =$S33 -> 12225689 | X33: =$S33 -> 12225689 | Y33: =$S33 -> 12225689 | Z33: =$S33 -> 12225689 | AA33: =$S33 -> 12225689 | ... AE33: =$S33 -> 12225689 | AF33: =+SUM(T33:AE33) -> 1.4670827e+08 | AG33: 0 | AH33: =$S33 -> 12225689 | AI33: =$S33 -> 12225689 | AJ33: =$S33 -> 12225689 | AK33: =$S33 -> 12225689 | AL33: =$S33 -> 12225689 | AM33: =$S33 -> 12225689 | AN33: =$S33 -> 12225689 | AO33: =$S33 -> 12225689 | ... AS33: =$S33 -> 12225689 | AT33: =+SUM(AH33:AS33) -> 1.4670827e+08 | AU33: 0 | AV33: =+IF(YEAR($H33)<$AV$5,$S33,IF(AND(YEAR($H33)=$AV$5,MONTH($H33)<=AV$6),$S33,0)) -> 12225689 | AW33: =+IF(YEAR($H33)<$AV$5,$S33,IF(AND(YEAR($H33)=$AV$5,MONTH($H33)<=AW$6),$S33,0)) -> 12225689 | AX33: =+IF(YEAR($H33)<$AV$5,$S33,IF(AND(YEAR($H33)=$AV$5,MONTH($H33)<=AX$6),$S33,0)) -> 12225689 | AY33: =+IF(YEAR($H33)<$AV$5,$S33,IF(AND(YEAR($H33)=$AV$5,MONTH($H33)<=AY$6),$S33,0)) -> 12225689 | AZ33: =+IF(YEAR($H33)<$AV$5,$S33,IF(AND(YEAR($H33)=$AV$5,MONTH($H33)<=AZ$6),$S33,0)) -> 12225689 | BA33: =+IF(YEAR($H33)<$AV$5,$S33,IF(AND(YEAR($H33)=$AV$5,MONTH($H33)<=BA$6),$S33,0)) -> 12225689 | BB33: =+IF(YEAR($H33)<$AV$5,$S33,IF(AND(YEAR($H33)=$AV$5,MONTH($H33)<=BB$6),$S33,0)) -> 12225689 | BC33: =+IF(YEAR($H33)<$AV$5,$S33,IF(AND(YEAR($H33)=$AV$5,MONTH($H33)<=BC$6),$S33,0)) -> 12225689 | ... BG33: =+IF(YEAR($H33)<$AV$5,$S33,IF(AND(YEAR($H33)=$AV$5,MONTH($H33)<=BG$6),$S33,0)) -> 12225689 | BH33: =+SUM(AV33:BG33) -> 1.4670827e+08 | BI33: =+R33-BH33 -> 1.3203745e+09 | BJ33: =+IF(YEAR($H33)<$BJ$5,$S33,IF(AND(YEAR($H33)=$BJ$5,MONTH($H33)<=BJ$6),$S33,0)) -> 12225689 | BK33: =+IF(YEAR($H33)<$BJ$5,$S33,IF(AND(YEAR($H33)=$BJ$5,MONTH($H33)<=BK$6),$S33,0)) -> 12225689 | BL33: =+IF(YEAR($H33)<$BJ$5,$S33,IF(AND(YEAR($H33)=$BJ$5,MONTH($H33)<=BL$6),$S33,0)) -> 12225689 | BM33: =+IF(YEAR($H33)<$BJ$5,$S33,IF(AND(YEAR($H33)=$BJ$5,MONTH($H33)<=BM$6),$S33,0)) -> 12225689 | BN33: =+IF(YEAR($H33)<$BJ$5,$S33,IF(AND(YEAR($H33)=$BJ$5,MONTH($H33)<=BN$6),$S33,0)) -> 12225689 | BO33: =+IF(YEAR($H33)<$BJ$5,$S33,IF(AND(YEAR($H33)=$BJ$5,MONTH($H33)<=BO$6),$S33,0)) -> 12225689 | BP33: =+IF(YEAR($H33)<$BJ$5,$S33,IF(AND(YEAR($H33)=$BJ$5,MONTH($H33)<=BP$6),$S33,0)) -> 12225689 | BQ33: =+IF(YEAR($H33)<$BJ$5,$S33,IF(AND(YEAR($H33)=$BJ$5,MONTH($H33)<=BQ$6),$S33,0)) -> 12225689 | ... BU33: =+IF(YEAR($H33)<$BJ$5,$S33,IF(AND(YEAR($H33)=$BJ$5,MONTH($H33)<=BU$6),$S33,0)) -> 12225689 | BV33: =+SUM(BJ33:BU33) -> 1.4670827e+08 | BW33: =+BI33-BV33 -> 1.1736662e+09 | BX33: =+$S33 -> 12225689 | BY33: =+$S33 -> 12225689 | BZ33: =+$S33 -> 12225689 | CA33: =+$S33 -> 12225689 | CB33: =+$S33 -> 12225689 | CC33: =+$S33 -> 12225689 | CD33: =+$S33 -> 12225689 | CE33: =+$S33 -> 12225689 | ... CI33: =+$S33 -> 12225689 | CJ33: =+SUM(BX33:CI33) -> 1.4670827e+08 | CK33: =+BW33-CJ33 -> 1.0269579e+09 | CM33: =VLOOKUP($E33,'Capex TT 2020'!$D$5:$F$35,3,0) -> #N/A | CN33: =IFERROR(VLOOKUP($E33,'Capex TT 2021'!$D$5:$F$35,3,0),0) -> 0 | CO33: =VLOOKUP($E33,'Capex TT 2022'!$D$5:$F$35,3,0) -> #N/A | CP33: =VLOOKUP($E33,'Capex TT 2023'!$D$5:$F$35,3,0) -> #N/A
A34: 6274.4 | B34: Chung | C34: =YEAR(H34) -> 2022 | D34: Z211201P | E34: 104600051 | F34: Hệ thống PCCC xưởng F03 | G34: 44834 | H34: 44835 | I34: 72 | J34: 1001602000 | K34: Xưởng sản xuất PET | M34: =+LEFT(N34,4) -> 6274 | N34: 6274001906 | R34: 70421390 | S34: 978074.86 | T34: =$S34 -> 978074.86 | U34: =$S34 -> 978074.86 | V34: =$S34 -> 978074.86 | W34: =$S34 -> 978074.86 | X34: =$S34 -> 978074.86 | Y34: =$S34 -> 978074.86 | Z34: =$S34 -> 978074.86 | AA34: =$S34 -> 978074.86 | ... AE34: =$S34 -> 978074.86 | AF34: =+SUM(T34:AE34) -> 11736898 | AG34: 0 | AH34: =$S34 -> 978074.86 | AI34: =$S34 -> 978074.86 | AJ34: =$S34 -> 978074.86 | AK34: =$S34 -> 978074.86 | AL34: =$S34 -> 978074.86 | AM34: =$S34 -> 978074.86 | AN34: =$S34 -> 978074.86 | AO34: =$S34 -> 978074.86 | ... AS34: =$S34 -> 978074.86 | AT34: =+SUM(AH34:AS34) -> 11736898 | AU34: 0 | AV34: =+IF(YEAR($H34)<$AV$5,$S34,IF(AND(YEAR($H34)=$AV$5,MONTH($H34)<=AV$6),$S34,0)) -> 978074.86 | AW34: =+IF(YEAR($H34)<$AV$5,$S34,IF(AND(YEAR($H34)=$AV$5,MONTH($H34)<=AW$6),$S34,0)) -> 978074.86 | AX34: =+IF(YEAR($H34)<$AV$5,$S34,IF(AND(YEAR($H34)=$AV$5,MONTH($H34)<=AX$6),$S34,0)) -> 978074.86 | AY34: =+IF(YEAR($H34)<$AV$5,$S34,IF(AND(YEAR($H34)=$AV$5,MONTH($H34)<=AY$6),$S34,0)) -> 978074.86 | AZ34: =+IF(YEAR($H34)<$AV$5,$S34,IF(AND(YEAR($H34)=$AV$5,MONTH($H34)<=AZ$6),$S34,0)) -> 978074.86 | BA34: =+IF(YEAR($H34)<$AV$5,$S34,IF(AND(YEAR($H34)=$AV$5,MONTH($H34)<=BA$6),$S34,0)) -> 978074.86 | BB34: =+IF(YEAR($H34)<$AV$5,$S34,IF(AND(YEAR($H34)=$AV$5,MONTH($H34)<=BB$6),$S34,0)) -> 978074.86 | BC34: =+IF(YEAR($H34)<$AV$5,$S34,IF(AND(YEAR($H34)=$AV$5,MONTH($H34)<=BC$6),$S34,0)) -> 978074.86 | ... BG34: =+IF(YEAR($H34)<$AV$5,$S34,IF(AND(YEAR($H34)=$AV$5,MONTH($H34)<=BG$6),$S34,0)) -> 978074.86 | BH34: =+SUM(AV34:BG34) -> 11736898 | BI34: =+R34-BH34 -> 58684492 | BJ34: =+IF(YEAR($H34)<$BJ$5,$S34,IF(AND(YEAR($H34)=$BJ$5,MONTH($H34)<=BJ$6),$S34,0)) -> 978074.86 | BK34: =+IF(YEAR($H34)<$BJ$5,$S34,IF(AND(YEAR($H34)=$BJ$5,MONTH($H34)<=BK$6),$S34,0)) -> 978074.86 | BL34: =+IF(YEAR($H34)<$BJ$5,$S34,IF(AND(YEAR($H34)=$BJ$5,MONTH($H34)<=BL$6),$S34,0)) -> 978074.86 | BM34: =+IF(YEAR($H34)<$BJ$5,$S34,IF(AND(YEAR($H34)=$BJ$5,MONTH($H34)<=BM$6),$S34,0)) -> 978074.86 | BN34: =+IF(YEAR($H34)<$BJ$5,$S34,IF(AND(YEAR($H34)=$BJ$5,MONTH($H34)<=BN$6),$S34,0)) -> 978074.86 | BO34: =+IF(YEAR($H34)<$BJ$5,$S34,IF(AND(YEAR($H34)=$BJ$5,MONTH($H34)<=BO$6),$S34,0)) -> 978074.86 | BP34: =+IF(YEAR($H34)<$BJ$5,$S34,IF(AND(YEAR($H34)=$BJ$5,MONTH($H34)<=BP$6),$S34,0)) -> 978074.86 | BQ34: =+IF(YEAR($H34)<$BJ$5,$S34,IF(AND(YEAR($H34)=$BJ$5,MONTH($H34)<=BQ$6),$S34,0)) -> 978074.86 | ... BU34: =+IF(YEAR($H34)<$BJ$5,$S34,IF(AND(YEAR($H34)=$BJ$5,MONTH($H34)<=BU$6),$S34,0)) -> 978074.86 | BV34: =+SUM(BJ34:BU34) -> 11736898 | BW34: =+BI34-BV34 -> 46947593 | BX34: =+$S34 -> 978074.86 | BY34: =+$S34 -> 978074.86 | BZ34: =+$S34 -> 978074.86 | CA34: =+$S34 -> 978074.86 | CB34: =+$S34 -> 978074.86 | CC34: =+$S34 -> 978074.86 | CD34: =+$S34 -> 978074.86 | CE34: =+$S34 -> 978074.86 | ... CI34: =+$S34 -> 978074.86 | CJ34: =+SUM(BX34:CI34) -> 11736898 | CK34: =+BW34-CJ34 -> 35210695 | CM34: =VLOOKUP($E34,'Capex TT 2020'!$D$5:$F$35,3,0) -> #N/A | CN34: =IFERROR(VLOOKUP($E34,'Capex TT 2021'!$D$5:$F$35,3,0),0) -> 0 | CO34: =VLOOKUP($E34,'Capex TT 2022'!$D$5:$F$35,3,0) -> #N/A | CP34: =VLOOKUP($E34,'Capex TT 2023'!$D$5:$F$35,3,0) -> #N/A
A35: 6274.4 | B35: Chung | C35: =YEAR(H35) -> 2022 | D35: Z211201P | E35: 104600052 | F35: Nâng trục 16-18 xưởng F03 | G35: 44834 | H35: 44835 | I35: 120 | J35: 1001602000 | K35: Xưởng sản xuất PET | M35: =+LEFT(N35,4) -> 6274 | N35: 6274001906 | R35: 928112057 | S35: 7734267.1 | T35: =$S35 -> 7734267.1 | U35: =$S35 -> 7734267.1 | V35: =$S35 -> 7734267.1 | W35: =$S35 -> 7734267.1 | X35: =$S35 -> 7734267.1 | Y35: =$S35 -> 7734267.1 | Z35: =$S35 -> 7734267.1 | AA35: =$S35 -> 7734267.1 | ... AE35: =$S35 -> 7734267.1 | AF35: =+SUM(T35:AE35) -> 92811206 | AG35: 0 | AH35: =$S35 -> 7734267.1 | AI35: =$S35 -> 7734267.1 | AJ35: =$S35 -> 7734267.1 | AK35: =$S35 -> 7734267.1 | AL35: =$S35 -> 7734267.1 | AM35: =$S35 -> 7734267.1 | AN35: =$S35 -> 7734267.1 | AO35: =$S35 -> 7734267.1 | ... AS35: =$S35 -> 7734267.1 | AT35: =+SUM(AH35:AS35) -> 92811206 | AU35: 0 | AV35: =+IF(YEAR($H35)<$AV$5,$S35,IF(AND(YEAR($H35)=$AV$5,MONTH($H35)<=AV$6),$S35,0)) -> 7734267.1 | AW35: =+IF(YEAR($H35)<$AV$5,$S35,IF(AND(YEAR($H35)=$AV$5,MONTH($H35)<=AW$6),$S35,0)) -> 7734267.1 | AX35: =+IF(YEAR($H35)<$AV$5,$S35,IF(AND(YEAR($H35)=$AV$5,MONTH($H35)<=AX$6),$S35,0)) -> 7734267.1 | AY35: =+IF(YEAR($H35)<$AV$5,$S35,IF(AND(YEAR($H35)=$AV$5,MONTH($H35)<=AY$6),$S35,0)) -> 7734267.1 | AZ35: =+IF(YEAR($H35)<$AV$5,$S35,IF(AND(YEAR($H35)=$AV$5,MONTH($H35)<=AZ$6),$S35,0)) -> 7734267.1 | BA35: =+IF(YEAR($H35)<$AV$5,$S35,IF(AND(YEAR($H35)=$AV$5,MONTH($H35)<=BA$6),$S35,0)) -> 7734267.1 | BB35: =+IF(YEAR($H35)<$AV$5,$S35,IF(AND(YEAR($H35)=$AV$5,MONTH($H35)<=BB$6),$S35,0)) -> 7734267.1 | BC35: =+IF(YEAR($H35)<$AV$5,$S35,IF(AND(YEAR($H35)=$AV$5,MONTH($H35)<=BC$6),$S35,0)) -> 7734267.1 | ... BG35: =+IF(YEAR($H35)<$AV$5,$S35,IF(AND(YEAR($H35)=$AV$5,MONTH($H35)<=BG$6),$S35,0)) -> 7734267.1 | BH35: =+SUM(AV35:BG35) -> 92811206 | BI35: =+R35-BH35 -> 8.3530085e+08 | BJ35: =+IF(YEAR($H35)<$BJ$5,$S35,IF(AND(YEAR($H35)=$BJ$5,MONTH($H35)<=BJ$6),$S35,0)) -> 7734267.1 | BK35: =+IF(YEAR($H35)<$BJ$5,$S35,IF(AND(YEAR($H35)=$BJ$5,MONTH($H35)<=BK$6),$S35,0)) -> 7734267.1 | BL35: =+IF(YEAR($H35)<$BJ$5,$S35,IF(AND(YEAR($H35)=$BJ$5,MONTH($H35)<=BL$6),$S35,0)) -> 7734267.1 | BM35: =+IF(YEAR($H35)<$BJ$5,$S35,IF(AND(YEAR($H35)=$BJ$5,MONTH($H35)<=BM$6),$S35,0)) -> 7734267.1 | BN35: =+IF(YEAR($H35)<$BJ$5,$S35,IF(AND(YEAR($H35)=$BJ$5,MONTH($H35)<=BN$6),$S35,0)) -> 7734267.1 | BO35: =+IF(YEAR($H35)<$BJ$5,$S35,IF(AND(YEAR($H35)=$BJ$5,MONTH($H35)<=BO$6),$S35,0)) -> 7734267.1 | BP35: =+IF(YEAR($H35)<$BJ$5,$S35,IF(AND(YEAR($H35)=$BJ$5,MONTH($H35)<=BP$6),$S35,0)) -> 7734267.1 | BQ35: =+IF(YEAR($H35)<$BJ$5,$S35,IF(AND(YEAR($H35)=$BJ$5,MONTH($H35)<=BQ$6),$S35,0)) -> 7734267.1 | ... BU35: =+IF(YEAR($H35)<$BJ$5,$S35,IF(AND(YEAR($H35)=$BJ$5,MONTH($H35)<=BU$6),$S35,0)) -> 7734267.1 | BV35: =+SUM(BJ35:BU35) -> 92811206 | BW35: =+BI35-BV35 -> 7.4248965e+08 | BX35: =+$S35 -> 7734267.1 | BY35: =+$S35 -> 7734267.1 | BZ35: =+$S35 -> 7734267.1 | CA35: =+$S35 -> 7734267.1 | CB35: =+$S35 -> 7734267.1 | CC35: =+$S35 -> 7734267.1 | CD35: =+$S35 -> 7734267.1 | CE35: =+$S35 -> 7734267.1 | ... CI35: =+$S35 -> 7734267.1 | CJ35: =+SUM(BX35:CI35) -> 92811206 | CK35: =+BW35-CJ35 -> 6.4967844e+08 | CM35: =VLOOKUP($E35,'Capex TT 2020'!$D$5:$F$35,3,0) -> #N/A | CN35: =IFERROR(VLOOKUP($E35,'Capex TT 2021'!$D$5:$F$35,3,0),0) -> 0 | CO35: =VLOOKUP($E35,'Capex TT 2022'!$D$5:$F$35,3,0) -> #N/A | CP35: =VLOOKUP($E35,'Capex TT 2023'!$D$5:$F$35,3,0) -> #N/A
A36: 6274.4 | B36: Chung | C36: =YEAR(H36) -> 2023 | D36: Z211201P | E36: 104600062 | F36: Hệ thống PCCC xưởng F04 | G36: 44915 | H36: 44927 | I36: 96 | J36: 1001605000 | K36: Khối SX - Xưởng 4 | M36: =+LEFT(N36,4) -> 6274 | N36: 6274001906 | R36: 941765419 | S36: 9810056.4 | T36: =$S36 -> 9810056.4 | U36: =$S36 -> 9810056.4 | V36: =$S36 -> 9810056.4 | W36: =$S36 -> 9810056.4 | X36: =$S36 -> 9810056.4 | Y36: =$S36 -> 9810056.4 | Z36: =$S36 -> 9810056.4 | AA36: =$S36 -> 9810056.4 | ... AE36: =$S36 -> 9810056.4 | AF36: =+SUM(T36:AE36) -> 1.1772068e+08 | AG36: 0 | AH36: =$S36 -> 9810056.4 | AI36: =$S36 -> 9810056.4 | AJ36: =$S36 -> 9810056.4 | AK36: =$S36 -> 9810056.4 | AL36: =$S36 -> 9810056.4 | AM36: =$S36 -> 9810056.4 | AN36: =$S36 -> 9810056.4 | AO36: =$S36 -> 9810056.4 | ... AS36: =$S36 -> 9810056.4 | AT36: =+SUM(AH36:AS36) -> 1.1772068e+08 | AU36: 0 | AV36: =+IF(YEAR($H36)<$AV$5,$S36,IF(AND(YEAR($H36)=$AV$5,MONTH($H36)<=AV$6),$S36,0)) -> 9810056.4 | AW36: =+IF(YEAR($H36)<$AV$5,$S36,IF(AND(YEAR($H36)=$AV$5,MONTH($H36)<=AW$6),$S36,0)) -> 9810056.4 | AX36: =+IF(YEAR($H36)<$AV$5,$S36,IF(AND(YEAR($H36)=$AV$5,MONTH($H36)<=AX$6),$S36,0)) -> 9810056.4 | AY36: =+IF(YEAR($H36)<$AV$5,$S36,IF(AND(YEAR($H36)=$AV$5,MONTH($H36)<=AY$6),$S36,0)) -> 9810056.4 | AZ36: =+IF(YEAR($H36)<$AV$5,$S36,IF(AND(YEAR($H36)=$AV$5,MONTH($H36)<=AZ$6),$S36,0)) -> 9810056.4 | BA36: =+IF(YEAR($H36)<$AV$5,$S36,IF(AND(YEAR($H36)=$AV$5,MONTH($H36)<=BA$6),$S36,0)) -> 9810056.4 | BB36: =+IF(YEAR($H36)<$AV$5,$S36,IF(AND(YEAR($H36)=$AV$5,MONTH($H36)<=BB$6),$S36,0)) -> 9810056.4 | BC36: =+IF(YEAR($H36)<$AV$5,$S36,IF(AND(YEAR($H36)=$AV$5,MONTH($H36)<=BC$6),$S36,0)) -> 9810056.4 | ... BG36: =+IF(YEAR($H36)<$AV$5,$S36,IF(AND(YEAR($H36)=$AV$5,MONTH($H36)<=BG$6),$S36,0)) -> 9810056.4 | BH36: =+SUM(AV36:BG36) -> 1.1772068e+08 | BI36: 0 | BJ36: =+IF(YEAR($H36)<$BJ$5,$S36,IF(AND(YEAR($H36)=$BJ$5,MONTH($H36)<=BJ$6),$S36,0)) -> 9810056.4 | BK36: =+IF(YEAR($H36)<$BJ$5,$S36,IF(AND(YEAR($H36)=$BJ$5,MONTH($H36)<=BK$6),$S36,0)) -> 9810056.4 | BL36: =+IF(YEAR($H36)<$BJ$5,$S36,IF(AND(YEAR($H36)=$BJ$5,MONTH($H36)<=BL$6),$S36,0)) -> 9810056.4 | BM36: =+IF(YEAR($H36)<$BJ$5,$S36,IF(AND(YEAR($H36)=$BJ$5,MONTH($H36)<=BM$6),$S36,0)) -> 9810056.4 | BN36: =+IF(YEAR($H36)<$BJ$5,$S36,IF(AND(YEAR($H36)=$BJ$5,MONTH($H36)<=BN$6),$S36,0)) -> 9810056.4 | BO36: =+IF(YEAR($H36)<$BJ$5,$S36,IF(AND(YEAR($H36)=$BJ$5,MONTH($H36)<=BO$6),$S36,0)) -> 9810056.4 | BP36: =+IF(YEAR($H36)<$BJ$5,$S36,IF(AND(YEAR($H36)=$BJ$5,MONTH($H36)<=BP$6),$S36,0)) -> 9810056.4 | BQ36: =+IF(YEAR($H36)<$BJ$5,$S36,IF(AND(YEAR($H36)=$BJ$5,MONTH($H36)<=BQ$6),$S36,0)) -> 9810056.4 | ... BU36: =+IF(YEAR($H36)<$BJ$5,$S36,IF(AND(YEAR($H36)=$BJ$5,MONTH($H36)<=BU$6),$S36,0)) -> 9810056.4 | BV36: =+SUM(BJ36:BU36) -> 1.1772068e+08 | BW36: =+R36-BV36 -> 8.2404474e+08 | BX36: =+$S36 -> 9810056.4 | BY36: =+$S36 -> 9810056.4 | BZ36: =+$S36 -> 9810056.4 | CA36: =+$S36 -> 9810056.4 | CB36: =+$S36 -> 9810056.4 | CC36: =+$S36 -> 9810056.4 | CD36: =+$S36 -> 9810056.4 | CE36: =+$S36 -> 9810056.4 | ... CI36: =+$S36 -> 9810056.4 | CJ36: =+SUM(BX36:CI36) -> 1.1772068e+08 | CK36: =+BW36-CJ36 -> 7.0632406e+08 | CM36: =VLOOKUP($E36,'Capex TT 2020'!$D$5:$F$35,3,0) -> #N/A | CN36: =IFERROR(VLOOKUP($E36,'Capex TT 2021'!$D$5:$F$35,3,0),0) -> 0 | CO36: =VLOOKUP($E36,'Capex TT 2022'!$D$5:$F$35,3,0) -> #N/A | CP36: =VLOOKUP($E36,'Capex TT 2023'!$D$5:$F$35,3,0) -> #N/A
